Workbook

Sheet Filtered result
A1: =IFERROR(__xludf.DUMMYFUNCTION("FILTER(Aggregation!A:BQ,Aggregation!H:H<>"""") "),"Account ID") -> Account ID | B1: =IFERROR(__xludf.DUMMYFUNCTION("""COMPUTED_VALUE"""),"Partner name") -> Partner name | C1: =IFERROR(__xludf.DUMMYFUNCTION("""COMPUTED_VALUE"""),"CSM") -> CSM | D1: =IFERROR(__xludf.DUMMYFUNCTION("""COMPUTED_VALUE"""),"Region") -> Region | E1: =IFERROR(__xludf.DUMMYFUNCTION("""COMPUTED_VALUE"""),"Country") -> Country | F1: =IFERROR(__xludf.DUMMYFUNCTION("""COMPUTED_VALUE"""),"Partner Segment") -> Partner Segment | G1: =IFERROR(__xludf.DUMMYFUNCTION("""COMPUTED_VALUE"""),"Business Plan Setup and Acceptance - Result") -> Business Plan Setup and Acceptance - Result | H1: =IFERROR(__xludf.DUMMYFUNCTION("""COMPUTED_VALUE"""),"Business Plan Setup and Acceptance - Target") -> Business Plan Setup and Acceptance - Target | I1: =IFERROR(__xludf.DUMMYFUNCTION("""COMPUTED_VALUE"""),"Business Plan Setup and Acceptance - Achievement") -> Business Plan Setup and Acceptance - Achievement | J1: =IFERROR(__xludf.DUMMYFUNCTION("""COMPUTED_VALUE"""),"Sales IN Revenues vs Sales target - Result") -> Sales IN Revenues vs Sales target - Result | K1: =IFERROR(__xludf.DUMMYFUNCTION("""COMPUTED_VALUE"""),"Sales IN Revenues vs Sales target - Target") -> Sales IN Revenues vs Sales target - Target | L1: =IFERROR(__xludf.DUMMYFUNCTION("""COMPUTED_VALUE"""),"Sales IN Revenues vs Sales target - Achievement") -> Sales IN Revenues vs Sales target - Achievement | M1: =IFERROR(__xludf.DUMMYFUNCTION("""COMPUTED_VALUE"""),"Certifications achievements vs recommended - Result") -> Certifications achievements vs recommended - Result | N1: =IFERROR(__xludf.DUMMYFUNCTION("""COMPUTED_VALUE"""),"Certifications achievements vs recommended - Target") -> Certifications achievements vs recommended - Target | O1: =IFERROR(__xludf.DUMMYFUNCTION("""COMPUTED_VALUE"""),"Certifications achievements vs recommended - Achievement") -> Certifications achievements vs recommended - Achievement | P1: =IFERROR(__xludf.DUMMYFUNCTION("""COMPUTED_VALUE"""),"Communications - Certifications achievements vs recommended - Result") -> Communications - Certifications achievements vs recommended - Result | Q1: =IFERROR(__xludf.DUMMYFUNCTION("""COMPUTED_VALUE"""),"Communications - Certifications achievements vs recommended - Result") -> Communications - Certifications achievements vs recommended - Result | R1: =IFERROR(__xludf.DUMMYFUNCTION("""COMPUTED_VALUE"""),"Communications - Certifications achievements vs recommended - Achievement") -> Communications - Certifications achievements vs recommended - Achievement | S1: =IFERROR(__xludf.DUMMYFUNCTION("""COMPUTED_VALUE"""),"Networking - Certifications achievements vs recommended - Result") -> Networking - Certifications achievements vs recommended - Result | T1: =IFERROR(__xludf.DUMMYFUNCTION("""COMPUTED_VALUE"""),"Networking - Certifications achievements vs recommended - Result") -> Networking - Certifications achievements vs recommended - Result | U1: =IFERROR(__xludf.DUMMYFUNCTION("""COMPUTED_VALUE"""),"Networking - Certifications achievements vs recommended - Achievement") -> Networking - Certifications achievements vs recommended - Achievement | V1: =IFERROR(__xludf.DUMMYFUNCTION("""COMPUTED_VALUE"""),"Marketing Plan (extract summary from SF) - Result") -> Marketing Plan (extract summary from SF) - Result | W1: =IFERROR(__xludf.DUMMYFUNCTION("""COMPUTED_VALUE"""),"Marketing Plan (extract summary from SF) - Target") -> Marketing Plan (extract summary from SF) - Target | X1: =IFERROR(__xludf.DUMMYFUNCTION("""COMPUTED_VALUE"""),"Marketing Plan (extract summary from SF) - Achievement") -> Marketing Plan (extract summary from SF) - Achievement | Y1: =IFERROR(__xludf.DUMMYFUNCTION("""COMPUTED_VALUE"""),"Quarterly Pipeline vs Target Pipeline - Result - Q1") -> Quarterly Pipeline vs Target Pipeline - Result - Q1 | Z1: =IFERROR(__xludf.DUMMYFUNCTION("""COMPUTED_VALUE"""),"Quarterly Pipeline vs Target Pipeline - Target - Q1") -> Quarterly Pipeline vs Target Pipeline - Target - Q1 | AA1: =IFERROR(__xludf.DUMMYFUNCTION("""COMPUTED_VALUE"""),"Quarterly Pipeline vs Target Pipeline - Achievement - Q1") -> Quarterly Pipeline vs Target Pipeline - Achievement - Q1 | AB1: =IFERROR(__xludf.DUMMYFUNCTION("""COMPUTED_VALUE"""),"Quarterly Pipeline vs Target Pipeline - Result - Q2") -> Quarterly Pipeline vs Target Pipeline - Result - Q2 | AC1: =IFERROR(__xludf.DUMMYFUNCTION("""COMPUTED_VALUE"""),"Quarterly Pipeline vs Target Pipeline - Target - Q2") -> Quarterly Pipeline vs Target Pipeline - Target - Q2 | AD1: =IFERROR(__xludf.DUMMYFUNCTION("""COMPUTED_VALUE"""),"Quarterly Pipeline vs Target Pipeline - Achievement - Q2") -> Quarterly Pipeline vs Target Pipeline - Achievement - Q2 | AE1: =IFERROR(__xludf.DUMMYFUNCTION("""COMPUTED_VALUE"""),"Quarterly Pipeline vs Target Pipeline - Result - Q3") -> Quarterly Pipeline vs Target Pipeline - Result - Q3 | AF1: =IFERROR(__xludf.DUMMYFUNCTION("""COMPUTED_VALUE"""),"Quarterly Pipeline vs Target Pipeline - Target - Q3") -> Quarterly Pipeline vs Target Pipeline - Target - Q3 | AG1: =IFERROR(__xludf.DUMMYFUNCTION("""COMPUTED_VALUE"""),"Quarterly Pipeline vs Target Pipeline - Achievement - Q3") -> Quarterly Pipeline vs Target Pipeline - Achievement - Q3 | AH1: =IFERROR(__xludf.DUMMYFUNCTION("""COMPUTED_VALUE"""),"Quarterly Pipeline vs Target Pipeline - Result - Q4") -> Quarterly Pipeline vs Target Pipeline - Result - Q4 | AI1: =IFERROR(__xludf.DUMMYFUNCTION("""COMPUTED_VALUE"""),"Quarterly Pipeline vs Target Pipeline - Target - Q4") -> Quarterly Pipeline vs Target Pipeline - Target - Q4 | AJ1: =IFERROR(__xludf.DUMMYFUNCTION("""COMPUTED_VALUE"""),"Quarterly Pipeline vs Target Pipeline - Achievement - Q4") -> Quarterly Pipeline vs Target Pipeline - Achievement - Q4 | AK1: =IFERROR(__xludf.DUMMYFUNCTION("""COMPUTED_VALUE"""),"Quarterly Pipeline vs Target Pipeline - Result - 2025 Total") -> Quarterly Pipeline vs Target Pipeline - Result - 2025 Total | AL1: =IFERROR(__xludf.DUMMYFUNCTION("""COMPUTED_VALUE"""),"Quarterly Pipeline vs Target Pipeline - Target - 2025 Total") -> Quarterly Pipeline vs Target Pipeline - Target - 2025 Total | AM1: =IFERROR(__xludf.DUMMYFUNCTION("""COMPUTED_VALUE"""),"Quarterly Pipeline vs Target Pipeline - Achievement - 2025 Total") -> Quarterly Pipeline vs Target Pipeline - Achievement - 2025 Total | AN1: =IFERROR(__xludf.DUMMYFUNCTION("""COMPUTED_VALUE"""),"Quarterly Pipeline vs Target Pipeline - Result - Q1 2026") -> Quarterly Pipeline vs Target Pipeline - Result - Q1 2026 | AO1: =IFERROR(__xludf.DUMMYFUNCTION("""COMPUTED_VALUE"""),"Quarterly Pipeline vs Target Pipeline - Target - Q1 2026") -> Quarterly Pipeline vs Target Pipeline - Target - Q1 2026 | AP1: =IFERROR(__xludf.DUMMYFUNCTION("""COMPUTED_VALUE"""),"Quarterly Pipeline vs Target Pipeline - Achievement - Q1 2026") -> Quarterly Pipeline vs Target Pipeline - Achievement - Q1 2026 | AQ1: =IFERROR(__xludf.DUMMYFUNCTION("""COMPUTED_VALUE"""),"Quarterly Pipeline vs Target Pipeline - Result - Q2 2026") -> Quarterly Pipeline vs Target Pipeline - Result - Q2 2026 | AR1: =IFERROR(__xludf.DUMMYFUNCTION("""COMPUTED_VALUE"""),"Quarterly Pipeline vs Target Pipeline - Target - Q2 2026") -> Quarterly Pipeline vs Target Pipeline - Target - Q2 2026 | AS1: =IFERROR(__xludf.DUMMYFUNCTION("""COMPUTED_VALUE"""),"Quarterly Pipeline vs Target Pipeline - Achievement - Q2 2026") -> Quarterly Pipeline vs Target Pipeline - Achievement - Q2 2026 | AT1: =IFERROR(__xludf.DUMMYFUNCTION("""COMPUTED_VALUE"""),"Quarterly Pipeline vs Target Pipeline - Result - Q3 2026") -> Quarterly Pipeline vs Target Pipeline - Result - Q3 2026 | AU1: =IFERROR(__xludf.DUMMYFUNCTION("""COMPUTED_VALUE"""),"Quarterly Pipeline vs Target Pipeline - Target - Q3 2026") -> Quarterly Pipeline vs Target Pipeline - Target - Q3 2026 | AV1: =IFERROR(__xludf.DUMMYFUNCTION("""COMPUTED_VALUE"""),"Quarterly Pipeline vs Target Pipeline - Achievement - Q3 2026") -> Quarterly Pipeline vs Target Pipeline - Achievement - Q3 2026 | AW1: =IFERROR(__xludf.DUMMYFUNCTION("""COMPUTED_VALUE"""),"Quarterly Pipeline vs Target Pipeline - Result - Q4 2026") -> Quarterly Pipeline vs Target Pipeline - Result - Q4 2026 | AX1: =IFERROR(__xludf.DUMMYFUNCTION("""COMPUTED_VALUE"""),"Quarterly Pipeline vs Target Pipeline - Target - Q4 2026") -> Quarterly Pipeline vs Target Pipeline - Target - Q4 2026 | AY1: =IFERROR(__xludf.DUMMYFUNCTION("""COMPUTED_VALUE"""),"Quarterly Pipeline vs Target Pipeline - Achievement - Q4 2026") -> Quarterly Pipeline vs Target Pipeline - Achievement - Q4 2026 | AZ1: =IFERROR(__xludf.DUMMYFUNCTION("""COMPUTED_VALUE"""),"Quarterly Pipeline vs Target Pipeline - Result - 2026 Total") -> Quarterly Pipeline vs Target Pipeline - Result - 2026 Total | BA1: =IFERROR(__xludf.DUMMYFUNCTION("""COMPUTED_VALUE"""),"Quarterly Pipeline vs Target Pipeline - Target - 2026 Total") -> Quarterly Pipeline vs Target Pipeline - Target - 2026 Total
A2: =IFERROR(__xludf.DUMMYFUNCTION("""COMPUTED_VALUE"""),"67eff1ff22947812f40fa354") -> 67eff1ff22947812f40fa354 | B2: =IFERROR(__xludf.DUMMYFUNCTION("""COMPUTED_VALUE"""),"ISTC de Mexico") -> ISTC de Mexico | C2: =IFERROR(__xludf.DUMMYFUNCTION("""COMPUTED_VALUE"""),"philippe.girard@al-enterprise.com, rui.silva@al-enterprise.com, joaquin.flores@al-enterprise.com") -> philippe.girard@al-enterprise.com, rui.silva@al-enterprise.com, joaquin.flores@al-enterprise.com | D2: =IFERROR(__xludf.DUMMYFUNCTION("""COMPUTED_VALUE"""),"americas") -> americas | E2: =IFERROR(__xludf.DUMMYFUNCTION("""COMPUTED_VALUE"""),"MX") -> MX | F2: =IFERROR(__xludf.DUMMYFUNCTION("""COMPUTED_VALUE"""),"distributor") -> distributor | G2: =IFERROR(__xludf.DUMMYFUNCTION("""COMPUTED_VALUE"""),0.0) -> 0 | H2: =IFERROR(__xludf.DUMMYFUNCTION("""COMPUTED_VALUE"""),1.0) -> 1 | I2: =IFERROR(__xludf.DUMMYFUNCTION("""COMPUTED_VALUE"""),0.0) -> 0 | J2: =IFERROR(__xludf.DUMMYFUNCTION("""COMPUTED_VALUE"""),0.0) -> 0 | K2: =IFERROR(__xludf.DUMMYFUNCTION("""COMPUTED_VALUE"""),500.0) -> 500 | L2: =IFERROR(__xludf.DUMMYFUNCTION("""COMPUTED_VALUE"""),0.0) -> 0 | M2: =IFERROR(__xludf.DUMMYFUNCTION("""COMPUTED_VALUE"""),0.0) -> 0 | N2: =IFERROR(__xludf.DUMMYFUNCTION("""COMPUTED_VALUE"""),0.0) -> 0 | O2: =IFERROR(__xludf.DUMMYFUNCTION("""COMPUTED_VALUE"""),"") | P2: =IFERROR(__xludf.DUMMYFUNCTION("""COMPUTED_VALUE"""),0.0) -> 0 | Q2: =IFERROR(__xludf.DUMMYFUNCTION("""COMPUTED_VALUE"""),1.0) -> 1 | R2: =IFERROR(__xludf.DUMMYFUNCTION("""COMPUTED_VALUE"""),0.0) -> 0 | S2: =IFERROR(__xludf.DUMMYFUNCTION("""COMPUTED_VALUE"""),0.0) -> 0 | T2: =IFERROR(__xludf.DUMMYFUNCTION("""COMPUTED_VALUE"""),1.0) -> 1 | U2: =IFERROR(__xludf.DUMMYFUNCTION("""COMPUTED_VALUE"""),0.0) -> 0 | V2: =IFERROR(__xludf.DUMMYFUNCTION("""COMPUTED_VALUE"""),0.0) -> 0 | W2: =IFERROR(__xludf.DUMMYFUNCTION("""COMPUTED_VALUE"""),1.0) -> 1 | X2: =IFERROR(__xludf.DUMMYFUNCTION("""COMPUTED_VALUE"""),0.0) -> 0 | Y2: =IFERROR(__xludf.DUMMYFUNCTION("""COMPUTED_VALUE"""),0.0) -> 0 | Z2: =IFERROR(__xludf.DUMMYFUNCTION("""COMPUTED_VALUE"""),0.0) -> 0 | AA2: =IFERROR(__xludf.DUMMYFUNCTION("""COMPUTED_VALUE"""),"") | AB2: =IFERROR(__xludf.DUMMYFUNCTION("""COMPUTED_VALUE"""),0.0) -> 0 | AC2: =IFERROR(__xludf.DUMMYFUNCTION("""COMPUTED_VALUE"""),383.33) -> 383.33 | AD2: =IFERROR(__xludf.DUMMYFUNCTION("""COMPUTED_VALUE"""),0.0) -> 0 | AE2: =IFERROR(__xludf.DUMMYFUNCTION("""COMPUTED_VALUE"""),49.55) -> 49.55 | AF2: =IFERROR(__xludf.DUMMYFUNCTION("""COMPUTED_VALUE"""),449.99) -> 449.99 | AG2: =IFERROR(__xludf.DUMMYFUNCTION("""COMPUTED_VALUE"""),0.11011355807906842) -> 0.11011356 | AH2: =IFERROR(__xludf.DUMMYFUNCTION("""COMPUTED_VALUE"""),45.83) -> 45.83 | AI2: =IFERROR(__xludf.DUMMYFUNCTION("""COMPUTED_VALUE"""),483.34) -> 483.34 | AJ2: =IFERROR(__xludf.DUMMYFUNCTION("""COMPUTED_VALUE"""),0.09481938180163033) -> 0.094819382 | AK2: =IFERROR(__xludf.DUMMYFUNCTION("""COMPUTED_VALUE"""),95.38) -> 95.38 | AL2: =IFERROR(__xludf.DUMMYFUNCTION("""COMPUTED_VALUE"""),1316.6599999999999) -> 1316.66 | AM2: =IFERROR(__xludf.DUMMYFUNCTION("""COMPUTED_VALUE"""),0.0724408731183449) -> 0.072440873 | AN2: =IFERROR(__xludf.DUMMYFUNCTION("""COMPUTED_VALUE"""),0.0) -> 0 | AO2: =IFERROR(__xludf.DUMMYFUNCTION("""COMPUTED_VALUE"""),0.0) -> 0 | AP2: =IFERROR(__xludf.DUMMYFUNCTION("""COMPUTED_VALUE"""),"") | AQ2: =IFERROR(__xludf.DUMMYFUNCTION("""COMPUTED_VALUE"""),0.0) -> 0 | AR2: =IFERROR(__xludf.DUMMYFUNCTION("""COMPUTED_VALUE"""),0.0) -> 0 | AS2: =IFERROR(__xludf.DUMMYFUNCTION("""COMPUTED_VALUE"""),"") | AT2: =IFERROR(__xludf.DUMMYFUNCTION("""COMPUTED_VALUE"""),0.0) -> 0 | AU2: =IFERROR(__xludf.DUMMYFUNCTION("""COMPUTED_VALUE"""),0.0) -> 0 | AV2: =IFERROR(__xludf.DUMMYFUNCTION("""COMPUTED_VALUE"""),"") | AW2: =IFERROR(__xludf.DUMMYFUNCTION("""COMPUTED_VALUE"""),0.0) -> 0 | AX2: =IFERROR(__xludf.DUMMYFUNCTION("""COMPUTED_VALUE"""),0.0) -> 0 | AY2: =IFERROR(__xludf.DUMMYFUNCTION("""COMPUTED_VALUE"""),"") | AZ2: =IFERROR(__xludf.DUMMYFUNCTION("""COMPUTED_VALUE"""),0.0) -> 0 | BA2: =IFERROR(__xludf.DUMMYFUNCTION("""COMPUTED_VALUE"""),0.0) -> 0 | BB2: =IFERROR(__xludf.DUMMYFUNCTION("""COMPUTED_VALUE"""),"")
A3: =IFERROR(__xludf.DUMMYFUNCTION("""COMPUTED_VALUE"""),"65f1c0a04b86f221530d41c2") -> 65f1c0a04b86f221530d41c2 | B3: =IFERROR(__xludf.DUMMYFUNCTION("""COMPUTED_VALUE"""),"Serverli Inc") -> Serverli Inc | C3: =IFERROR(__xludf.DUMMYFUNCTION("""COMPUTED_VALUE"""),"rui.silva@al-enterprise.com, michael-j.francis@al-enterprise.com, luigy.estevanell@al-enterprise.com") -> rui.silva@al-enterprise.com, michael-j.francis@al-enterprise.com, luigy.estevanell@al-enterprise.com | D3: =IFERROR(__xludf.DUMMYFUNCTION("""COMPUTED_VALUE"""),"americas") -> americas | E3: =IFERROR(__xludf.DUMMYFUNCTION("""COMPUTED_VALUE"""),"US") -> US | F3: =IFERROR(__xludf.DUMMYFUNCTION("""COMPUTED_VALUE"""),"expert_200") -> expert_200 | G3: =IFERROR(__xludf.DUMMYFUNCTION("""COMPUTED_VALUE"""),0.0) -> 0 | H3: =IFERROR(__xludf.DUMMYFUNCTION("""COMPUTED_VALUE"""),1.0) -> 1 | I3: =IFERROR(__xludf.DUMMYFUNCTION("""COMPUTED_VALUE"""),0.0) -> 0 | J3: =IFERROR(__xludf.DUMMYFUNCTION("""COMPUTED_VALUE"""),0.0) -> 0 | K3: =IFERROR(__xludf.DUMMYFUNCTION("""COMPUTED_VALUE"""),99.2) -> 99.2 | L3: =IFERROR(__xludf.DUMMYFUNCTION("""COMPUTED_VALUE"""),0.0) -> 0 | M3: =IFERROR(__xludf.DUMMYFUNCTION("""COMPUTED_VALUE"""),1.0) -> 1 | N3: =IFERROR(__xludf.DUMMYFUNCTION("""COMPUTED_VALUE"""),0.0) -> 0 | O3: =IFERROR(__xludf.DUMMYFUNCTION("""COMPUTED_VALUE"""),"") | P3: =IFERROR(__xludf.DUMMYFUNCTION("""COMPUTED_VALUE"""),0.0) -> 0 | Q3: =IFERROR(__xludf.DUMMYFUNCTION("""COMPUTED_VALUE"""),1.0) -> 1 | R3: =IFERROR(__xludf.DUMMYFUNCTION("""COMPUTED_VALUE"""),0.0) -> 0 | S3: =IFERROR(__xludf.DUMMYFUNCTION("""COMPUTED_VALUE"""),0.0) -> 0 | T3: =IFERROR(__xludf.DUMMYFUNCTION("""COMPUTED_VALUE"""),1.0) -> 1 | U3: =IFERROR(__xludf.DUMMYFUNCTION("""COMPUTED_VALUE"""),0.0) -> 0 | V3: =IFERROR(__xludf.DUMMYFUNCTION("""COMPUTED_VALUE"""),0.0) -> 0 | W3: =IFERROR(__xludf.DUMMYFUNCTION("""COMPUTED_VALUE"""),1.0) -> 1 | X3: =IFERROR(__xludf.DUMMYFUNCTION("""COMPUTED_VALUE"""),0.0) -> 0 | Y3: =IFERROR(__xludf.DUMMYFUNCTION("""COMPUTED_VALUE"""),0.0) -> 0 | Z3: =IFERROR(__xludf.DUMMYFUNCTION("""COMPUTED_VALUE"""),0.0) -> 0 | AA3: =IFERROR(__xludf.DUMMYFUNCTION("""COMPUTED_VALUE"""),"") | AB3: =IFERROR(__xludf.DUMMYFUNCTION("""COMPUTED_VALUE"""),44.27) -> 44.27 | AC3: =IFERROR(__xludf.DUMMYFUNCTION("""COMPUTED_VALUE"""),66.01) -> 66.01 | AD3: =IFERROR(__xludf.DUMMYFUNCTION("""COMPUTED_VALUE"""),0.6706559612179973) -> 0.67065596 | AE3: =IFERROR(__xludf.DUMMYFUNCTION("""COMPUTED_VALUE"""),30.0) -> 30 | AF3: =IFERROR(__xludf.DUMMYFUNCTION("""COMPUTED_VALUE"""),99.32) -> 99.32 | AG3: =IFERROR(__xludf.DUMMYFUNCTION("""COMPUTED_VALUE"""),0.30205396697543296) -> 0.30205397 | AH3: =IFERROR(__xludf.DUMMYFUNCTION("""COMPUTED_VALUE"""),301.0) -> 301 | AI3: =IFERROR(__xludf.DUMMYFUNCTION("""COMPUTED_VALUE"""),99.32) -> 99.32 | AJ3: =IFERROR(__xludf.DUMMYFUNCTION("""COMPUTED_VALUE"""),3.0306081353201773) -> 3.0306081 | AK3: =IFERROR(__xludf.DUMMYFUNCTION("""COMPUTED_VALUE"""),375.27) -> 375.27 | AL3: =IFERROR(__xludf.DUMMYFUNCTION("""COMPUTED_VALUE"""),264.65) -> 264.65 | AM3: =IFERROR(__xludf.DUMMYFUNCTION("""COMPUTED_VALUE"""),1.417986019270735) -> 1.417986 | AN3: =IFERROR(__xludf.DUMMYFUNCTION("""COMPUTED_VALUE"""),301.0) -> 301 | AO3: =IFERROR(__xludf.DUMMYFUNCTION("""COMPUTED_VALUE"""),0.0) -> 0 | AP3: =IFERROR(__xludf.DUMMYFUNCTION("""COMPUTED_VALUE"""),"") | AQ3: =IFERROR(__xludf.DUMMYFUNCTION("""COMPUTED_VALUE"""),0.0) -> 0 | AR3: =IFERROR(__xludf.DUMMYFUNCTION("""COMPUTED_VALUE"""),0.0) -> 0 | AS3: =IFERROR(__xludf.DUMMYFUNCTION("""COMPUTED_VALUE"""),"") | AT3: =IFERROR(__xludf.DUMMYFUNCTION("""COMPUTED_VALUE"""),0.0) -> 0 | AU3: =IFERROR(__xludf.DUMMYFUNCTION("""COMPUTED_VALUE"""),0.0) -> 0 | AV3: =IFERROR(__xludf.DUMMYFUNCTION("""COMPUTED_VALUE"""),"") | AW3: =IFERROR(__xludf.DUMMYFUNCTION("""COMPUTED_VALUE"""),0.0) -> 0 | AX3: =IFERROR(__xludf.DUMMYFUNCTION("""COMPUTED_VALUE"""),0.0) -> 0 | AY3: =IFERROR(__xludf.DUMMYFUNCTION("""COMPUTED_VALUE"""),"") | AZ3: =IFERROR(__xludf.DUMMYFUNCTION("""COMPUTED_VALUE"""),301.0) -> 301 | BA3: =IFERROR(__xludf.DUMMYFUNCTION("""COMPUTED_VALUE"""),0.0) -> 0 | BB3: =IFERROR(__xludf.DUMMYFUNCTION("""COMPUTED_VALUE"""),"")
A4: =IFERROR(__xludf.DUMMYFUNCTION("""COMPUTED_VALUE"""),"63ced843c5c820531c268186") -> 63ced843c5c820531c268186 | B4: =IFERROR(__xludf.DUMMYFUNCTION("""COMPUTED_VALUE"""),"3CORP TECHNOLOGY INFRAESTRUTURA DE") -> 3CORP TECHNOLOGY INFRAESTRUTURA DE | C4: =IFERROR(__xludf.DUMMYFUNCTION("""COMPUTED_VALUE"""),"renato-takashi.yoshizako@al-enterprise.com") -> renato-takashi.yoshizako@al-enterprise.com | D4: =IFERROR(__xludf.DUMMYFUNCTION("""COMPUTED_VALUE"""),"americas") -> americas | E4: =IFERROR(__xludf.DUMMYFUNCTION("""COMPUTED_VALUE"""),"BR") -> BR | F4: =IFERROR(__xludf.DUMMYFUNCTION("""COMPUTED_VALUE"""),"yes") -> yes | G4: =IFERROR(__xludf.DUMMYFUNCTION("""COMPUTED_VALUE"""),1.0) -> 1 | H4: =IFERROR(__xludf.DUMMYFUNCTION("""COMPUTED_VALUE"""),1.0) -> 1 | I4: =IFERROR(__xludf.DUMMYFUNCTION("""COMPUTED_VALUE"""),1.0) -> 1 | J4: =IFERROR(__xludf.DUMMYFUNCTION("""COMPUTED_VALUE"""),219.99) -> 219.99 | K4: =IFERROR(__xludf.DUMMYFUNCTION("""COMPUTED_VALUE"""),4099.96) -> 4099.96 | L4: =IFERROR(__xludf.DUMMYFUNCTION("""COMPUTED_VALUE"""),0.05365662104020527) -> 0.053656621 | M4: =IFERROR(__xludf.DUMMYFUNCTION("""COMPUTED_VALUE"""),267.0) -> 267 | N4: =IFERROR(__xludf.DUMMYFUNCTION("""COMPUTED_VALUE"""),52.0) -> 52 | O4: =IFERROR(__xludf.DUMMYFUNCTION("""COMPUTED_VALUE"""),5.134615384615385) -> 5.1346154 | P4: =IFERROR(__xludf.DUMMYFUNCTION("""COMPUTED_VALUE"""),1.0) -> 1 | Q4: =IFERROR(__xludf.DUMMYFUNCTION("""COMPUTED_VALUE"""),1.0) -> 1 | R4: =IFERROR(__xludf.DUMMYFUNCTION("""COMPUTED_VALUE"""),1.0) -> 1 | S4: =IFERROR(__xludf.DUMMYFUNCTION("""COMPUTED_VALUE"""),0.0) -> 0 | T4: =IFERROR(__xludf.DUMMYFUNCTION("""COMPUTED_VALUE"""),1.0) -> 1 | U4: =IFERROR(__xludf.DUMMYFUNCTION("""COMPUTED_VALUE"""),0.0) -> 0 | V4: =IFERROR(__xludf.DUMMYFUNCTION("""COMPUTED_VALUE"""),0.0) -> 0 | W4: =IFERROR(__xludf.DUMMYFUNCTION("""COMPUTED_VALUE"""),1.0) -> 1 | X4: =IFERROR(__xludf.DUMMYFUNCTION("""COMPUTED_VALUE"""),0.0) -> 0 | Y4: =IFERROR(__xludf.DUMMYFUNCTION("""COMPUTED_VALUE"""),44.0) -> 44 | Z4: =IFERROR(__xludf.DUMMYFUNCTION("""COMPUTED_VALUE"""),0.0) -> 0 | AA4: =IFERROR(__xludf.DUMMYFUNCTION("""COMPUTED_VALUE"""),"") | AB4: =IFERROR(__xludf.DUMMYFUNCTION("""COMPUTED_VALUE"""),29.0) -> 29 | AC4: =IFERROR(__xludf.DUMMYFUNCTION("""COMPUTED_VALUE"""),3416.62) -> 3416.62 | AD4: =IFERROR(__xludf.DUMMYFUNCTION("""COMPUTED_VALUE"""),0.008487920810625707) -> 0.0084879208 | AE4: =IFERROR(__xludf.DUMMYFUNCTION("""COMPUTED_VALUE"""),1788.03) -> 1788.03 | AF4: =IFERROR(__xludf.DUMMYFUNCTION("""COMPUTED_VALUE"""),3416.97) -> 3416.97 | AG4: =IFERROR(__xludf.DUMMYFUNCTION("""COMPUTED_VALUE"""),0.523279396658443) -> 0.5232794 | AH4: =IFERROR(__xludf.DUMMYFUNCTION("""COMPUTED_VALUE"""),542.99) -> 542.99 | AI4: =IFERROR(__xludf.DUMMYFUNCTION("""COMPUTED_VALUE"""),3416.97) -> 3416.97 | AJ4: =IFERROR(__xludf.DUMMYFUNCTION("""COMPUTED_VALUE"""),0.15890979434996505) -> 0.15890979 | AK4: =IFERROR(__xludf.DUMMYFUNCTION("""COMPUTED_VALUE"""),2404.02) -> 2404.02 | AL4: =IFERROR(__xludf.DUMMYFUNCTION("""COMPUTED_VALUE"""),10250.56) -> 10250.56 | AM4: =IFERROR(__xludf.DUMMYFUNCTION("""COMPUTED_VALUE"""),0.2345257234726688) -> 0.23452572 | AN4: =IFERROR(__xludf.DUMMYFUNCTION("""COMPUTED_VALUE"""),56.8) -> 56.8 | AO4: =IFERROR(__xludf.DUMMYFUNCTION("""COMPUTED_VALUE"""),0.0) -> 0 | AP4: =IFERROR(__xludf.DUMMYFUNCTION("""COMPUTED_VALUE"""),"") | AQ4: =IFERROR(__xludf.DUMMYFUNCTION("""COMPUTED_VALUE"""),79.0) -> 79 | AR4: =IFERROR(__xludf.DUMMYFUNCTION("""COMPUTED_VALUE"""),0.0) -> 0 | AS4: =IFERROR(__xludf.DUMMYFUNCTION("""COMPUTED_VALUE"""),"") | AT4: =IFERROR(__xludf.DUMMYFUNCTION("""COMPUTED_VALUE"""),0.0) -> 0 | AU4: =IFERROR(__xludf.DUMMYFUNCTION("""COMPUTED_VALUE"""),0.0) -> 0 | AV4: =IFERROR(__xludf.DUMMYFUNCTION("""COMPUTED_VALUE"""),"") | AW4: =IFERROR(__xludf.DUMMYFUNCTION("""COMPUTED_VALUE"""),0.0) -> 0 | AX4: =IFERROR(__xludf.DUMMYFUNCTION("""COMPUTED_VALUE"""),0.0) -> 0 | AY4: =IFERROR(__xludf.DUMMYFUNCTION("""COMPUTED_VALUE"""),"") | AZ4: =IFERROR(__xludf.DUMMYFUNCTION("""COMPUTED_VALUE"""),135.8) -> 135.8 | BA4: =IFERROR(__xludf.DUMMYFUNCTION("""COMPUTED_VALUE"""),0.0) -> 0 | BB4: =IFERROR(__xludf.DUMMYFUNCTION("""COMPUTED_VALUE"""),"")
A5: =IFERROR(__xludf.DUMMYFUNCTION("""COMPUTED_VALUE"""),"67a5dc38617ada49240d92c2") -> 67a5dc38617ada49240d92c2 | B5: =IFERROR(__xludf.DUMMYFUNCTION("""COMPUTED_VALUE"""),"9 to 5 Computer") -> 9 to 5 Computer | C5: =IFERROR(__xludf.DUMMYFUNCTION("""COMPUTED_VALUE"""),"michael-j.francis@al-enterprise.com, luigy.estevanell@al-enterprise.com") -> michael-j.francis@al-enterprise.com, luigy.estevanell@al-enterprise.com | D5: =IFERROR(__xludf.DUMMYFUNCTION("""COMPUTED_VALUE"""),"americas") -> americas | E5: =IFERROR(__xludf.DUMMYFUNCTION("""COMPUTED_VALUE"""),"US") -> US | F5: =IFERROR(__xludf.DUMMYFUNCTION("""COMPUTED_VALUE"""),"expert_200") -> expert_200 | G5: =IFERROR(__xludf.DUMMYFUNCTION("""COMPUTED_VALUE"""),0.0) -> 0 | H5: =IFERROR(__xludf.DUMMYFUNCTION("""COMPUTED_VALUE"""),1.0) -> 1 | I5: =IFERROR(__xludf.DUMMYFUNCTION("""COMPUTED_VALUE"""),0.0) -> 0 | J5: =IFERROR(__xludf.DUMMYFUNCTION("""COMPUTED_VALUE"""),15.12) -> 15.12 | K5: =IFERROR(__xludf.DUMMYFUNCTION("""COMPUTED_VALUE"""),155.0) -> 155 | L5: =IFERROR(__xludf.DUMMYFUNCTION("""COMPUTED_VALUE"""),0.09754838709677419) -> 0.097548387 | M5: =IFERROR(__xludf.DUMMYFUNCTION("""COMPUTED_VALUE"""),0.0) -> 0 | N5: =IFERROR(__xludf.DUMMYFUNCTION("""COMPUTED_VALUE"""),0.0) -> 0 | O5: =IFERROR(__xludf.DUMMYFUNCTION("""COMPUTED_VALUE"""),"") | P5: =IFERROR(__xludf.DUMMYFUNCTION("""COMPUTED_VALUE"""),0.0) -> 0 | Q5: =IFERROR(__xludf.DUMMYFUNCTION("""COMPUTED_VALUE"""),1.0) -> 1 | R5: =IFERROR(__xludf.DUMMYFUNCTION("""COMPUTED_VALUE"""),0.0) -> 0 | S5: =IFERROR(__xludf.DUMMYFUNCTION("""COMPUTED_VALUE"""),0.0) -> 0 | T5: =IFERROR(__xludf.DUMMYFUNCTION("""COMPUTED_VALUE"""),1.0) -> 1 | U5: =IFERROR(__xludf.DUMMYFUNCTION("""COMPUTED_VALUE"""),0.0) -> 0 | V5: =IFERROR(__xludf.DUMMYFUNCTION("""COMPUTED_VALUE"""),0.0) -> 0 | W5: =IFERROR(__xludf.DUMMYFUNCTION("""COMPUTED_VALUE"""),1.0) -> 1 | X5: =IFERROR(__xludf.DUMMYFUNCTION("""COMPUTED_VALUE"""),0.0) -> 0 | Y5: =IFERROR(__xludf.DUMMYFUNCTION("""COMPUTED_VALUE"""),0.0) -> 0 | Z5: =IFERROR(__xludf.DUMMYFUNCTION("""COMPUTED_VALUE"""),0.0) -> 0 | AA5: =IFERROR(__xludf.DUMMYFUNCTION("""COMPUTED_VALUE"""),"") | AB5: =IFERROR(__xludf.DUMMYFUNCTION("""COMPUTED_VALUE"""),0.0) -> 0 | AC5: =IFERROR(__xludf.DUMMYFUNCTION("""COMPUTED_VALUE"""),0.0) -> 0 | AD5: =IFERROR(__xludf.DUMMYFUNCTION("""COMPUTED_VALUE"""),"") | AE5: =IFERROR(__xludf.DUMMYFUNCTION("""COMPUTED_VALUE"""),0.0) -> 0 | AF5: =IFERROR(__xludf.DUMMYFUNCTION("""COMPUTED_VALUE"""),154.98) -> 154.98 | AG5: =IFERROR(__xludf.DUMMYFUNCTION("""COMPUTED_VALUE"""),0.0) -> 0 | AH5: =IFERROR(__xludf.DUMMYFUNCTION("""COMPUTED_VALUE"""),0.0) -> 0 | AI5: =IFERROR(__xludf.DUMMYFUNCTION("""COMPUTED_VALUE"""),154.98) -> 154.98 | AJ5: =IFERROR(__xludf.DUMMYFUNCTION("""COMPUTED_VALUE"""),0.0) -> 0 | AK5: =IFERROR(__xludf.DUMMYFUNCTION("""COMPUTED_VALUE"""),0.0) -> 0 | AL5: =IFERROR(__xludf.DUMMYFUNCTION("""COMPUTED_VALUE"""),309.96) -> 309.96 | AM5: =IFERROR(__xludf.DUMMYFUNCTION("""COMPUTED_VALUE"""),0.0) -> 0 | AN5: =IFERROR(__xludf.DUMMYFUNCTION("""COMPUTED_VALUE"""),0.0) -> 0 | AO5: =IFERROR(__xludf.DUMMYFUNCTION("""COMPUTED_VALUE"""),0.0) -> 0 | AP5: =IFERROR(__xludf.DUMMYFUNCTION("""COMPUTED_VALUE"""),"") | AQ5: =IFERROR(__xludf.DUMMYFUNCTION("""COMPUTED_VALUE"""),0.0) -> 0 | AR5: =IFERROR(__xludf.DUMMYFUNCTION("""COMPUTED_VALUE"""),0.0) -> 0 | AS5: =IFERROR(__xludf.DUMMYFUNCTION("""COMPUTED_VALUE"""),"") | AT5: =IFERROR(__xludf.DUMMYFUNCTION("""COMPUTED_VALUE"""),0.0) -> 0 | AU5: =IFERROR(__xludf.DUMMYFUNCTION("""COMPUTED_VALUE"""),0.0) -> 0 | AV5: =IFERROR(__xludf.DUMMYFUNCTION("""COMPUTED_VALUE"""),"") | AW5: =IFERROR(__xludf.DUMMYFUNCTION("""COMPUTED_VALUE"""),0.0) -> 0 | AX5: =IFERROR(__xludf.DUMMYFUNCTION("""COMPUTED_VALUE"""),0.0) -> 0 | AY5: =IFERROR(__xludf.DUMMYFUNCTION("""COMPUTED_VALUE"""),"") | AZ5: =IFERROR(__xludf.DUMMYFUNCTION("""COMPUTED_VALUE"""),0.0) -> 0 | BA5: =IFERROR(__xludf.DUMMYFUNCTION("""COMPUTED_VALUE"""),0.0) -> 0 | BB5: =IFERROR(__xludf.DUMMYFUNCTION("""COMPUTED_VALUE"""),"")
A6: =IFERROR(__xludf.DUMMYFUNCTION("""COMPUTED_VALUE"""),"66a75f819d5f4ed144040ad2") -> 66a75f819d5f4ed144040ad2 | B6: =IFERROR(__xludf.DUMMYFUNCTION("""COMPUTED_VALUE"""),"A&O TEC GmbH") -> A&O TEC GmbH | C6: =IFERROR(__xludf.DUMMYFUNCTION("""COMPUTED_VALUE"""),"thomas.ullmann@al-enterprise.com, andreas.grossheimann@al-enterprise.com") -> thomas.ullmann@al-enterprise.com, andreas.grossheimann@al-enterprise.com | D6: =IFERROR(__xludf.DUMMYFUNCTION("""COMPUTED_VALUE"""),"germany") -> germany | E6: =IFERROR(__xludf.DUMMYFUNCTION("""COMPUTED_VALUE"""),"DE") -> DE | F6: =IFERROR(__xludf.DUMMYFUNCTION("""COMPUTED_VALUE"""),"expert_200") -> expert_200 | G6: =IFERROR(__xludf.DUMMYFUNCTION("""COMPUTED_VALUE"""),1.0) -> 1 | H6: =IFERROR(__xludf.DUMMYFUNCTION("""COMPUTED_VALUE"""),1.0) -> 1 | I6: =IFERROR(__xludf.DUMMYFUNCTION("""COMPUTED_VALUE"""),1.0) -> 1 | J6: =IFERROR(__xludf.DUMMYFUNCTION("""COMPUTED_VALUE"""),0.0) -> 0 | K6: =IFERROR(__xludf.DUMMYFUNCTION("""COMPUTED_VALUE"""),753.0) -> 753 | L6: =IFERROR(__xludf.DUMMYFUNCTION("""COMPUTED_VALUE"""),0.0) -> 0 | M6: =IFERROR(__xludf.DUMMYFUNCTION("""COMPUTED_VALUE"""),0.0) -> 0 | N6: =IFERROR(__xludf.DUMMYFUNCTION("""COMPUTED_VALUE"""),0.0) -> 0 | O6: =IFERROR(__xludf.DUMMYFUNCTION("""COMPUTED_VALUE"""),"") | P6: =IFERROR(__xludf.DUMMYFUNCTION("""COMPUTED_VALUE"""),0.0) -> 0 | Q6: =IFERROR(__xludf.DUMMYFUNCTION("""COMPUTED_VALUE"""),1.0) -> 1 | R6: =IFERROR(__xludf.DUMMYFUNCTION("""COMPUTED_VALUE"""),0.0) -> 0 | S6: =IFERROR(__xludf.DUMMYFUNCTION("""COMPUTED_VALUE"""),0.0) -> 0 | T6: =IFERROR(__xludf.DUMMYFUNCTION("""COMPUTED_VALUE"""),1.0) -> 1 | U6: =IFERROR(__xludf.DUMMYFUNCTION("""COMPUTED_VALUE"""),0.0) -> 0 | V6: =IFERROR(__xludf.DUMMYFUNCTION("""COMPUTED_VALUE"""),0.0) -> 0 | W6: =IFERROR(__xludf.DUMMYFUNCTION("""COMPUTED_VALUE"""),1.0) -> 1 | X6: =IFERROR(__xludf.DUMMYFUNCTION("""COMPUTED_VALUE"""),0.0) -> 0 | Y6: =IFERROR(__xludf.DUMMYFUNCTION("""COMPUTED_VALUE"""),32.4) -> 32.4 | Z6: =IFERROR(__xludf.DUMMYFUNCTION("""COMPUTED_VALUE"""),0.0) -> 0 | AA6: =IFERROR(__xludf.DUMMYFUNCTION("""COMPUTED_VALUE"""),"") | AB6: =IFERROR(__xludf.DUMMYFUNCTION("""COMPUTED_VALUE"""),34.44) -> 34.44 | AC6: =IFERROR(__xludf.DUMMYFUNCTION("""COMPUTED_VALUE"""),502.0) -> 502 | AD6: =IFERROR(__xludf.DUMMYFUNCTION("""COMPUTED_VALUE"""),0.06860557768924302) -> 0.068605578 | AE6: =IFERROR(__xludf.DUMMYFUNCTION("""COMPUTED_VALUE"""),119.34) -> 119.34 | AF6: =IFERROR(__xludf.DUMMYFUNCTION("""COMPUTED_VALUE"""),753.0) -> 753 | AG6: =IFERROR(__xludf.DUMMYFUNCTION("""COMPUTED_VALUE"""),0.15848605577689243) -> 0.15848606 | AH6: =IFERROR(__xludf.DUMMYFUNCTION("""COMPUTED_VALUE"""),196.84) -> 196.84 | AI6: =IFERROR(__xludf.DUMMYFUNCTION("""COMPUTED_VALUE"""),753.0) -> 753 | AJ6: =IFERROR(__xludf.DUMMYFUNCTION("""COMPUTED_VALUE"""),0.26140770252324036) -> 0.2614077 | AK6: =IFERROR(__xludf.DUMMYFUNCTION("""COMPUTED_VALUE"""),383.02) -> 383.02 | AL6: =IFERROR(__xludf.DUMMYFUNCTION("""COMPUTED_VALUE"""),2008.0) -> 2008 | AM6: =IFERROR(__xludf.DUMMYFUNCTION("""COMPUTED_VALUE"""),0.19074701195219124) -> 0.19074701 | AN6: =IFERROR(__xludf.DUMMYFUNCTION("""COMPUTED_VALUE"""),32.4) -> 32.4 | AO6: =IFERROR(__xludf.DUMMYFUNCTION("""COMPUTED_VALUE"""),0.0) -> 0 | AP6: =IFERROR(__xludf.DUMMYFUNCTION("""COMPUTED_VALUE"""),"") | AQ6: =IFERROR(__xludf.DUMMYFUNCTION("""COMPUTED_VALUE"""),0.0) -> 0 | AR6: =IFERROR(__xludf.DUMMYFUNCTION("""COMPUTED_VALUE"""),0.0) -> 0 | AS6: =IFERROR(__xludf.DUMMYFUNCTION("""COMPUTED_VALUE"""),"") | AT6: =IFERROR(__xludf.DUMMYFUNCTION("""COMPUTED_VALUE"""),0.0) -> 0 | AU6: =IFERROR(__xludf.DUMMYFUNCTION("""COMPUTED_VALUE"""),0.0) -> 0 | AV6: =IFERROR(__xludf.DUMMYFUNCTION("""COMPUTED_VALUE"""),"") | AW6: =IFERROR(__xludf.DUMMYFUNCTION("""COMPUTED_VALUE"""),0.0) -> 0 | AX6: =IFERROR(__xludf.DUMMYFUNCTION("""COMPUTED_VALUE"""),0.0) -> 0 | AY6: =IFERROR(__xludf.DUMMYFUNCTION("""COMPUTED_VALUE"""),"") | AZ6: =IFERROR(__xludf.DUMMYFUNCTION("""COMPUTED_VALUE"""),32.4) -> 32.4 | BA6: =IFERROR(__xludf.DUMMYFUNCTION("""COMPUTED_VALUE"""),0.0) -> 0 | BB6: =IFERROR(__xludf.DUMMYFUNCTION("""COMPUTED_VALUE"""),"")
A7: =IFERROR(__xludf.DUMMYFUNCTION("""COMPUTED_VALUE"""),"63ef9d58384f27260c1ba49b") -> 63ef9d58384f27260c1ba49b | B7: =IFERROR(__xludf.DUMMYFUNCTION("""COMPUTED_VALUE"""),"AAA Solar Electric, Inc.") -> AAA Solar Electric, Inc. | C7: =IFERROR(__xludf.DUMMYFUNCTION("""COMPUTED_VALUE"""),"gene.hawks@al-enterprise.com, bill.rademacher@al-enterprise.com") -> gene.hawks@al-enterprise.com, bill.rademacher@al-enterprise.com | D7: =IFERROR(__xludf.DUMMYFUNCTION("""COMPUTED_VALUE"""),"americas") -> americas | E7: =IFERROR(__xludf.DUMMYFUNCTION("""COMPUTED_VALUE"""),"US") -> US | F7: =IFERROR(__xludf.DUMMYFUNCTION("""COMPUTED_VALUE"""),"expert_200") -> expert_200 | G7: =IFERROR(__xludf.DUMMYFUNCTION("""COMPUTED_VALUE"""),0.0) -> 0 | H7: =IFERROR(__xludf.DUMMYFUNCTION("""COMPUTED_VALUE"""),1.0) -> 1 | I7: =IFERROR(__xludf.DUMMYFUNCTION("""COMPUTED_VALUE"""),0.0) -> 0 | J7: =IFERROR(__xludf.DUMMYFUNCTION("""COMPUTED_VALUE"""),34.12) -> 34.12 | K7: =IFERROR(__xludf.DUMMYFUNCTION("""COMPUTED_VALUE"""),0.0) -> 0 | L7: =IFERROR(__xludf.DUMMYFUNCTION("""COMPUTED_VALUE"""),"") | M7: =IFERROR(__xludf.DUMMYFUNCTION("""COMPUTED_VALUE"""),0.0) -> 0 | N7: =IFERROR(__xludf.DUMMYFUNCTION("""COMPUTED_VALUE"""),56.0) -> 56 | O7: =IFERROR(__xludf.DUMMYFUNCTION("""COMPUTED_VALUE"""),0.0) -> 0 | P7: =IFERROR(__xludf.DUMMYFUNCTION("""COMPUTED_VALUE"""),0.0) -> 0 | Q7: =IFERROR(__xludf.DUMMYFUNCTION("""COMPUTED_VALUE"""),1.0) -> 1 | R7: =IFERROR(__xludf.DUMMYFUNCTION("""COMPUTED_VALUE"""),0.0) -> 0 | S7: =IFERROR(__xludf.DUMMYFUNCTION("""COMPUTED_VALUE"""),0.0) -> 0 | T7: =IFERROR(__xludf.DUMMYFUNCTION("""COMPUTED_VALUE"""),1.0) -> 1 | U7: =IFERROR(__xludf.DUMMYFUNCTION("""COMPUTED_VALUE"""),0.0) -> 0 | V7: =IFERROR(__xludf.DUMMYFUNCTION("""COMPUTED_VALUE"""),0.0) -> 0 | W7: =IFERROR(__xludf.DUMMYFUNCTION("""COMPUTED_VALUE"""),1.0) -> 1 | X7: =IFERROR(__xludf.DUMMYFUNCTION("""COMPUTED_VALUE"""),0.0) -> 0 | Y7: =IFERROR(__xludf.DUMMYFUNCTION("""COMPUTED_VALUE"""),20.84) -> 20.84 | Z7: =IFERROR(__xludf.DUMMYFUNCTION("""COMPUTED_VALUE"""),0.0) -> 0 | AA7: =IFERROR(__xludf.DUMMYFUNCTION("""COMPUTED_VALUE"""),"") | AB7: =IFERROR(__xludf.DUMMYFUNCTION("""COMPUTED_VALUE"""),0.0) -> 0 | AC7: =IFERROR(__xludf.DUMMYFUNCTION("""COMPUTED_VALUE"""),0.0) -> 0 | AD7: =IFERROR(__xludf.DUMMYFUNCTION("""COMPUTED_VALUE"""),"") | AE7: =IFERROR(__xludf.DUMMYFUNCTION("""COMPUTED_VALUE"""),0.0) -> 0 | AF7: =IFERROR(__xludf.DUMMYFUNCTION("""COMPUTED_VALUE"""),0.0) -> 0 | AG7: =IFERROR(__xludf.DUMMYFUNCTION("""COMPUTED_VALUE"""),"") | AH7: =IFERROR(__xludf.DUMMYFUNCTION("""COMPUTED_VALUE"""),0.0) -> 0 | AI7: =IFERROR(__xludf.DUMMYFUNCTION("""COMPUTED_VALUE"""),0.0) -> 0 | AJ7: =IFERROR(__xludf.DUMMYFUNCTION("""COMPUTED_VALUE"""),"") | AK7: =IFERROR(__xludf.DUMMYFUNCTION("""COMPUTED_VALUE"""),20.84) -> 20.84 | AL7: =IFERROR(__xludf.DUMMYFUNCTION("""COMPUTED_VALUE"""),0.0) -> 0 | AM7: =IFERROR(__xludf.DUMMYFUNCTION("""COMPUTED_VALUE"""),"") | AN7: =IFERROR(__xludf.DUMMYFUNCTION("""COMPUTED_VALUE"""),0.0) -> 0 | AO7: =IFERROR(__xludf.DUMMYFUNCTION("""COMPUTED_VALUE"""),0.0) -> 0 | AP7: =IFERROR(__xludf.DUMMYFUNCTION("""COMPUTED_VALUE"""),"") | AQ7: =IFERROR(__xludf.DUMMYFUNCTION("""COMPUTED_VALUE"""),0.0) -> 0 | AR7: =IFERROR(__xludf.DUMMYFUNCTION("""COMPUTED_VALUE"""),0.0) -> 0 | AS7: =IFERROR(__xludf.DUMMYFUNCTION("""COMPUTED_VALUE"""),"") | AT7: =IFERROR(__xludf.DUMMYFUNCTION("""COMPUTED_VALUE"""),0.0) -> 0 | AU7: =IFERROR(__xludf.DUMMYFUNCTION("""COMPUTED_VALUE"""),0.0) -> 0 | AV7: =IFERROR(__xludf.DUMMYFUNCTION("""COMPUTED_VALUE"""),"") | AW7: =IFERROR(__xludf.DUMMYFUNCTION("""COMPUTED_VALUE"""),0.0) -> 0 | AX7: =IFERROR(__xludf.DUMMYFUNCTION("""COMPUTED_VALUE"""),0.0) -> 0 | AY7: =IFERROR(__xludf.DUMMYFUNCTION("""COMPUTED_VALUE"""),"") | AZ7: =IFERROR(__xludf.DUMMYFUNCTION("""COMPUTED_VALUE"""),0.0) -> 0 | BA7: =IFERROR(__xludf.DUMMYFUNCTION("""COMPUTED_VALUE"""),0.0) -> 0 | BB7: =IFERROR(__xludf.DUMMYFUNCTION("""COMPUTED_VALUE"""),"")
A8: =IFERROR(__xludf.DUMMYFUNCTION("""COMPUTED_VALUE"""),"6299fef42acbb9510b5e178a") -> 6299fef42acbb9510b5e178a | B8: =IFERROR(__xludf.DUMMYFUNCTION("""COMPUTED_VALUE"""),"abl social federation GmbH") -> abl social federation GmbH | C8: =IFERROR(__xludf.DUMMYFUNCTION("""COMPUTED_VALUE"""),"olivier.ravel@al-enterprise.com, rui.silva@al-enterprise.com, thomas.ullmann@al-enterprise.com, andreas.grossheimann@al-enterprise.com, katrin.pfeiffer@al-enterprise.com, sibylle.klopfer@al-enterprise.com, igor.leko@al-enterprise.com, daniel.scheidl@al-en"&"terprise.com, hakan.adiguezel@al-enterprise.com") -> olivier.ravel@al-enterprise.com, rui.silva@al-enterprise.com, thomas.ullmann@al-enterprise.com, andreas.grossheimann@al-enterprise.com, katrin.pfeiffer@al-enterprise.com, sibylle.klopfer@al-enterprise.com, igor.leko@al-enterprise.com, daniel.scheidl@al-enterprise.com, hakan.adiguezel@al-enterprise.com | D8: =IFERROR(__xludf.DUMMYFUNCTION("""COMPUTED_VALUE"""),"germany") -> germany | E8: =IFERROR(__xludf.DUMMYFUNCTION("""COMPUTED_VALUE"""),"DE") -> DE | F8: =IFERROR(__xludf.DUMMYFUNCTION("""COMPUTED_VALUE"""),"expert_200") -> expert_200 | G8: =IFERROR(__xludf.DUMMYFUNCTION("""COMPUTED_VALUE"""),0.0) -> 0 | H8: =IFERROR(__xludf.DUMMYFUNCTION("""COMPUTED_VALUE"""),1.0) -> 1 | I8: =IFERROR(__xludf.DUMMYFUNCTION("""COMPUTED_VALUE"""),0.0) -> 0 | J8: =IFERROR(__xludf.DUMMYFUNCTION("""COMPUTED_VALUE"""),0.0) -> 0 | K8: =IFERROR(__xludf.DUMMYFUNCTION("""COMPUTED_VALUE"""),0.0) -> 0 | L8: =IFERROR(__xludf.DUMMYFUNCTION("""COMPUTED_VALUE"""),"") | M8: =IFERROR(__xludf.DUMMYFUNCTION("""COMPUTED_VALUE"""),6.0) -> 6 | N8: =IFERROR(__xludf.DUMMYFUNCTION("""COMPUTED_VALUE"""),0.0) -> 0 | O8: =IFERROR(__xludf.DUMMYFUNCTION("""COMPUTED_VALUE"""),"") | P8: =IFERROR(__xludf.DUMMYFUNCTION("""COMPUTED_VALUE"""),0.0) -> 0 | Q8: =IFERROR(__xludf.DUMMYFUNCTION("""COMPUTED_VALUE"""),1.0) -> 1 | R8: =IFERROR(__xludf.DUMMYFUNCTION("""COMPUTED_VALUE"""),0.0) -> 0 | S8: =IFERROR(__xludf.DUMMYFUNCTION("""COMPUTED_VALUE"""),1.0) -> 1 | T8: =IFERROR(__xludf.DUMMYFUNCTION("""COMPUTED_VALUE"""),1.0) -> 1 | U8: =IFERROR(__xludf.DUMMYFUNCTION("""COMPUTED_VALUE"""),1.0) -> 1 | V8: =IFERROR(__xludf.DUMMYFUNCTION("""COMPUTED_VALUE"""),0.0) -> 0 | W8: =IFERROR(__xludf.DUMMYFUNCTION("""COMPUTED_VALUE"""),1.0) -> 1 | X8: =IFERROR(__xludf.DUMMYFUNCTION("""COMPUTED_VALUE"""),0.0) -> 0 | Y8: =IFERROR(__xludf.DUMMYFUNCTION("""COMPUTED_VALUE"""),0.0) -> 0 | Z8: =IFERROR(__xludf.DUMMYFUNCTION("""COMPUTED_VALUE"""),0.0) -> 0 | AA8: =IFERROR(__xludf.DUMMYFUNCTION("""COMPUTED_VALUE"""),"") | AB8: =IFERROR(__xludf.DUMMYFUNCTION("""COMPUTED_VALUE"""),0.0) -> 0 | AC8: =IFERROR(__xludf.DUMMYFUNCTION("""COMPUTED_VALUE"""),0.0) -> 0 | AD8: =IFERROR(__xludf.DUMMYFUNCTION("""COMPUTED_VALUE"""),"") | AE8: =IFERROR(__xludf.DUMMYFUNCTION("""COMPUTED_VALUE"""),0.0) -> 0 | AF8: =IFERROR(__xludf.DUMMYFUNCTION("""COMPUTED_VALUE"""),0.0) -> 0 | AG8: =IFERROR(__xludf.DUMMYFUNCTION("""COMPUTED_VALUE"""),"") | AH8: =IFERROR(__xludf.DUMMYFUNCTION("""COMPUTED_VALUE"""),0.0) -> 0 | AI8: =IFERROR(__xludf.DUMMYFUNCTION("""COMPUTED_VALUE"""),0.0) -> 0 | AJ8: =IFERROR(__xludf.DUMMYFUNCTION("""COMPUTED_VALUE"""),"") | AK8: =IFERROR(__xludf.DUMMYFUNCTION("""COMPUTED_VALUE"""),0.0) -> 0 | AL8: =IFERROR(__xludf.DUMMYFUNCTION("""COMPUTED_VALUE"""),0.0) -> 0 | AM8: =IFERROR(__xludf.DUMMYFUNCTION("""COMPUTED_VALUE"""),"") | AN8: =IFERROR(__xludf.DUMMYFUNCTION("""COMPUTED_VALUE"""),0.0) -> 0 | AO8: =IFERROR(__xludf.DUMMYFUNCTION("""COMPUTED_VALUE"""),0.0) -> 0 | AP8: =IFERROR(__xludf.DUMMYFUNCTION("""COMPUTED_VALUE"""),"") | AQ8: =IFERROR(__xludf.DUMMYFUNCTION("""COMPUTED_VALUE"""),0.0) -> 0 | AR8: =IFERROR(__xludf.DUMMYFUNCTION("""COMPUTED_VALUE"""),0.0) -> 0 | AS8: =IFERROR(__xludf.DUMMYFUNCTION("""COMPUTED_VALUE"""),"") | AT8: =IFERROR(__xludf.DUMMYFUNCTION("""COMPUTED_VALUE"""),0.0) -> 0 | AU8: =IFERROR(__xludf.DUMMYFUNCTION("""COMPUTED_VALUE"""),0.0) -> 0 | AV8: =IFERROR(__xludf.DUMMYFUNCTION("""COMPUTED_VALUE"""),"") | AW8: =IFERROR(__xludf.DUMMYFUNCTION("""COMPUTED_VALUE"""),0.0) -> 0 | AX8: =IFERROR(__xludf.DUMMYFUNCTION("""COMPUTED_VALUE"""),0.0) -> 0 | AY8: =IFERROR(__xludf.DUMMYFUNCTION("""COMPUTED_VALUE"""),"") | AZ8: =IFERROR(__xludf.DUMMYFUNCTION("""COMPUTED_VALUE"""),0.0) -> 0 | BA8: =IFERROR(__xludf.DUMMYFUNCTION("""COMPUTED_VALUE"""),0.0) -> 0 | BB8: =IFERROR(__xludf.DUMMYFUNCTION("""COMPUTED_VALUE"""),"")
A9: =IFERROR(__xludf.DUMMYFUNCTION("""COMPUTED_VALUE"""),"63ef9d5f384f27260c1bb00d") -> 63ef9d5f384f27260c1bb00d | B9: =IFERROR(__xludf.DUMMYFUNCTION("""COMPUTED_VALUE"""),"ACUNTIA, S.A.") -> ACUNTIA, S.A. | C9: =IFERROR(__xludf.DUMMYFUNCTION("""COMPUTED_VALUE"""),"mario.madrid-bustos@al-enterprise.com, astrid.savorani@al-enterprise.com, marcos.rodriguez@al-enterprise.com") -> mario.madrid-bustos@al-enterprise.com, astrid.savorani@al-enterprise.com, marcos.rodriguez@al-enterprise.com | D9: =IFERROR(__xludf.DUMMYFUNCTION("""COMPUTED_VALUE"""),"emea") -> emea | E9: =IFERROR(__xludf.DUMMYFUNCTION("""COMPUTED_VALUE"""),"ES") -> ES | F9: =IFERROR(__xludf.DUMMYFUNCTION("""COMPUTED_VALUE"""),"expert_200") -> expert_200 | G9: =IFERROR(__xludf.DUMMYFUNCTION("""COMPUTED_VALUE"""),1.0) -> 1 | H9: =IFERROR(__xludf.DUMMYFUNCTION("""COMPUTED_VALUE"""),1.0) -> 1 | I9: =IFERROR(__xludf.DUMMYFUNCTION("""COMPUTED_VALUE"""),1.0) -> 1 | J9: =IFERROR(__xludf.DUMMYFUNCTION("""COMPUTED_VALUE"""),72.79) -> 72.79 | K9: =IFERROR(__xludf.DUMMYFUNCTION("""COMPUTED_VALUE"""),500.0) -> 500 | L9: =IFERROR(__xludf.DUMMYFUNCTION("""COMPUTED_VALUE"""),0.14558000000000001) -> 0.14558 | M9: =IFERROR(__xludf.DUMMYFUNCTION("""COMPUTED_VALUE"""),19.0) -> 19 | N9: =IFERROR(__xludf.DUMMYFUNCTION("""COMPUTED_VALUE"""),52.0) -> 52 | O9: =IFERROR(__xludf.DUMMYFUNCTION("""COMPUTED_VALUE"""),0.36538461538461536) -> 0.36538462 | P9: =IFERROR(__xludf.DUMMYFUNCTION("""COMPUTED_VALUE"""),0.0) -> 0 | Q9: =IFERROR(__xludf.DUMMYFUNCTION("""COMPUTED_VALUE"""),1.0) -> 1 | R9: =IFERROR(__xludf.DUMMYFUNCTION("""COMPUTED_VALUE"""),0.0) -> 0 | S9: =IFERROR(__xludf.DUMMYFUNCTION("""COMPUTED_VALUE"""),1.0) -> 1 | T9: =IFERROR(__xludf.DUMMYFUNCTION("""COMPUTED_VALUE"""),1.0) -> 1 | U9: =IFERROR(__xludf.DUMMYFUNCTION("""COMPUTED_VALUE"""),1.0) -> 1 | V9: =IFERROR(__xludf.DUMMYFUNCTION("""COMPUTED_VALUE"""),0.0) -> 0 | W9: =IFERROR(__xludf.DUMMYFUNCTION("""COMPUTED_VALUE"""),1.0) -> 1 | X9: =IFERROR(__xludf.DUMMYFUNCTION("""COMPUTED_VALUE"""),0.0) -> 0 | Y9: =IFERROR(__xludf.DUMMYFUNCTION("""COMPUTED_VALUE"""),0.0) -> 0 | Z9: =IFERROR(__xludf.DUMMYFUNCTION("""COMPUTED_VALUE"""),0.0) -> 0 | AA9: =IFERROR(__xludf.DUMMYFUNCTION("""COMPUTED_VALUE"""),"") | AB9: =IFERROR(__xludf.DUMMYFUNCTION("""COMPUTED_VALUE"""),230.0) -> 230 | AC9: =IFERROR(__xludf.DUMMYFUNCTION("""COMPUTED_VALUE"""),357.14) -> 357.14 | AD9: =IFERROR(__xludf.DUMMYFUNCTION("""COMPUTED_VALUE"""),0.6440051520412163) -> 0.64400515 | AE9: =IFERROR(__xludf.DUMMYFUNCTION("""COMPUTED_VALUE"""),85.0) -> 85 | AF9: =IFERROR(__xludf.DUMMYFUNCTION("""COMPUTED_VALUE"""),357.14) -> 357.14 | AG9: =IFERROR(__xludf.DUMMYFUNCTION("""COMPUTED_VALUE"""),0.23800190401523214) -> 0.2380019 | AH9: =IFERROR(__xludf.DUMMYFUNCTION("""COMPUTED_VALUE"""),400.0) -> 400 | AI9: =IFERROR(__xludf.DUMMYFUNCTION("""COMPUTED_VALUE"""),357.14) -> 357.14 | AJ9: =IFERROR(__xludf.DUMMYFUNCTION("""COMPUTED_VALUE"""),1.1200089600716807) -> 1.120009 | AK9: =IFERROR(__xludf.DUMMYFUNCTION("""COMPUTED_VALUE"""),715.0) -> 715 | AL9: =IFERROR(__xludf.DUMMYFUNCTION("""COMPUTED_VALUE"""),1071.42) -> 1071.42 | AM9: =IFERROR(__xludf.DUMMYFUNCTION("""COMPUTED_VALUE"""),0.6673386720427096) -> 0.66733867 | AN9: =IFERROR(__xludf.DUMMYFUNCTION("""COMPUTED_VALUE"""),780.0) -> 780 | AO9: =IFERROR(__xludf.DUMMYFUNCTION("""COMPUTED_VALUE"""),0.0) -> 0 | AP9: =IFERROR(__xludf.DUMMYFUNCTION("""COMPUTED_VALUE"""),"") | AQ9: =IFERROR(__xludf.DUMMYFUNCTION("""COMPUTED_VALUE"""),900.0) -> 900 | AR9: =IFERROR(__xludf.DUMMYFUNCTION("""COMPUTED_VALUE"""),0.0) -> 0 | AS9: =IFERROR(__xludf.DUMMYFUNCTION("""COMPUTED_VALUE"""),"") | AT9: =IFERROR(__xludf.DUMMYFUNCTION("""COMPUTED_VALUE"""),0.0) -> 0 | AU9: =IFERROR(__xludf.DUMMYFUNCTION("""COMPUTED_VALUE"""),0.0) -> 0 | AV9: =IFERROR(__xludf.DUMMYFUNCTION("""COMPUTED_VALUE"""),"") | AW9: =IFERROR(__xludf.DUMMYFUNCTION("""COMPUTED_VALUE"""),0.0) -> 0 | AX9: =IFERROR(__xludf.DUMMYFUNCTION("""COMPUTED_VALUE"""),0.0) -> 0 | AY9: =IFERROR(__xludf.DUMMYFUNCTION("""COMPUTED_VALUE"""),"") | AZ9: =IFERROR(__xludf.DUMMYFUNCTION("""COMPUTED_VALUE"""),1680.0) -> 1680 | BA9: =IFERROR(__xludf.DUMMYFUNCTION("""COMPUTED_VALUE"""),0.0) -> 0 | BB9: =IFERROR(__xludf.DUMMYFUNCTION("""COMPUTED_VALUE"""),"")
A10: =IFERROR(__xludf.DUMMYFUNCTION("""COMPUTED_VALUE"""),"63ced84dc5c820531c2696bc") -> 63ced84dc5c820531c2696bc | B10: =IFERROR(__xludf.DUMMYFUNCTION("""COMPUTED_VALUE"""),"ADVANCE 2000, Inc.") -> ADVANCE 2000, Inc. | C10: =IFERROR(__xludf.DUMMYFUNCTION("""COMPUTED_VALUE"""),"brendan.flaherty@al-enterprise.com, michael-j.francis@al-enterprise.com, Steve.roos@al-enterprise.com") -> brendan.flaherty@al-enterprise.com, michael-j.francis@al-enterprise.com, Steve.roos@al-enterprise.com | D10: =IFERROR(__xludf.DUMMYFUNCTION("""COMPUTED_VALUE"""),"americas") -> americas | E10: =IFERROR(__xludf.DUMMYFUNCTION("""COMPUTED_VALUE"""),"US") -> US | F10: =IFERROR(__xludf.DUMMYFUNCTION("""COMPUTED_VALUE"""),"expert_200") -> expert_200 | G10: =IFERROR(__xludf.DUMMYFUNCTION("""COMPUTED_VALUE"""),0.0) -> 0 | H10: =IFERROR(__xludf.DUMMYFUNCTION("""COMPUTED_VALUE"""),1.0) -> 1 | I10: =IFERROR(__xludf.DUMMYFUNCTION("""COMPUTED_VALUE"""),0.0) -> 0 | J10: =IFERROR(__xludf.DUMMYFUNCTION("""COMPUTED_VALUE"""),270.47) -> 270.47 | K10: =IFERROR(__xludf.DUMMYFUNCTION("""COMPUTED_VALUE"""),897.99) -> 897.99 | L10: =IFERROR(__xludf.DUMMYFUNCTION("""COMPUTED_VALUE"""),0.3011948908117017) -> 0.30119489 | M10: =IFERROR(__xludf.DUMMYFUNCTION("""COMPUTED_VALUE"""),20.0) -> 20 | N10: =IFERROR(__xludf.DUMMYFUNCTION("""COMPUTED_VALUE"""),0.0) -> 0 | O10: =IFERROR(__xludf.DUMMYFUNCTION("""COMPUTED_VALUE"""),"") | P10: =IFERROR(__xludf.DUMMYFUNCTION("""COMPUTED_VALUE"""),0.0) -> 0 | Q10: =IFERROR(__xludf.DUMMYFUNCTION("""COMPUTED_VALUE"""),1.0) -> 1 | R10: =IFERROR(__xludf.DUMMYFUNCTION("""COMPUTED_VALUE"""),0.0) -> 0 | S10: =IFERROR(__xludf.DUMMYFUNCTION("""COMPUTED_VALUE"""),0.0) -> 0 | T10: =IFERROR(__xludf.DUMMYFUNCTION("""COMPUTED_VALUE"""),1.0) -> 1 | U10: =IFERROR(__xludf.DUMMYFUNCTION("""COMPUTED_VALUE"""),0.0) -> 0 | V10: =IFERROR(__xludf.DUMMYFUNCTION("""COMPUTED_VALUE"""),0.0) -> 0 | W10: =IFERROR(__xludf.DUMMYFUNCTION("""COMPUTED_VALUE"""),1.0) -> 1 | X10: =IFERROR(__xludf.DUMMYFUNCTION("""COMPUTED_VALUE"""),0.0) -> 0 | Y10: =IFERROR(__xludf.DUMMYFUNCTION("""COMPUTED_VALUE"""),23.32) -> 23.32 | Z10: =IFERROR(__xludf.DUMMYFUNCTION("""COMPUTED_VALUE"""),0.0) -> 0 | AA10: =IFERROR(__xludf.DUMMYFUNCTION("""COMPUTED_VALUE"""),"") | AB10: =IFERROR(__xludf.DUMMYFUNCTION("""COMPUTED_VALUE"""),6.87) -> 6.87 | AC10: =IFERROR(__xludf.DUMMYFUNCTION("""COMPUTED_VALUE"""),279.68) -> 279.68 | AD10: =IFERROR(__xludf.DUMMYFUNCTION("""COMPUTED_VALUE"""),0.02456378718535469) -> 0.024563787 | AE10: =IFERROR(__xludf.DUMMYFUNCTION("""COMPUTED_VALUE"""),80.05) -> 80.05 | AF10: =IFERROR(__xludf.DUMMYFUNCTION("""COMPUTED_VALUE"""),421.86) -> 421.86 | AG10: =IFERROR(__xludf.DUMMYFUNCTION("""COMPUTED_VALUE"""),0.18975489498885886) -> 0.1897549 | AH10: =IFERROR(__xludf.DUMMYFUNCTION("""COMPUTED_VALUE"""),190.48) -> 190.48 | AI10: =IFERROR(__xludf.DUMMYFUNCTION("""COMPUTED_VALUE"""),421.86) -> 421.86 | AJ10: =IFERROR(__xludf.DUMMYFUNCTION("""COMPUTED_VALUE"""),0.4515242023420092) -> 0.4515242 | AK10: =IFERROR(__xludf.DUMMYFUNCTION("""COMPUTED_VALUE"""),300.71999999999997) -> 300.72 | AL10: =IFERROR(__xludf.DUMMYFUNCTION("""COMPUTED_VALUE"""),1123.4) -> 1123.4 | AM10: =IFERROR(__xludf.DUMMYFUNCTION("""COMPUTED_VALUE"""),0.267687377603703) -> 0.26768738 | AN10: =IFERROR(__xludf.DUMMYFUNCTION("""COMPUTED_VALUE"""),204.24) -> 204.24 | AO10: =IFERROR(__xludf.DUMMYFUNCTION("""COMPUTED_VALUE"""),0.0) -> 0 | AP10: =IFERROR(__xludf.DUMMYFUNCTION("""COMPUTED_VALUE"""),"") | AQ10: =IFERROR(__xludf.DUMMYFUNCTION("""COMPUTED_VALUE"""),280.0) -> 280 | AR10: =IFERROR(__xludf.DUMMYFUNCTION("""COMPUTED_VALUE"""),0.0) -> 0 | AS10: =IFERROR(__xludf.DUMMYFUNCTION("""COMPUTED_VALUE"""),"") | AT10: =IFERROR(__xludf.DUMMYFUNCTION("""COMPUTED_VALUE"""),4.51) -> 4.51 | AU10: =IFERROR(__xludf.DUMMYFUNCTION("""COMPUTED_VALUE"""),0.0) -> 0 | AV10: =IFERROR(__xludf.DUMMYFUNCTION("""COMPUTED_VALUE"""),"") | AW10: =IFERROR(__xludf.DUMMYFUNCTION("""COMPUTED_VALUE"""),0.0) -> 0 | AX10: =IFERROR(__xludf.DUMMYFUNCTION("""COMPUTED_VALUE"""),0.0) -> 0 | AY10: =IFERROR(__xludf.DUMMYFUNCTION("""COMPUTED_VALUE"""),"") | AZ10: =IFERROR(__xludf.DUMMYFUNCTION("""COMPUTED_VALUE"""),488.75) -> 488.75 | BA10: =IFERROR(__xludf.DUMMYFUNCTION("""COMPUTED_VALUE"""),0.0) -> 0 | BB10: =IFERROR(__xludf.DUMMYFUNCTION("""COMPUTED_VALUE"""),"")
A11: =IFERROR(__xludf.DUMMYFUNCTION("""COMPUTED_VALUE"""),"67eff15de0c0fe4c300b74f2") -> 67eff15de0c0fe4c300b74f2 | B11: =IFERROR(__xludf.DUMMYFUNCTION("""COMPUTED_VALUE"""),"AGORA SOLUCOES EM TECNOLOGIA DA INFORMACAO E COMUNICACAO S.A(DF)") -> AGORA SOLUCOES EM TECNOLOGIA DA INFORMACAO E COMUNICACAO S.A(DF) | C11: =IFERROR(__xludf.DUMMYFUNCTION("""COMPUTED_VALUE"""),"gabriel.pires@al-enterprise.com") -> gabriel.pires@al-enterprise.com | D11: =IFERROR(__xludf.DUMMYFUNCTION("""COMPUTED_VALUE"""),"americas") -> americas | E11: =IFERROR(__xludf.DUMMYFUNCTION("""COMPUTED_VALUE"""),"BR") -> BR | F11: =IFERROR(__xludf.DUMMYFUNCTION("""COMPUTED_VALUE"""),"distributor_1000") -> distributor_1000 | G11: =IFERROR(__xludf.DUMMYFUNCTION("""COMPUTED_VALUE"""),1.0) -> 1 | H11: =IFERROR(__xludf.DUMMYFUNCTION("""COMPUTED_VALUE"""),1.0) -> 1 | I11: =IFERROR(__xludf.DUMMYFUNCTION("""COMPUTED_VALUE"""),1.0) -> 1 | J11: =IFERROR(__xludf.DUMMYFUNCTION("""COMPUTED_VALUE"""),0.0) -> 0 | K11: =IFERROR(__xludf.DUMMYFUNCTION("""COMPUTED_VALUE"""),2399.98) -> 2399.98 | L11: =IFERROR(__xludf.DUMMYFUNCTION("""COMPUTED_VALUE"""),0.0) -> 0 | M11: =IFERROR(__xludf.DUMMYFUNCTION("""COMPUTED_VALUE"""),0.0) -> 0 | N11: =IFERROR(__xludf.DUMMYFUNCTION("""COMPUTED_VALUE"""),0.0) -> 0 | O11: =IFERROR(__xludf.DUMMYFUNCTION("""COMPUTED_VALUE"""),"") | P11: =IFERROR(__xludf.DUMMYFUNCTION("""COMPUTED_VALUE"""),0.0) -> 0 | Q11: =IFERROR(__xludf.DUMMYFUNCTION("""COMPUTED_VALUE"""),1.0) -> 1 | R11: =IFERROR(__xludf.DUMMYFUNCTION("""COMPUTED_VALUE"""),0.0) -> 0 | S11: =IFERROR(__xludf.DUMMYFUNCTION("""COMPUTED_VALUE"""),0.0) -> 0 | T11: =IFERROR(__xludf.DUMMYFUNCTION("""COMPUTED_VALUE"""),1.0) -> 1 | U11: =IFERROR(__xludf.DUMMYFUNCTION("""COMPUTED_VALUE"""),0.0) -> 0 | V11: =IFERROR(__xludf.DUMMYFUNCTION("""COMPUTED_VALUE"""),1.0) -> 1 | W11: =IFERROR(__xludf.DUMMYFUNCTION("""COMPUTED_VALUE"""),1.0) -> 1 | X11: =IFERROR(__xludf.DUMMYFUNCTION("""COMPUTED_VALUE"""),1.0) -> 1 | Y11: =IFERROR(__xludf.DUMMYFUNCTION("""COMPUTED_VALUE"""),0.0) -> 0 | Z11: =IFERROR(__xludf.DUMMYFUNCTION("""COMPUTED_VALUE"""),0.0) -> 0 | AA11: =IFERROR(__xludf.DUMMYFUNCTION("""COMPUTED_VALUE"""),"") | AB11: =IFERROR(__xludf.DUMMYFUNCTION("""COMPUTED_VALUE"""),440.0) -> 440 | AC11: =IFERROR(__xludf.DUMMYFUNCTION("""COMPUTED_VALUE"""),733.31) -> 733.31 | AD11: =IFERROR(__xludf.DUMMYFUNCTION("""COMPUTED_VALUE"""),0.6000190915165483) -> 0.60001909 | AE11: =IFERROR(__xludf.DUMMYFUNCTION("""COMPUTED_VALUE"""),440.0) -> 440 | AF11: =IFERROR(__xludf.DUMMYFUNCTION("""COMPUTED_VALUE"""),2499.96) -> 2499.96 | AG11: =IFERROR(__xludf.DUMMYFUNCTION("""COMPUTED_VALUE"""),0.17600281604505671) -> 0.17600282 | AH11: =IFERROR(__xludf.DUMMYFUNCTION("""COMPUTED_VALUE"""),1339.99) -> 1339.99 | AI11: =IFERROR(__xludf.DUMMYFUNCTION("""COMPUTED_VALUE"""),4033.28) -> 4033.28 | AJ11: =IFERROR(__xludf.DUMMYFUNCTION("""COMPUTED_VALUE"""),0.3322333187876864) -> 0.33223332 | AK11: =IFERROR(__xludf.DUMMYFUNCTION("""COMPUTED_VALUE"""),2219.99) -> 2219.99 | AL11: =IFERROR(__xludf.DUMMYFUNCTION("""COMPUTED_VALUE"""),7266.55) -> 7266.55 | AM11: =IFERROR(__xludf.DUMMYFUNCTION("""COMPUTED_VALUE"""),0.3055081159559901) -> 0.30550812 | AN11: =IFERROR(__xludf.DUMMYFUNCTION("""COMPUTED_VALUE"""),0.0) -> 0 | AO11: =IFERROR(__xludf.DUMMYFUNCTION("""COMPUTED_VALUE"""),0.0) -> 0 | AP11: =IFERROR(__xludf.DUMMYFUNCTION("""COMPUTED_VALUE"""),"") | AQ11: =IFERROR(__xludf.DUMMYFUNCTION("""COMPUTED_VALUE"""),0.0) -> 0 | AR11: =IFERROR(__xludf.DUMMYFUNCTION("""COMPUTED_VALUE"""),0.0) -> 0 | AS11: =IFERROR(__xludf.DUMMYFUNCTION("""COMPUTED_VALUE"""),"") | AT11: =IFERROR(__xludf.DUMMYFUNCTION("""COMPUTED_VALUE"""),0.0) -> 0 | AU11: =IFERROR(__xludf.DUMMYFUNCTION("""COMPUTED_VALUE"""),0.0) -> 0 | AV11: =IFERROR(__xludf.DUMMYFUNCTION("""COMPUTED_VALUE"""),"") | AW11: =IFERROR(__xludf.DUMMYFUNCTION("""COMPUTED_VALUE"""),0.0) -> 0 | AX11: =IFERROR(__xludf.DUMMYFUNCTION("""COMPUTED_VALUE"""),0.0) -> 0 | AY11: =IFERROR(__xludf.DUMMYFUNCTION("""COMPUTED_VALUE"""),"") | AZ11: =IFERROR(__xludf.DUMMYFUNCTION("""COMPUTED_VALUE"""),0.0) -> 0 | BA11: =IFERROR(__xludf.DUMMYFUNCTION("""COMPUTED_VALUE"""),0.0) -> 0 | BB11: =IFERROR(__xludf.DUMMYFUNCTION("""COMPUTED_VALUE"""),"")
A12: =IFERROR(__xludf.DUMMYFUNCTION("""COMPUTED_VALUE"""),"63ced845c5c820531c268663") -> 63ced845c5c820531c268663 | B12: =IFERROR(__xludf.DUMMYFUNCTION("""COMPUTED_VALUE"""),"ALBETA GmbH") -> ALBETA GmbH | C12: =IFERROR(__xludf.DUMMYFUNCTION("""COMPUTED_VALUE"""),"katrin.pfeiffer@al-enterprise.com, krystian.sokalski@al-enterprise.com, alena.charnaokaya@al-enterprise.com, sibylle.klopfer@al-enterprise.com, igor.leko@al-enterprise.com") -> katrin.pfeiffer@al-enterprise.com, krystian.sokalski@al-enterprise.com, alena.charnaokaya@al-enterprise.com, sibylle.klopfer@al-enterprise.com, igor.leko@al-enterprise.com | D12: =IFERROR(__xludf.DUMMYFUNCTION("""COMPUTED_VALUE"""),"germany") -> germany | E12: =IFERROR(__xludf.DUMMYFUNCTION("""COMPUTED_VALUE"""),"DE") -> DE | F12: =IFERROR(__xludf.DUMMYFUNCTION("""COMPUTED_VALUE"""),"expert_1000") -> expert_1000 | G12: =IFERROR(__xludf.DUMMYFUNCTION("""COMPUTED_VALUE"""),1.0) -> 1 | H12: =IFERROR(__xludf.DUMMYFUNCTION("""COMPUTED_VALUE"""),1.0) -> 1 | I12: =IFERROR(__xludf.DUMMYFUNCTION("""COMPUTED_VALUE"""),1.0) -> 1 | J12: =IFERROR(__xludf.DUMMYFUNCTION("""COMPUTED_VALUE"""),100.36) -> 100.36 | K12: =IFERROR(__xludf.DUMMYFUNCTION("""COMPUTED_VALUE"""),1145.99) -> 1145.99 | L12: =IFERROR(__xludf.DUMMYFUNCTION("""COMPUTED_VALUE"""),0.08757493520885871) -> 0.087574935 | M12: =IFERROR(__xludf.DUMMYFUNCTION("""COMPUTED_VALUE"""),29.0) -> 29 | N12: =IFERROR(__xludf.DUMMYFUNCTION("""COMPUTED_VALUE"""),52.0) -> 52 | O12: =IFERROR(__xludf.DUMMYFUNCTION("""COMPUTED_VALUE"""),0.5576923076923077) -> 0.55769231 | P12: =IFERROR(__xludf.DUMMYFUNCTION("""COMPUTED_VALUE"""),1.0) -> 1 | Q12: =IFERROR(__xludf.DUMMYFUNCTION("""COMPUTED_VALUE"""),1.0) -> 1 | R12: =IFERROR(__xludf.DUMMYFUNCTION("""COMPUTED_VALUE"""),1.0) -> 1 | S12: =IFERROR(__xludf.DUMMYFUNCTION("""COMPUTED_VALUE"""),0.0) -> 0 | T12: =IFERROR(__xludf.DUMMYFUNCTION("""COMPUTED_VALUE"""),1.0) -> 1 | U12: =IFERROR(__xludf.DUMMYFUNCTION("""COMPUTED_VALUE"""),0.0) -> 0 | V12: =IFERROR(__xludf.DUMMYFUNCTION("""COMPUTED_VALUE"""),0.0) -> 0 | W12: =IFERROR(__xludf.DUMMYFUNCTION("""COMPUTED_VALUE"""),1.0) -> 1 | X12: =IFERROR(__xludf.DUMMYFUNCTION("""COMPUTED_VALUE"""),0.0) -> 0 | Y12: =IFERROR(__xludf.DUMMYFUNCTION("""COMPUTED_VALUE"""),5.58) -> 5.58 | Z12: =IFERROR(__xludf.DUMMYFUNCTION("""COMPUTED_VALUE"""),0.0) -> 0 | AA12: =IFERROR(__xludf.DUMMYFUNCTION("""COMPUTED_VALUE"""),"") | AB12: =IFERROR(__xludf.DUMMYFUNCTION("""COMPUTED_VALUE"""),2.77) -> 2.77 | AC12: =IFERROR(__xludf.DUMMYFUNCTION("""COMPUTED_VALUE"""),177.95) -> 177.95 | AD12: =IFERROR(__xludf.DUMMYFUNCTION("""COMPUTED_VALUE"""),0.01556617027254847) -> 0.01556617 | AE12: =IFERROR(__xludf.DUMMYFUNCTION("""COMPUTED_VALUE"""),527.96) -> 527.96 | AF12: =IFERROR(__xludf.DUMMYFUNCTION("""COMPUTED_VALUE"""),376.35) -> 376.35 | AG12: =IFERROR(__xludf.DUMMYFUNCTION("""COMPUTED_VALUE"""),1.4028430981798858) -> 1.4028431 | AH12: =IFERROR(__xludf.DUMMYFUNCTION("""COMPUTED_VALUE"""),432.44) -> 432.44 | AI12: =IFERROR(__xludf.DUMMYFUNCTION("""COMPUTED_VALUE"""),629.03) -> 629.03 | AJ12: =IFERROR(__xludf.DUMMYFUNCTION("""COMPUTED_VALUE"""),0.6874711857940004) -> 0.68747119 | AK12: =IFERROR(__xludf.DUMMYFUNCTION("""COMPUTED_VALUE"""),968.75) -> 968.75 | AL12: =IFERROR(__xludf.DUMMYFUNCTION("""COMPUTED_VALUE"""),1183.33) -> 1183.33 | AM12: =IFERROR(__xludf.DUMMYFUNCTION("""COMPUTED_VALUE"""),0.8186642779275435) -> 0.81866428 | AN12: =IFERROR(__xludf.DUMMYFUNCTION("""COMPUTED_VALUE"""),1.48) -> 1.48 | AO12: =IFERROR(__xludf.DUMMYFUNCTION("""COMPUTED_VALUE"""),0.0) -> 0 | AP12: =IFERROR(__xludf.DUMMYFUNCTION("""COMPUTED_VALUE"""),"") | AQ12: =IFERROR(__xludf.DUMMYFUNCTION("""COMPUTED_VALUE"""),59.47) -> 59.47 | AR12: =IFERROR(__xludf.DUMMYFUNCTION("""COMPUTED_VALUE"""),0.0) -> 0 | AS12: =IFERROR(__xludf.DUMMYFUNCTION("""COMPUTED_VALUE"""),"") | AT12: =IFERROR(__xludf.DUMMYFUNCTION("""COMPUTED_VALUE"""),0.0) -> 0 | AU12: =IFERROR(__xludf.DUMMYFUNCTION("""COMPUTED_VALUE"""),0.0) -> 0 | AV12: =IFERROR(__xludf.DUMMYFUNCTION("""COMPUTED_VALUE"""),"") | AW12: =IFERROR(__xludf.DUMMYFUNCTION("""COMPUTED_VALUE"""),38.12) -> 38.12 | AX12: =IFERROR(__xludf.DUMMYFUNCTION("""COMPUTED_VALUE"""),0.0) -> 0 | AY12: =IFERROR(__xludf.DUMMYFUNCTION("""COMPUTED_VALUE"""),"") | AZ12: =IFERROR(__xludf.DUMMYFUNCTION("""COMPUTED_VALUE"""),99.07) -> 99.07 | BA12: =IFERROR(__xludf.DUMMYFUNCTION("""COMPUTED_VALUE"""),0.0) -> 0 | BB12: =IFERROR(__xludf.DUMMYFUNCTION("""COMPUTED_VALUE"""),"")
A13: =IFERROR(__xludf.DUMMYFUNCTION("""COMPUTED_VALUE"""),"63ced84ac5c820531c2690e0") -> 63ced84ac5c820531c2690e0 | B13: =IFERROR(__xludf.DUMMYFUNCTION("""COMPUTED_VALUE"""),"Alca Enterprise, Corp.") -> Alca Enterprise, Corp. | C13: =IFERROR(__xludf.DUMMYFUNCTION("""COMPUTED_VALUE"""),"jorge.silva@al-enterprise.com") -> jorge.silva@al-enterprise.com | D13: =IFERROR(__xludf.DUMMYFUNCTION("""COMPUTED_VALUE"""),"americas") -> americas | E13: =IFERROR(__xludf.DUMMYFUNCTION("""COMPUTED_VALUE"""),"PA") -> PA | F13: =IFERROR(__xludf.DUMMYFUNCTION("""COMPUTED_VALUE"""),"distributor") -> distributor | G13: =IFERROR(__xludf.DUMMYFUNCTION("""COMPUTED_VALUE"""),0.0) -> 0 | H13: =IFERROR(__xludf.DUMMYFUNCTION("""COMPUTED_VALUE"""),1.0) -> 1 | I13: =IFERROR(__xludf.DUMMYFUNCTION("""COMPUTED_VALUE"""),0.0) -> 0 | J13: =IFERROR(__xludf.DUMMYFUNCTION("""COMPUTED_VALUE"""),139.59) -> 139.59 | K13: =IFERROR(__xludf.DUMMYFUNCTION("""COMPUTED_VALUE"""),434.0) -> 434 | L13: =IFERROR(__xludf.DUMMYFUNCTION("""COMPUTED_VALUE"""),0.32163594470046086) -> 0.32163594 | M13: =IFERROR(__xludf.DUMMYFUNCTION("""COMPUTED_VALUE"""),2.0) -> 2 | N13: =IFERROR(__xludf.DUMMYFUNCTION("""COMPUTED_VALUE"""),56.0) -> 56 | O13: =IFERROR(__xludf.DUMMYFUNCTION("""COMPUTED_VALUE"""),0.03571428571428571) -> 0.035714286 | P13: =IFERROR(__xludf.DUMMYFUNCTION("""COMPUTED_VALUE"""),0.0) -> 0 | Q13: =IFERROR(__xludf.DUMMYFUNCTION("""COMPUTED_VALUE"""),1.0) -> 1 | R13: =IFERROR(__xludf.DUMMYFUNCTION("""COMPUTED_VALUE"""),0.0) -> 0 | S13: =IFERROR(__xludf.DUMMYFUNCTION("""COMPUTED_VALUE"""),0.0) -> 0 | T13: =IFERROR(__xludf.DUMMYFUNCTION("""COMPUTED_VALUE"""),1.0) -> 1 | U13: =IFERROR(__xludf.DUMMYFUNCTION("""COMPUTED_VALUE"""),0.0) -> 0 | V13: =IFERROR(__xludf.DUMMYFUNCTION("""COMPUTED_VALUE"""),0.0) -> 0 | W13: =IFERROR(__xludf.DUMMYFUNCTION("""COMPUTED_VALUE"""),1.0) -> 1 | X13: =IFERROR(__xludf.DUMMYFUNCTION("""COMPUTED_VALUE"""),0.0) -> 0 | Y13: =IFERROR(__xludf.DUMMYFUNCTION("""COMPUTED_VALUE"""),2.2) -> 2.2 | Z13: =IFERROR(__xludf.DUMMYFUNCTION("""COMPUTED_VALUE"""),0.0) -> 0 | AA13: =IFERROR(__xludf.DUMMYFUNCTION("""COMPUTED_VALUE"""),"") | AB13: =IFERROR(__xludf.DUMMYFUNCTION("""COMPUTED_VALUE"""),2.2) -> 2.2 | AC13: =IFERROR(__xludf.DUMMYFUNCTION("""COMPUTED_VALUE"""),885.73) -> 885.73 | AD13: =IFERROR(__xludf.DUMMYFUNCTION("""COMPUTED_VALUE"""),0.0024838268998453256) -> 0.0024838269 | AE13: =IFERROR(__xludf.DUMMYFUNCTION("""COMPUTED_VALUE"""),15.39) -> 15.39 | AF13: =IFERROR(__xludf.DUMMYFUNCTION("""COMPUTED_VALUE"""),921.38) -> 921.38 | AG13: =IFERROR(__xludf.DUMMYFUNCTION("""COMPUTED_VALUE"""),0.016703206060474506) -> 0.016703206 | AH13: =IFERROR(__xludf.DUMMYFUNCTION("""COMPUTED_VALUE"""),3.53) -> 3.53 | AI13: =IFERROR(__xludf.DUMMYFUNCTION("""COMPUTED_VALUE"""),935.68) -> 935.68 | AJ13: =IFERROR(__xludf.DUMMYFUNCTION("""COMPUTED_VALUE"""),0.00377265731874145) -> 0.0037726573 | AK13: =IFERROR(__xludf.DUMMYFUNCTION("""COMPUTED_VALUE"""),23.32) -> 23.32 | AL13: =IFERROR(__xludf.DUMMYFUNCTION("""COMPUTED_VALUE"""),2742.79) -> 2742.79 | AM13: =IFERROR(__xludf.DUMMYFUNCTION("""COMPUTED_VALUE"""),0.00850229146234309) -> 0.0085022915 | AN13: =IFERROR(__xludf.DUMMYFUNCTION("""COMPUTED_VALUE"""),0.0) -> 0 | AO13: =IFERROR(__xludf.DUMMYFUNCTION("""COMPUTED_VALUE"""),0.0) -> 0 | AP13: =IFERROR(__xludf.DUMMYFUNCTION("""COMPUTED_VALUE"""),"") | AQ13: =IFERROR(__xludf.DUMMYFUNCTION("""COMPUTED_VALUE"""),0.0) -> 0 | AR13: =IFERROR(__xludf.DUMMYFUNCTION("""COMPUTED_VALUE"""),0.0) -> 0 | AS13: =IFERROR(__xludf.DUMMYFUNCTION("""COMPUTED_VALUE"""),"") | AT13: =IFERROR(__xludf.DUMMYFUNCTION("""COMPUTED_VALUE"""),0.0) -> 0 | AU13: =IFERROR(__xludf.DUMMYFUNCTION("""COMPUTED_VALUE"""),0.0) -> 0 | AV13: =IFERROR(__xludf.DUMMYFUNCTION("""COMPUTED_VALUE"""),"") | AW13: =IFERROR(__xludf.DUMMYFUNCTION("""COMPUTED_VALUE"""),0.0) -> 0 | AX13: =IFERROR(__xludf.DUMMYFUNCTION("""COMPUTED_VALUE"""),0.0) -> 0 | AY13: =IFERROR(__xludf.DUMMYFUNCTION("""COMPUTED_VALUE"""),"") | AZ13: =IFERROR(__xludf.DUMMYFUNCTION("""COMPUTED_VALUE"""),0.0) -> 0 | BA13: =IFERROR(__xludf.DUMMYFUNCTION("""COMPUTED_VALUE"""),0.0) -> 0 | BB13: =IFERROR(__xludf.DUMMYFUNCTION("""COMPUTED_VALUE"""),"")
A14: =IFERROR(__xludf.DUMMYFUNCTION("""COMPUTED_VALUE"""),"63ced843c5c820531c268168") -> 63ced843c5c820531c268168 | B14: =IFERROR(__xludf.DUMMYFUNCTION("""COMPUTED_VALUE"""),"ALCTEL TELECOM") -> ALCTEL TELECOM | C14: =IFERROR(__xludf.DUMMYFUNCTION("""COMPUTED_VALUE"""),"renato-takashi.yoshizako@al-enterprise.com") -> renato-takashi.yoshizako@al-enterprise.com | D14: =IFERROR(__xludf.DUMMYFUNCTION("""COMPUTED_VALUE"""),"americas") -> americas | E14: =IFERROR(__xludf.DUMMYFUNCTION("""COMPUTED_VALUE"""),"BR") -> BR | F14: =IFERROR(__xludf.DUMMYFUNCTION("""COMPUTED_VALUE"""),"expert_1000") -> expert_1000 | G14: =IFERROR(__xludf.DUMMYFUNCTION("""COMPUTED_VALUE"""),1.0) -> 1 | H14: =IFERROR(__xludf.DUMMYFUNCTION("""COMPUTED_VALUE"""),1.0) -> 1 | I14: =IFERROR(__xludf.DUMMYFUNCTION("""COMPUTED_VALUE"""),1.0) -> 1 | J14: =IFERROR(__xludf.DUMMYFUNCTION("""COMPUTED_VALUE"""),65.65) -> 65.65 | K14: =IFERROR(__xludf.DUMMYFUNCTION("""COMPUTED_VALUE"""),1549.99) -> 1549.99 | L14: =IFERROR(__xludf.DUMMYFUNCTION("""COMPUTED_VALUE"""),0.042355111968464317) -> 0.042355112 | M14: =IFERROR(__xludf.DUMMYFUNCTION("""COMPUTED_VALUE"""),48.0) -> 48 | N14: =IFERROR(__xludf.DUMMYFUNCTION("""COMPUTED_VALUE"""),40.0) -> 40 | O14: =IFERROR(__xludf.DUMMYFUNCTION("""COMPUTED_VALUE"""),1.2) -> 1.2 | P14: =IFERROR(__xludf.DUMMYFUNCTION("""COMPUTED_VALUE"""),1.0) -> 1 | Q14: =IFERROR(__xludf.DUMMYFUNCTION("""COMPUTED_VALUE"""),1.0) -> 1 | R14: =IFERROR(__xludf.DUMMYFUNCTION("""COMPUTED_VALUE"""),1.0) -> 1 | S14: =IFERROR(__xludf.DUMMYFUNCTION("""COMPUTED_VALUE"""),1.0) -> 1 | T14: =IFERROR(__xludf.DUMMYFUNCTION("""COMPUTED_VALUE"""),1.0) -> 1 | U14: =IFERROR(__xludf.DUMMYFUNCTION("""COMPUTED_VALUE"""),1.0) -> 1 | V14: =IFERROR(__xludf.DUMMYFUNCTION("""COMPUTED_VALUE"""),0.0) -> 0 | W14: =IFERROR(__xludf.DUMMYFUNCTION("""COMPUTED_VALUE"""),1.0) -> 1 | X14: =IFERROR(__xludf.DUMMYFUNCTION("""COMPUTED_VALUE"""),0.0) -> 0 | Y14: =IFERROR(__xludf.DUMMYFUNCTION("""COMPUTED_VALUE"""),13.85) -> 13.85 | Z14: =IFERROR(__xludf.DUMMYFUNCTION("""COMPUTED_VALUE"""),0.0) -> 0 | AA14: =IFERROR(__xludf.DUMMYFUNCTION("""COMPUTED_VALUE"""),"") | AB14: =IFERROR(__xludf.DUMMYFUNCTION("""COMPUTED_VALUE"""),6.13) -> 6.13 | AC14: =IFERROR(__xludf.DUMMYFUNCTION("""COMPUTED_VALUE"""),1291.67) -> 1291.67 | AD14: =IFERROR(__xludf.DUMMYFUNCTION("""COMPUTED_VALUE"""),0.004745794204402053) -> 0.0047457942 | AE14: =IFERROR(__xludf.DUMMYFUNCTION("""COMPUTED_VALUE"""),229.14) -> 229.14 | AF14: =IFERROR(__xludf.DUMMYFUNCTION("""COMPUTED_VALUE"""),1291.67) -> 1291.67 | AG14: =IFERROR(__xludf.DUMMYFUNCTION("""COMPUTED_VALUE"""),0.177398251875479) -> 0.17739825 | AH14: =IFERROR(__xludf.DUMMYFUNCTION("""COMPUTED_VALUE"""),1124.39) -> 1124.39 | AI14: =IFERROR(__xludf.DUMMYFUNCTION("""COMPUTED_VALUE"""),1291.67) -> 1291.67 | AJ14: =IFERROR(__xludf.DUMMYFUNCTION("""COMPUTED_VALUE"""),0.8704932374368066) -> 0.87049324 | AK14: =IFERROR(__xludf.DUMMYFUNCTION("""COMPUTED_VALUE"""),1373.51) -> 1373.51 | AL14: =IFERROR(__xludf.DUMMYFUNCTION("""COMPUTED_VALUE"""),3875.01) -> 3875.01 | AM14: =IFERROR(__xludf.DUMMYFUNCTION("""COMPUTED_VALUE"""),0.35445327883024813) -> 0.35445328 | AN14: =IFERROR(__xludf.DUMMYFUNCTION("""COMPUTED_VALUE"""),1.47) -> 1.47 | AO14: =IFERROR(__xludf.DUMMYFUNCTION("""COMPUTED_VALUE"""),0.0) -> 0 | AP14: =IFERROR(__xludf.DUMMYFUNCTION("""COMPUTED_VALUE"""),"") | AQ14: =IFERROR(__xludf.DUMMYFUNCTION("""COMPUTED_VALUE"""),110.0) -> 110 | AR14: =IFERROR(__xludf.DUMMYFUNCTION("""COMPUTED_VALUE"""),0.0) -> 0 | AS14: =IFERROR(__xludf.DUMMYFUNCTION("""COMPUTED_VALUE"""),"") | AT14: =IFERROR(__xludf.DUMMYFUNCTION("""COMPUTED_VALUE"""),0.0) -> 0 | AU14: =IFERROR(__xludf.DUMMYFUNCTION("""COMPUTED_VALUE"""),0.0) -> 0 | AV14: =IFERROR(__xludf.DUMMYFUNCTION("""COMPUTED_VALUE"""),"") | AW14: =IFERROR(__xludf.DUMMYFUNCTION("""COMPUTED_VALUE"""),0.0) -> 0 | AX14: =IFERROR(__xludf.DUMMYFUNCTION("""COMPUTED_VALUE"""),0.0) -> 0 | AY14: =IFERROR(__xludf.DUMMYFUNCTION("""COMPUTED_VALUE"""),"") | AZ14: =IFERROR(__xludf.DUMMYFUNCTION("""COMPUTED_VALUE"""),111.47) -> 111.47 | BA14: =IFERROR(__xludf.DUMMYFUNCTION("""COMPUTED_VALUE"""),0.0) -> 0 | BB14: =IFERROR(__xludf.DUMMYFUNCTION("""COMPUTED_VALUE"""),"")
A15: =IFERROR(__xludf.DUMMYFUNCTION("""COMPUTED_VALUE"""),"63ced849c5c820531c268f5a") -> 63ced849c5c820531c268f5a | B15: =IFERROR(__xludf.DUMMYFUNCTION("""COMPUTED_VALUE"""),"ALSO Deutschland GmbH") -> ALSO Deutschland GmbH | C15: =IFERROR(__xludf.DUMMYFUNCTION("""COMPUTED_VALUE"""),"michael.moog@al-enterprise.com, katrin.pfeiffer@al-enterprise.com, sibylle.klopfer@al-enterprise.com, igor.leko@al-enterprise.com") -> michael.moog@al-enterprise.com, katrin.pfeiffer@al-enterprise.com, sibylle.klopfer@al-enterprise.com, igor.leko@al-enterprise.com | D15: =IFERROR(__xludf.DUMMYFUNCTION("""COMPUTED_VALUE"""),"germany") -> germany | E15: =IFERROR(__xludf.DUMMYFUNCTION("""COMPUTED_VALUE"""),"DE") -> DE | F15: =IFERROR(__xludf.DUMMYFUNCTION("""COMPUTED_VALUE"""),"distributor_1000") -> distributor_1000 | G15: =IFERROR(__xludf.DUMMYFUNCTION("""COMPUTED_VALUE"""),0.0) -> 0 | H15: =IFERROR(__xludf.DUMMYFUNCTION("""COMPUTED_VALUE"""),1.0) -> 1 | I15: =IFERROR(__xludf.DUMMYFUNCTION("""COMPUTED_VALUE"""),0.0) -> 0 | J15: =IFERROR(__xludf.DUMMYFUNCTION("""COMPUTED_VALUE"""),2756.73) -> 2756.73 | K15: =IFERROR(__xludf.DUMMYFUNCTION("""COMPUTED_VALUE"""),5340.0) -> 5340 | L15: =IFERROR(__xludf.DUMMYFUNCTION("""COMPUTED_VALUE"""),0.5162415730337079) -> 0.51624157 | M15: =IFERROR(__xludf.DUMMYFUNCTION("""COMPUTED_VALUE"""),27.0) -> 27 | N15: =IFERROR(__xludf.DUMMYFUNCTION("""COMPUTED_VALUE"""),52.0) -> 52 | O15: =IFERROR(__xludf.DUMMYFUNCTION("""COMPUTED_VALUE"""),0.5192307692307693) -> 0.51923077 | P15: =IFERROR(__xludf.DUMMYFUNCTION("""COMPUTED_VALUE"""),1.0) -> 1 | Q15: =IFERROR(__xludf.DUMMYFUNCTION("""COMPUTED_VALUE"""),1.0) -> 1 | R15: =IFERROR(__xludf.DUMMYFUNCTION("""COMPUTED_VALUE"""),1.0) -> 1 | S15: =IFERROR(__xludf.DUMMYFUNCTION("""COMPUTED_VALUE"""),0.0) -> 0 | T15: =IFERROR(__xludf.DUMMYFUNCTION("""COMPUTED_VALUE"""),1.0) -> 1 | U15: =IFERROR(__xludf.DUMMYFUNCTION("""COMPUTED_VALUE"""),0.0) -> 0 | V15: =IFERROR(__xludf.DUMMYFUNCTION("""COMPUTED_VALUE"""),0.0) -> 0 | W15: =IFERROR(__xludf.DUMMYFUNCTION("""COMPUTED_VALUE"""),1.0) -> 1 | X15: =IFERROR(__xludf.DUMMYFUNCTION("""COMPUTED_VALUE"""),0.0) -> 0 | Y15: =IFERROR(__xludf.DUMMYFUNCTION("""COMPUTED_VALUE"""),14.52) -> 14.52 | Z15: =IFERROR(__xludf.DUMMYFUNCTION("""COMPUTED_VALUE"""),0.0) -> 0 | AA15: =IFERROR(__xludf.DUMMYFUNCTION("""COMPUTED_VALUE"""),"") | AB15: =IFERROR(__xludf.DUMMYFUNCTION("""COMPUTED_VALUE"""),7.05) -> 7.05 | AC15: =IFERROR(__xludf.DUMMYFUNCTION("""COMPUTED_VALUE"""),1066.67) -> 1066.67 | AD15: =IFERROR(__xludf.DUMMYFUNCTION("""COMPUTED_VALUE"""),0.006609354345767669) -> 0.0066093543 | AE15: =IFERROR(__xludf.DUMMYFUNCTION("""COMPUTED_VALUE"""),318.42) -> 318.42 | AF15: =IFERROR(__xludf.DUMMYFUNCTION("""COMPUTED_VALUE"""),1600.0) -> 1600 | AG15: =IFERROR(__xludf.DUMMYFUNCTION("""COMPUTED_VALUE"""),0.1990125) -> 0.1990125 | AH15: =IFERROR(__xludf.DUMMYFUNCTION("""COMPUTED_VALUE"""),282.09) -> 282.09 | AI15: =IFERROR(__xludf.DUMMYFUNCTION("""COMPUTED_VALUE"""),1600.0) -> 1600 | AJ15: =IFERROR(__xludf.DUMMYFUNCTION("""COMPUTED_VALUE"""),0.17630625) -> 0.17630625 | AK15: =IFERROR(__xludf.DUMMYFUNCTION("""COMPUTED_VALUE"""),622.0799999999999) -> 622.08 | AL15: =IFERROR(__xludf.DUMMYFUNCTION("""COMPUTED_VALUE"""),4266.67) -> 4266.67 | AM15: =IFERROR(__xludf.DUMMYFUNCTION("""COMPUTED_VALUE"""),0.14579988609383898) -> 0.14579989 | AN15: =IFERROR(__xludf.DUMMYFUNCTION("""COMPUTED_VALUE"""),17.75) -> 17.75 | AO15: =IFERROR(__xludf.DUMMYFUNCTION("""COMPUTED_VALUE"""),0.0) -> 0 | AP15: =IFERROR(__xludf.DUMMYFUNCTION("""COMPUTED_VALUE"""),"") | AQ15: =IFERROR(__xludf.DUMMYFUNCTION("""COMPUTED_VALUE"""),114.76) -> 114.76 | AR15: =IFERROR(__xludf.DUMMYFUNCTION("""COMPUTED_VALUE"""),0.0) -> 0 | AS15: =IFERROR(__xludf.DUMMYFUNCTION("""COMPUTED_VALUE"""),"") | AT15: =IFERROR(__xludf.DUMMYFUNCTION("""COMPUTED_VALUE"""),27.16) -> 27.16 | AU15: =IFERROR(__xludf.DUMMYFUNCTION("""COMPUTED_VALUE"""),0.0) -> 0 | AV15: =IFERROR(__xludf.DUMMYFUNCTION("""COMPUTED_VALUE"""),"") | AW15: =IFERROR(__xludf.DUMMYFUNCTION("""COMPUTED_VALUE"""),52.99) -> 52.99 | AX15: =IFERROR(__xludf.DUMMYFUNCTION("""COMPUTED_VALUE"""),0.0) -> 0 | AY15: =IFERROR(__xludf.DUMMYFUNCTION("""COMPUTED_VALUE"""),"") | AZ15: =IFERROR(__xludf.DUMMYFUNCTION("""COMPUTED_VALUE"""),212.66) -> 212.66 | BA15: =IFERROR(__xludf.DUMMYFUNCTION("""COMPUTED_VALUE"""),0.0) -> 0 | BB15: =IFERROR(__xludf.DUMMYFUNCTION("""COMPUTED_VALUE"""),"")
A16: =IFERROR(__xludf.DUMMYFUNCTION("""COMPUTED_VALUE"""),"63ced846c5c820531c2687f8") -> 63ced846c5c820531c2687f8 | B16: =IFERROR(__xludf.DUMMYFUNCTION("""COMPUTED_VALUE"""),"AMBAR TELECOMUNICACIONES SL") -> AMBAR TELECOMUNICACIONES SL | C16: =IFERROR(__xludf.DUMMYFUNCTION("""COMPUTED_VALUE"""),"mario.madrid-bustos@al-enterprise.com, astrid.savorani@al-enterprise.com, marcos.rodriguez@al-enterprise.com, borja.gonzalvez@al-enterprise.com") -> mario.madrid-bustos@al-enterprise.com, astrid.savorani@al-enterprise.com, marcos.rodriguez@al-enterprise.com, borja.gonzalvez@al-enterprise.com | D16: =IFERROR(__xludf.DUMMYFUNCTION("""COMPUTED_VALUE"""),"emea") -> emea | E16: =IFERROR(__xludf.DUMMYFUNCTION("""COMPUTED_VALUE"""),"ES") -> ES | F16: =IFERROR(__xludf.DUMMYFUNCTION("""COMPUTED_VALUE"""),"expert_200") -> expert_200 | G16: =IFERROR(__xludf.DUMMYFUNCTION("""COMPUTED_VALUE"""),1.0) -> 1 | H16: =IFERROR(__xludf.DUMMYFUNCTION("""COMPUTED_VALUE"""),1.0) -> 1 | I16: =IFERROR(__xludf.DUMMYFUNCTION("""COMPUTED_VALUE"""),1.0) -> 1 | J16: =IFERROR(__xludf.DUMMYFUNCTION("""COMPUTED_VALUE"""),17.22) -> 17.22 | K16: =IFERROR(__xludf.DUMMYFUNCTION("""COMPUTED_VALUE"""),550.0) -> 550 | L16: =IFERROR(__xludf.DUMMYFUNCTION("""COMPUTED_VALUE"""),0.031309090909090904) -> 0.031309091 | M16: =IFERROR(__xludf.DUMMYFUNCTION("""COMPUTED_VALUE"""),16.0) -> 16 | N16: =IFERROR(__xludf.DUMMYFUNCTION("""COMPUTED_VALUE"""),52.0) -> 52 | O16: =IFERROR(__xludf.DUMMYFUNCTION("""COMPUTED_VALUE"""),0.3076923076923077) -> 0.30769231 | P16: =IFERROR(__xludf.DUMMYFUNCTION("""COMPUTED_VALUE"""),0.0) -> 0 | Q16: =IFERROR(__xludf.DUMMYFUNCTION("""COMPUTED_VALUE"""),1.0) -> 1 | R16: =IFERROR(__xludf.DUMMYFUNCTION("""COMPUTED_VALUE"""),0.0) -> 0 | S16: =IFERROR(__xludf.DUMMYFUNCTION("""COMPUTED_VALUE"""),1.0) -> 1 | T16: =IFERROR(__xludf.DUMMYFUNCTION("""COMPUTED_VALUE"""),1.0) -> 1 | U16: =IFERROR(__xludf.DUMMYFUNCTION("""COMPUTED_VALUE"""),1.0) -> 1 | V16: =IFERROR(__xludf.DUMMYFUNCTION("""COMPUTED_VALUE"""),0.0) -> 0 | W16: =IFERROR(__xludf.DUMMYFUNCTION("""COMPUTED_VALUE"""),1.0) -> 1 | X16: =IFERROR(__xludf.DUMMYFUNCTION("""COMPUTED_VALUE"""),0.0) -> 0 | Y16: =IFERROR(__xludf.DUMMYFUNCTION("""COMPUTED_VALUE"""),5.7) -> 5.7 | Z16: =IFERROR(__xludf.DUMMYFUNCTION("""COMPUTED_VALUE"""),0.0) -> 0 | AA16: =IFERROR(__xludf.DUMMYFUNCTION("""COMPUTED_VALUE"""),"") | AB16: =IFERROR(__xludf.DUMMYFUNCTION("""COMPUTED_VALUE"""),85.0) -> 85 | AC16: =IFERROR(__xludf.DUMMYFUNCTION("""COMPUTED_VALUE"""),327.38) -> 327.38 | AD16: =IFERROR(__xludf.DUMMYFUNCTION("""COMPUTED_VALUE"""),0.25963711894434605) -> 0.25963712 | AE16: =IFERROR(__xludf.DUMMYFUNCTION("""COMPUTED_VALUE"""),111.0) -> 111 | AF16: =IFERROR(__xludf.DUMMYFUNCTION("""COMPUTED_VALUE"""),327.38) -> 327.38 | AG16: =IFERROR(__xludf.DUMMYFUNCTION("""COMPUTED_VALUE"""),0.3390555317979107) -> 0.33905553 | AH16: =IFERROR(__xludf.DUMMYFUNCTION("""COMPUTED_VALUE"""),20.0) -> 20 | AI16: =IFERROR(__xludf.DUMMYFUNCTION("""COMPUTED_VALUE"""),327.38) -> 327.38 | AJ16: =IFERROR(__xludf.DUMMYFUNCTION("""COMPUTED_VALUE"""),0.06109108681043436) -> 0.061091087 | AK16: =IFERROR(__xludf.DUMMYFUNCTION("""COMPUTED_VALUE"""),221.7) -> 221.7 | AL16: =IFERROR(__xludf.DUMMYFUNCTION("""COMPUTED_VALUE"""),982.14) -> 982.14 | AM16: =IFERROR(__xludf.DUMMYFUNCTION("""COMPUTED_VALUE"""),0.22573156576455494) -> 0.22573157 | AN16: =IFERROR(__xludf.DUMMYFUNCTION("""COMPUTED_VALUE"""),0.0) -> 0 | AO16: =IFERROR(__xludf.DUMMYFUNCTION("""COMPUTED_VALUE"""),0.0) -> 0 | AP16: =IFERROR(__xludf.DUMMYFUNCTION("""COMPUTED_VALUE"""),"") | AQ16: =IFERROR(__xludf.DUMMYFUNCTION("""COMPUTED_VALUE"""),0.0) -> 0 | AR16: =IFERROR(__xludf.DUMMYFUNCTION("""COMPUTED_VALUE"""),0.0) -> 0 | AS16: =IFERROR(__xludf.DUMMYFUNCTION("""COMPUTED_VALUE"""),"") | AT16: =IFERROR(__xludf.DUMMYFUNCTION("""COMPUTED_VALUE"""),0.0) -> 0 | AU16: =IFERROR(__xludf.DUMMYFUNCTION("""COMPUTED_VALUE"""),0.0) -> 0 | AV16: =IFERROR(__xludf.DUMMYFUNCTION("""COMPUTED_VALUE"""),"") | AW16: =IFERROR(__xludf.DUMMYFUNCTION("""COMPUTED_VALUE"""),0.0) -> 0 | AX16: =IFERROR(__xludf.DUMMYFUNCTION("""COMPUTED_VALUE"""),0.0) -> 0 | AY16: =IFERROR(__xludf.DUMMYFUNCTION("""COMPUTED_VALUE"""),"") | AZ16: =IFERROR(__xludf.DUMMYFUNCTION("""COMPUTED_VALUE"""),0.0) -> 0 | BA16: =IFERROR(__xludf.DUMMYFUNCTION("""COMPUTED_VALUE"""),0.0) -> 0 | BB16: =IFERROR(__xludf.DUMMYFUNCTION("""COMPUTED_VALUE"""),"")
A17: =IFERROR(__xludf.DUMMYFUNCTION("""COMPUTED_VALUE"""),"63ef9d5c384f27260c1baa7f") -> 63ef9d5c384f27260c1baa7f | B17: =IFERROR(__xludf.DUMMYFUNCTION("""COMPUTED_VALUE"""),"APLICACIONES ELECTRICAS ENE") -> APLICACIONES ELECTRICAS ENE | C17: =IFERROR(__xludf.DUMMYFUNCTION("""COMPUTED_VALUE"""),"mario.madrid-bustos@al-enterprise.com, astrid.savorani@al-enterprise.com, marcos.rodriguez@al-enterprise.com, borja.gonzalvez@al-enterprise.com") -> mario.madrid-bustos@al-enterprise.com, astrid.savorani@al-enterprise.com, marcos.rodriguez@al-enterprise.com, borja.gonzalvez@al-enterprise.com | D17: =IFERROR(__xludf.DUMMYFUNCTION("""COMPUTED_VALUE"""),"emea") -> emea | E17: =IFERROR(__xludf.DUMMYFUNCTION("""COMPUTED_VALUE"""),"ES") -> ES | F17: =IFERROR(__xludf.DUMMYFUNCTION("""COMPUTED_VALUE"""),"expert_200") -> expert_200 | G17: =IFERROR(__xludf.DUMMYFUNCTION("""COMPUTED_VALUE"""),1.0) -> 1 | H17: =IFERROR(__xludf.DUMMYFUNCTION("""COMPUTED_VALUE"""),1.0) -> 1 | I17: =IFERROR(__xludf.DUMMYFUNCTION("""COMPUTED_VALUE"""),1.0) -> 1 | J17: =IFERROR(__xludf.DUMMYFUNCTION("""COMPUTED_VALUE"""),88.22) -> 88.22 | K17: =IFERROR(__xludf.DUMMYFUNCTION("""COMPUTED_VALUE"""),300.0) -> 300 | L17: =IFERROR(__xludf.DUMMYFUNCTION("""COMPUTED_VALUE"""),0.29406666666666664) -> 0.29406667 | M17: =IFERROR(__xludf.DUMMYFUNCTION("""COMPUTED_VALUE"""),51.0) -> 51 | N17: =IFERROR(__xludf.DUMMYFUNCTION("""COMPUTED_VALUE"""),52.0) -> 52 | O17: =IFERROR(__xludf.DUMMYFUNCTION("""COMPUTED_VALUE"""),0.9807692307692307) -> 0.98076923 | P17: =IFERROR(__xludf.DUMMYFUNCTION("""COMPUTED_VALUE"""),1.0) -> 1 | Q17: =IFERROR(__xludf.DUMMYFUNCTION("""COMPUTED_VALUE"""),1.0) -> 1 | R17: =IFERROR(__xludf.DUMMYFUNCTION("""COMPUTED_VALUE"""),1.0) -> 1 | S17: =IFERROR(__xludf.DUMMYFUNCTION("""COMPUTED_VALUE"""),1.0) -> 1 | T17: =IFERROR(__xludf.DUMMYFUNCTION("""COMPUTED_VALUE"""),1.0) -> 1 | U17: =IFERROR(__xludf.DUMMYFUNCTION("""COMPUTED_VALUE"""),1.0) -> 1 | V17: =IFERROR(__xludf.DUMMYFUNCTION("""COMPUTED_VALUE"""),0.0) -> 0 | W17: =IFERROR(__xludf.DUMMYFUNCTION("""COMPUTED_VALUE"""),1.0) -> 1 | X17: =IFERROR(__xludf.DUMMYFUNCTION("""COMPUTED_VALUE"""),0.0) -> 0 | Y17: =IFERROR(__xludf.DUMMYFUNCTION("""COMPUTED_VALUE"""),4.42) -> 4.42 | Z17: =IFERROR(__xludf.DUMMYFUNCTION("""COMPUTED_VALUE"""),0.0) -> 0 | AA17: =IFERROR(__xludf.DUMMYFUNCTION("""COMPUTED_VALUE"""),"") | AB17: =IFERROR(__xludf.DUMMYFUNCTION("""COMPUTED_VALUE"""),1.86) -> 1.86 | AC17: =IFERROR(__xludf.DUMMYFUNCTION("""COMPUTED_VALUE"""),147.06) -> 147.06 | AD17: =IFERROR(__xludf.DUMMYFUNCTION("""COMPUTED_VALUE"""),0.012647898816809467) -> 0.012647899 | AE17: =IFERROR(__xludf.DUMMYFUNCTION("""COMPUTED_VALUE"""),54.08) -> 54.08 | AF17: =IFERROR(__xludf.DUMMYFUNCTION("""COMPUTED_VALUE"""),147.06) -> 147.06 | AG17: =IFERROR(__xludf.DUMMYFUNCTION("""COMPUTED_VALUE"""),0.3677410580715354) -> 0.36774106 | AH17: =IFERROR(__xludf.DUMMYFUNCTION("""COMPUTED_VALUE"""),108.4) -> 108.4 | AI17: =IFERROR(__xludf.DUMMYFUNCTION("""COMPUTED_VALUE"""),147.06) -> 147.06 | AJ17: =IFERROR(__xludf.DUMMYFUNCTION("""COMPUTED_VALUE"""),0.7371141030871753) -> 0.7371141 | AK17: =IFERROR(__xludf.DUMMYFUNCTION("""COMPUTED_VALUE"""),168.76) -> 168.76 | AL17: =IFERROR(__xludf.DUMMYFUNCTION("""COMPUTED_VALUE"""),441.18) -> 441.18 | AM17: =IFERROR(__xludf.DUMMYFUNCTION("""COMPUTED_VALUE"""),0.38251960650981454) -> 0.38251961 | AN17: =IFERROR(__xludf.DUMMYFUNCTION("""COMPUTED_VALUE"""),0.0) -> 0 | AO17: =IFERROR(__xludf.DUMMYFUNCTION("""COMPUTED_VALUE"""),0.0) -> 0 | AP17: =IFERROR(__xludf.DUMMYFUNCTION("""COMPUTED_VALUE"""),"") | AQ17: =IFERROR(__xludf.DUMMYFUNCTION("""COMPUTED_VALUE"""),0.0) -> 0 | AR17: =IFERROR(__xludf.DUMMYFUNCTION("""COMPUTED_VALUE"""),0.0) -> 0 | AS17: =IFERROR(__xludf.DUMMYFUNCTION("""COMPUTED_VALUE"""),"") | AT17: =IFERROR(__xludf.DUMMYFUNCTION("""COMPUTED_VALUE"""),0.0) -> 0 | AU17: =IFERROR(__xludf.DUMMYFUNCTION("""COMPUTED_VALUE"""),0.0) -> 0 | AV17: =IFERROR(__xludf.DUMMYFUNCTION("""COMPUTED_VALUE"""),"") | AW17: =IFERROR(__xludf.DUMMYFUNCTION("""COMPUTED_VALUE"""),0.0) -> 0 | AX17: =IFERROR(__xludf.DUMMYFUNCTION("""COMPUTED_VALUE"""),0.0) -> 0 | AY17: =IFERROR(__xludf.DUMMYFUNCTION("""COMPUTED_VALUE"""),"") | AZ17: =IFERROR(__xludf.DUMMYFUNCTION("""COMPUTED_VALUE"""),0.0) -> 0 | BA17: =IFERROR(__xludf.DUMMYFUNCTION("""COMPUTED_VALUE"""),0.0) -> 0 | BB17: =IFERROR(__xludf.DUMMYFUNCTION("""COMPUTED_VALUE"""),"")
A18: =IFERROR(__xludf.DUMMYFUNCTION("""COMPUTED_VALUE"""),"63ef9d60384f27260c1bb0cd") -> 63ef9d60384f27260c1bb0cd | B18: =IFERROR(__xludf.DUMMYFUNCTION("""COMPUTED_VALUE"""),"Arki Management") -> Arki Management | C18: =IFERROR(__xludf.DUMMYFUNCTION("""COMPUTED_VALUE"""),"mario.madrid-bustos@al-enterprise.com, astrid.savorani@al-enterprise.com, marcos.rodriguez@al-enterprise.com") -> mario.madrid-bustos@al-enterprise.com, astrid.savorani@al-enterprise.com, marcos.rodriguez@al-enterprise.com | D18: =IFERROR(__xludf.DUMMYFUNCTION("""COMPUTED_VALUE"""),"emea") -> emea | E18: =IFERROR(__xludf.DUMMYFUNCTION("""COMPUTED_VALUE"""),"ES") -> ES | F18: =IFERROR(__xludf.DUMMYFUNCTION("""COMPUTED_VALUE"""),"expert_200") -> expert_200 | G18: =IFERROR(__xludf.DUMMYFUNCTION("""COMPUTED_VALUE"""),0.0) -> 0 | H18: =IFERROR(__xludf.DUMMYFUNCTION("""COMPUTED_VALUE"""),1.0) -> 1 | I18: =IFERROR(__xludf.DUMMYFUNCTION("""COMPUTED_VALUE"""),0.0) -> 0 | J18: =IFERROR(__xludf.DUMMYFUNCTION("""COMPUTED_VALUE"""),18.39) -> 18.39 | K18: =IFERROR(__xludf.DUMMYFUNCTION("""COMPUTED_VALUE"""),0.0) -> 0 | L18: =IFERROR(__xludf.DUMMYFUNCTION("""COMPUTED_VALUE"""),"") | M18: =IFERROR(__xludf.DUMMYFUNCTION("""COMPUTED_VALUE"""),0.0) -> 0 | N18: =IFERROR(__xludf.DUMMYFUNCTION("""COMPUTED_VALUE"""),0.0) -> 0 | O18: =IFERROR(__xludf.DUMMYFUNCTION("""COMPUTED_VALUE"""),"") | P18: =IFERROR(__xludf.DUMMYFUNCTION("""COMPUTED_VALUE"""),0.0) -> 0 | Q18: =IFERROR(__xludf.DUMMYFUNCTION("""COMPUTED_VALUE"""),1.0) -> 1 | R18: =IFERROR(__xludf.DUMMYFUNCTION("""COMPUTED_VALUE"""),0.0) -> 0 | S18: =IFERROR(__xludf.DUMMYFUNCTION("""COMPUTED_VALUE"""),0.0) -> 0 | T18: =IFERROR(__xludf.DUMMYFUNCTION("""COMPUTED_VALUE"""),1.0) -> 1 | U18: =IFERROR(__xludf.DUMMYFUNCTION("""COMPUTED_VALUE"""),0.0) -> 0 | V18: =IFERROR(__xludf.DUMMYFUNCTION("""COMPUTED_VALUE"""),0.0) -> 0 | W18: =IFERROR(__xludf.DUMMYFUNCTION("""COMPUTED_VALUE"""),1.0) -> 1 | X18: =IFERROR(__xludf.DUMMYFUNCTION("""COMPUTED_VALUE"""),0.0) -> 0 | Y18: =IFERROR(__xludf.DUMMYFUNCTION("""COMPUTED_VALUE"""),75.0) -> 75 | Z18: =IFERROR(__xludf.DUMMYFUNCTION("""COMPUTED_VALUE"""),0.0) -> 0 | AA18: =IFERROR(__xludf.DUMMYFUNCTION("""COMPUTED_VALUE"""),"") | AB18: =IFERROR(__xludf.DUMMYFUNCTION("""COMPUTED_VALUE"""),9.0) -> 9 | AC18: =IFERROR(__xludf.DUMMYFUNCTION("""COMPUTED_VALUE"""),0.0) -> 0 | AD18: =IFERROR(__xludf.DUMMYFUNCTION("""COMPUTED_VALUE"""),"") | AE18: =IFERROR(__xludf.DUMMYFUNCTION("""COMPUTED_VALUE"""),73.3) -> 73.3 | AF18: =IFERROR(__xludf.DUMMYFUNCTION("""COMPUTED_VALUE"""),0.0) -> 0 | AG18: =IFERROR(__xludf.DUMMYFUNCTION("""COMPUTED_VALUE"""),"") | AH18: =IFERROR(__xludf.DUMMYFUNCTION("""COMPUTED_VALUE"""),135.8) -> 135.8 | AI18: =IFERROR(__xludf.DUMMYFUNCTION("""COMPUTED_VALUE"""),0.0) -> 0 | AJ18: =IFERROR(__xludf.DUMMYFUNCTION("""COMPUTED_VALUE"""),"") | AK18: =IFERROR(__xludf.DUMMYFUNCTION("""COMPUTED_VALUE"""),293.1) -> 293.1 | AL18: =IFERROR(__xludf.DUMMYFUNCTION("""COMPUTED_VALUE"""),0.0) -> 0 | AM18: =IFERROR(__xludf.DUMMYFUNCTION("""COMPUTED_VALUE"""),"") | AN18: =IFERROR(__xludf.DUMMYFUNCTION("""COMPUTED_VALUE"""),0.0) -> 0 | AO18: =IFERROR(__xludf.DUMMYFUNCTION("""COMPUTED_VALUE"""),0.0) -> 0 | AP18: =IFERROR(__xludf.DUMMYFUNCTION("""COMPUTED_VALUE"""),"") | AQ18: =IFERROR(__xludf.DUMMYFUNCTION("""COMPUTED_VALUE"""),0.0) -> 0 | AR18: =IFERROR(__xludf.DUMMYFUNCTION("""COMPUTED_VALUE"""),0.0) -> 0 | AS18: =IFERROR(__xludf.DUMMYFUNCTION("""COMPUTED_VALUE"""),"") | AT18: =IFERROR(__xludf.DUMMYFUNCTION("""COMPUTED_VALUE"""),0.0) -> 0 | AU18: =IFERROR(__xludf.DUMMYFUNCTION("""COMPUTED_VALUE"""),0.0) -> 0 | AV18: =IFERROR(__xludf.DUMMYFUNCTION("""COMPUTED_VALUE"""),"") | AW18: =IFERROR(__xludf.DUMMYFUNCTION("""COMPUTED_VALUE"""),0.0) -> 0 | AX18: =IFERROR(__xludf.DUMMYFUNCTION("""COMPUTED_VALUE"""),0.0) -> 0 | AY18: =IFERROR(__xludf.DUMMYFUNCTION("""COMPUTED_VALUE"""),"") | AZ18: =IFERROR(__xludf.DUMMYFUNCTION("""COMPUTED_VALUE"""),0.0) -> 0 | BA18: =IFERROR(__xludf.DUMMYFUNCTION("""COMPUTED_VALUE"""),0.0) -> 0 | BB18: =IFERROR(__xludf.DUMMYFUNCTION("""COMPUTED_VALUE"""),"")
A19: =IFERROR(__xludf.DUMMYFUNCTION("""COMPUTED_VALUE"""),"63ef9d57384f27260c1ba2f1") -> 63ef9d57384f27260c1ba2f1 | B19: =IFERROR(__xludf.DUMMYFUNCTION("""COMPUTED_VALUE"""),"ARROW ENTERPRISE COMPUTING SOLUTION") -> ARROW ENTERPRISE COMPUTING SOLUTION | C19: =IFERROR(__xludf.DUMMYFUNCTION("""COMPUTED_VALUE"""),"holly.berger@al-enterprise.com") -> holly.berger@al-enterprise.com | D19: =IFERROR(__xludf.DUMMYFUNCTION("""COMPUTED_VALUE"""),"americas") -> americas | E19: =IFERROR(__xludf.DUMMYFUNCTION("""COMPUTED_VALUE"""),"US") -> US | F19: =IFERROR(__xludf.DUMMYFUNCTION("""COMPUTED_VALUE"""),"distributor_1000") -> distributor_1000 | G19: =IFERROR(__xludf.DUMMYFUNCTION("""COMPUTED_VALUE"""),0.0) -> 0 | H19: =IFERROR(__xludf.DUMMYFUNCTION("""COMPUTED_VALUE"""),1.0) -> 1 | I19: =IFERROR(__xludf.DUMMYFUNCTION("""COMPUTED_VALUE"""),0.0) -> 0 | J19: =IFERROR(__xludf.DUMMYFUNCTION("""COMPUTED_VALUE"""),10554.48) -> 10554.48 | K19: =IFERROR(__xludf.DUMMYFUNCTION("""COMPUTED_VALUE"""),12725.89) -> 12725.89 | L19: =IFERROR(__xludf.DUMMYFUNCTION("""COMPUTED_VALUE"""),0.8293706766285108) -> 0.82937068 | M19: =IFERROR(__xludf.DUMMYFUNCTION("""COMPUTED_VALUE"""),16.0) -> 16 | N19: =IFERROR(__xludf.DUMMYFUNCTION("""COMPUTED_VALUE"""),56.0) -> 56 | O19: =IFERROR(__xludf.DUMMYFUNCTION("""COMPUTED_VALUE"""),0.2857142857142857) -> 0.28571429 | P19: =IFERROR(__xludf.DUMMYFUNCTION("""COMPUTED_VALUE"""),1.0) -> 1 | Q19: =IFERROR(__xludf.DUMMYFUNCTION("""COMPUTED_VALUE"""),1.0) -> 1 | R19: =IFERROR(__xludf.DUMMYFUNCTION("""COMPUTED_VALUE"""),1.0) -> 1 | S19: =IFERROR(__xludf.DUMMYFUNCTION("""COMPUTED_VALUE"""),1.0) -> 1 | T19: =IFERROR(__xludf.DUMMYFUNCTION("""COMPUTED_VALUE"""),1.0) -> 1 | U19: =IFERROR(__xludf.DUMMYFUNCTION("""COMPUTED_VALUE"""),1.0) -> 1 | V19: =IFERROR(__xludf.DUMMYFUNCTION("""COMPUTED_VALUE"""),0.0) -> 0 | W19: =IFERROR(__xludf.DUMMYFUNCTION("""COMPUTED_VALUE"""),1.0) -> 1 | X19: =IFERROR(__xludf.DUMMYFUNCTION("""COMPUTED_VALUE"""),0.0) -> 0 | Y19: =IFERROR(__xludf.DUMMYFUNCTION("""COMPUTED_VALUE"""),3.08) -> 3.08 | Z19: =IFERROR(__xludf.DUMMYFUNCTION("""COMPUTED_VALUE"""),0.0) -> 0 | AA19: =IFERROR(__xludf.DUMMYFUNCTION("""COMPUTED_VALUE"""),"") | AB19: =IFERROR(__xludf.DUMMYFUNCTION("""COMPUTED_VALUE"""),8.97) -> 8.97 | AC19: =IFERROR(__xludf.DUMMYFUNCTION("""COMPUTED_VALUE"""),6881.01) -> 6881.01 | AD19: =IFERROR(__xludf.DUMMYFUNCTION("""COMPUTED_VALUE"""),0.0013035877000614736) -> 0.0013035877 | AE19: =IFERROR(__xludf.DUMMYFUNCTION("""COMPUTED_VALUE"""),296.05) -> 296.05 | AF19: =IFERROR(__xludf.DUMMYFUNCTION("""COMPUTED_VALUE"""),10318.83) -> 10318.83 | AG19: =IFERROR(__xludf.DUMMYFUNCTION("""COMPUTED_VALUE"""),0.028690268179628893) -> 0.028690268 | AH19: =IFERROR(__xludf.DUMMYFUNCTION("""COMPUTED_VALUE"""),18.91) -> 18.91 | AI19: =IFERROR(__xludf.DUMMYFUNCTION("""COMPUTED_VALUE"""),10316.12) -> 10316.12 | AJ19: =IFERROR(__xludf.DUMMYFUNCTION("""COMPUTED_VALUE"""),0.0018330535123670525) -> 0.0018330535 | AK19: =IFERROR(__xludf.DUMMYFUNCTION("""COMPUTED_VALUE"""),327.01000000000005) -> 327.01 | AL19: =IFERROR(__xludf.DUMMYFUNCTION("""COMPUTED_VALUE"""),27515.96) -> 27515.96 | AM19: =IFERROR(__xludf.DUMMYFUNCTION("""COMPUTED_VALUE"""),0.011884375467910262) -> 0.011884375 | AN19: =IFERROR(__xludf.DUMMYFUNCTION("""COMPUTED_VALUE"""),2.74) -> 2.74 | AO19: =IFERROR(__xludf.DUMMYFUNCTION("""COMPUTED_VALUE"""),0.0) -> 0 | AP19: =IFERROR(__xludf.DUMMYFUNCTION("""COMPUTED_VALUE"""),"") | AQ19: =IFERROR(__xludf.DUMMYFUNCTION("""COMPUTED_VALUE"""),28.22) -> 28.22 | AR19: =IFERROR(__xludf.DUMMYFUNCTION("""COMPUTED_VALUE"""),0.0) -> 0 | AS19: =IFERROR(__xludf.DUMMYFUNCTION("""COMPUTED_VALUE"""),"") | AT19: =IFERROR(__xludf.DUMMYFUNCTION("""COMPUTED_VALUE"""),8.38) -> 8.38 | AU19: =IFERROR(__xludf.DUMMYFUNCTION("""COMPUTED_VALUE"""),0.0) -> 0 | AV19: =IFERROR(__xludf.DUMMYFUNCTION("""COMPUTED_VALUE"""),"") | AW19: =IFERROR(__xludf.DUMMYFUNCTION("""COMPUTED_VALUE"""),0.0) -> 0 | AX19: =IFERROR(__xludf.DUMMYFUNCTION("""COMPUTED_VALUE"""),0.0) -> 0 | AY19: =IFERROR(__xludf.DUMMYFUNCTION("""COMPUTED_VALUE"""),"") | AZ19: =IFERROR(__xludf.DUMMYFUNCTION("""COMPUTED_VALUE"""),39.34) -> 39.34 | BA19: =IFERROR(__xludf.DUMMYFUNCTION("""COMPUTED_VALUE"""),0.0) -> 0 | BB19: =IFERROR(__xludf.DUMMYFUNCTION("""COMPUTED_VALUE"""),"")
A20: =IFERROR(__xludf.DUMMYFUNCTION("""COMPUTED_VALUE"""),"63ced849c5c820531c268e5b") -> 63ced849c5c820531c268e5b | B20: =IFERROR(__xludf.DUMMYFUNCTION("""COMPUTED_VALUE"""),"ASTEL - ADVANCED SOLUCIONES DE") -> ASTEL - ADVANCED SOLUCIONES DE | C20: =IFERROR(__xludf.DUMMYFUNCTION("""COMPUTED_VALUE"""),"joaquin.flores@al-enterprise.com") -> joaquin.flores@al-enterprise.com | D20: =IFERROR(__xludf.DUMMYFUNCTION("""COMPUTED_VALUE"""),"americas") -> americas | E20: =IFERROR(__xludf.DUMMYFUNCTION("""COMPUTED_VALUE"""),"MX") -> MX | F20: =IFERROR(__xludf.DUMMYFUNCTION("""COMPUTED_VALUE"""),"distributor_1000") -> distributor_1000 | G20: =IFERROR(__xludf.DUMMYFUNCTION("""COMPUTED_VALUE"""),0.0) -> 0 | H20: =IFERROR(__xludf.DUMMYFUNCTION("""COMPUTED_VALUE"""),1.0) -> 1 | I20: =IFERROR(__xludf.DUMMYFUNCTION("""COMPUTED_VALUE"""),0.0) -> 0 | J20: =IFERROR(__xludf.DUMMYFUNCTION("""COMPUTED_VALUE"""),785.44) -> 785.44 | K20: =IFERROR(__xludf.DUMMYFUNCTION("""COMPUTED_VALUE"""),2875.97) -> 2875.97 | L20: =IFERROR(__xludf.DUMMYFUNCTION("""COMPUTED_VALUE"""),0.27310437869657894) -> 0.27310438 | M20: =IFERROR(__xludf.DUMMYFUNCTION("""COMPUTED_VALUE"""),81.0) -> 81 | N20: =IFERROR(__xludf.DUMMYFUNCTION("""COMPUTED_VALUE"""),52.0) -> 52 | O20: =IFERROR(__xludf.DUMMYFUNCTION("""COMPUTED_VALUE"""),1.5576923076923077) -> 1.5576923 | P20: =IFERROR(__xludf.DUMMYFUNCTION("""COMPUTED_VALUE"""),1.0) -> 1 | Q20: =IFERROR(__xludf.DUMMYFUNCTION("""COMPUTED_VALUE"""),1.0) -> 1 | R20: =IFERROR(__xludf.DUMMYFUNCTION("""COMPUTED_VALUE"""),1.0) -> 1 | S20: =IFERROR(__xludf.DUMMYFUNCTION("""COMPUTED_VALUE"""),1.0) -> 1 | T20: =IFERROR(__xludf.DUMMYFUNCTION("""COMPUTED_VALUE"""),1.0) -> 1 | U20: =IFERROR(__xludf.DUMMYFUNCTION("""COMPUTED_VALUE"""),1.0) -> 1 | V20: =IFERROR(__xludf.DUMMYFUNCTION("""COMPUTED_VALUE"""),0.0) -> 0 | W20: =IFERROR(__xludf.DUMMYFUNCTION("""COMPUTED_VALUE"""),1.0) -> 1 | X20: =IFERROR(__xludf.DUMMYFUNCTION("""COMPUTED_VALUE"""),0.0) -> 0 | Y20: =IFERROR(__xludf.DUMMYFUNCTION("""COMPUTED_VALUE"""),14.49) -> 14.49 | Z20: =IFERROR(__xludf.DUMMYFUNCTION("""COMPUTED_VALUE"""),0.0) -> 0 | AA20: =IFERROR(__xludf.DUMMYFUNCTION("""COMPUTED_VALUE"""),"") | AB20: =IFERROR(__xludf.DUMMYFUNCTION("""COMPUTED_VALUE"""),17.91) -> 17.91 | AC20: =IFERROR(__xludf.DUMMYFUNCTION("""COMPUTED_VALUE"""),845.58) -> 845.58 | AD20: =IFERROR(__xludf.DUMMYFUNCTION("""COMPUTED_VALUE"""),0.021180728021003334) -> 0.021180728 | AE20: =IFERROR(__xludf.DUMMYFUNCTION("""COMPUTED_VALUE"""),93.62) -> 93.62 | AF20: =IFERROR(__xludf.DUMMYFUNCTION("""COMPUTED_VALUE"""),1269.09) -> 1269.09 | AG20: =IFERROR(__xludf.DUMMYFUNCTION("""COMPUTED_VALUE"""),0.07376939381761735) -> 0.073769394 | AH20: =IFERROR(__xludf.DUMMYFUNCTION("""COMPUTED_VALUE"""),184.87) -> 184.87 | AI20: =IFERROR(__xludf.DUMMYFUNCTION("""COMPUTED_VALUE"""),1269.09) -> 1269.09 | AJ20: =IFERROR(__xludf.DUMMYFUNCTION("""COMPUTED_VALUE"""),0.14567130778746978) -> 0.14567131 | AK20: =IFERROR(__xludf.DUMMYFUNCTION("""COMPUTED_VALUE"""),310.89) -> 310.89 | AL20: =IFERROR(__xludf.DUMMYFUNCTION("""COMPUTED_VALUE"""),3383.76) -> 3383.76 | AM20: =IFERROR(__xludf.DUMMYFUNCTION("""COMPUTED_VALUE"""),0.09187708348109794) -> 0.091877083 | AN20: =IFERROR(__xludf.DUMMYFUNCTION("""COMPUTED_VALUE"""),41.46) -> 41.46 | AO20: =IFERROR(__xludf.DUMMYFUNCTION("""COMPUTED_VALUE"""),0.0) -> 0 | AP20: =IFERROR(__xludf.DUMMYFUNCTION("""COMPUTED_VALUE"""),"") | AQ20: =IFERROR(__xludf.DUMMYFUNCTION("""COMPUTED_VALUE"""),64.23) -> 64.23 | AR20: =IFERROR(__xludf.DUMMYFUNCTION("""COMPUTED_VALUE"""),0.0) -> 0 | AS20: =IFERROR(__xludf.DUMMYFUNCTION("""COMPUTED_VALUE"""),"") | AT20: =IFERROR(__xludf.DUMMYFUNCTION("""COMPUTED_VALUE"""),0.0) -> 0 | AU20: =IFERROR(__xludf.DUMMYFUNCTION("""COMPUTED_VALUE"""),0.0) -> 0 | AV20: =IFERROR(__xludf.DUMMYFUNCTION("""COMPUTED_VALUE"""),"") | AW20: =IFERROR(__xludf.DUMMYFUNCTION("""COMPUTED_VALUE"""),7.26) -> 7.26 | AX20: =IFERROR(__xludf.DUMMYFUNCTION("""COMPUTED_VALUE"""),0.0) -> 0 | AY20: =IFERROR(__xludf.DUMMYFUNCTION("""COMPUTED_VALUE"""),"") | AZ20: =IFERROR(__xludf.DUMMYFUNCTION("""COMPUTED_VALUE"""),112.95) -> 112.95 | BA20: =IFERROR(__xludf.DUMMYFUNCTION("""COMPUTED_VALUE"""),0.0) -> 0 | BB20: =IFERROR(__xludf.DUMMYFUNCTION("""COMPUTED_VALUE"""),"")
A21: =IFERROR(__xludf.DUMMYFUNCTION("""COMPUTED_VALUE"""),"67a5d9f053e26e938a079872") -> 67a5d9f053e26e938a079872 | B21: =IFERROR(__xludf.DUMMYFUNCTION("""COMPUTED_VALUE"""),"Axcelerate Networks, Inc.") -> Axcelerate Networks, Inc. | C21: =IFERROR(__xludf.DUMMYFUNCTION("""COMPUTED_VALUE"""),"bill.rademacher@al-enterprise.com") -> bill.rademacher@al-enterprise.com | D21: =IFERROR(__xludf.DUMMYFUNCTION("""COMPUTED_VALUE"""),"americas") -> americas | E21: =IFERROR(__xludf.DUMMYFUNCTION("""COMPUTED_VALUE"""),"US") -> US | F21: =IFERROR(__xludf.DUMMYFUNCTION("""COMPUTED_VALUE"""),"expert_200") -> expert_200 | G21: =IFERROR(__xludf.DUMMYFUNCTION("""COMPUTED_VALUE"""),0.0) -> 0 | H21: =IFERROR(__xludf.DUMMYFUNCTION("""COMPUTED_VALUE"""),1.0) -> 1 | I21: =IFERROR(__xludf.DUMMYFUNCTION("""COMPUTED_VALUE"""),0.0) -> 0 | J21: =IFERROR(__xludf.DUMMYFUNCTION("""COMPUTED_VALUE"""),0.0) -> 0 | K21: =IFERROR(__xludf.DUMMYFUNCTION("""COMPUTED_VALUE"""),0.0) -> 0 | L21: =IFERROR(__xludf.DUMMYFUNCTION("""COMPUTED_VALUE"""),"") | M21: =IFERROR(__xludf.DUMMYFUNCTION("""COMPUTED_VALUE"""),0.0) -> 0 | N21: =IFERROR(__xludf.DUMMYFUNCTION("""COMPUTED_VALUE"""),0.0) -> 0 | O21: =IFERROR(__xludf.DUMMYFUNCTION("""COMPUTED_VALUE"""),"") | P21: =IFERROR(__xludf.DUMMYFUNCTION("""COMPUTED_VALUE"""),0.0) -> 0 | Q21: =IFERROR(__xludf.DUMMYFUNCTION("""COMPUTED_VALUE"""),1.0) -> 1 | R21: =IFERROR(__xludf.DUMMYFUNCTION("""COMPUTED_VALUE"""),0.0) -> 0 | S21: =IFERROR(__xludf.DUMMYFUNCTION("""COMPUTED_VALUE"""),0.0) -> 0 | T21: =IFERROR(__xludf.DUMMYFUNCTION("""COMPUTED_VALUE"""),1.0) -> 1 | U21: =IFERROR(__xludf.DUMMYFUNCTION("""COMPUTED_VALUE"""),0.0) -> 0 | V21: =IFERROR(__xludf.DUMMYFUNCTION("""COMPUTED_VALUE"""),0.0) -> 0 | W21: =IFERROR(__xludf.DUMMYFUNCTION("""COMPUTED_VALUE"""),1.0) -> 1 | X21: =IFERROR(__xludf.DUMMYFUNCTION("""COMPUTED_VALUE"""),0.0) -> 0 | Y21: =IFERROR(__xludf.DUMMYFUNCTION("""COMPUTED_VALUE"""),0.0) -> 0 | Z21: =IFERROR(__xludf.DUMMYFUNCTION("""COMPUTED_VALUE"""),0.0) -> 0 | AA21: =IFERROR(__xludf.DUMMYFUNCTION("""COMPUTED_VALUE"""),"") | AB21: =IFERROR(__xludf.DUMMYFUNCTION("""COMPUTED_VALUE"""),0.0) -> 0 | AC21: =IFERROR(__xludf.DUMMYFUNCTION("""COMPUTED_VALUE"""),0.0) -> 0 | AD21: =IFERROR(__xludf.DUMMYFUNCTION("""COMPUTED_VALUE"""),"") | AE21: =IFERROR(__xludf.DUMMYFUNCTION("""COMPUTED_VALUE"""),0.0) -> 0 | AF21: =IFERROR(__xludf.DUMMYFUNCTION("""COMPUTED_VALUE"""),0.0) -> 0 | AG21: =IFERROR(__xludf.DUMMYFUNCTION("""COMPUTED_VALUE"""),"") | AH21: =IFERROR(__xludf.DUMMYFUNCTION("""COMPUTED_VALUE"""),0.0) -> 0 | AI21: =IFERROR(__xludf.DUMMYFUNCTION("""COMPUTED_VALUE"""),0.0) -> 0 | AJ21: =IFERROR(__xludf.DUMMYFUNCTION("""COMPUTED_VALUE"""),"") | AK21: =IFERROR(__xludf.DUMMYFUNCTION("""COMPUTED_VALUE"""),0.0) -> 0 | AL21: =IFERROR(__xludf.DUMMYFUNCTION("""COMPUTED_VALUE"""),0.0) -> 0 | AM21: =IFERROR(__xludf.DUMMYFUNCTION("""COMPUTED_VALUE"""),"") | AN21: =IFERROR(__xludf.DUMMYFUNCTION("""COMPUTED_VALUE"""),0.0) -> 0 | AO21: =IFERROR(__xludf.DUMMYFUNCTION("""COMPUTED_VALUE"""),0.0) -> 0 | AP21: =IFERROR(__xludf.DUMMYFUNCTION("""COMPUTED_VALUE"""),"") | AQ21: =IFERROR(__xludf.DUMMYFUNCTION("""COMPUTED_VALUE"""),0.0) -> 0 | AR21: =IFERROR(__xludf.DUMMYFUNCTION("""COMPUTED_VALUE"""),0.0) -> 0 | AS21: =IFERROR(__xludf.DUMMYFUNCTION("""COMPUTED_VALUE"""),"") | AT21: =IFERROR(__xludf.DUMMYFUNCTION("""COMPUTED_VALUE"""),0.0) -> 0 | AU21: =IFERROR(__xludf.DUMMYFUNCTION("""COMPUTED_VALUE"""),0.0) -> 0 | AV21: =IFERROR(__xludf.DUMMYFUNCTION("""COMPUTED_VALUE"""),"") | AW21: =IFERROR(__xludf.DUMMYFUNCTION("""COMPUTED_VALUE"""),0.0) -> 0 | AX21: =IFERROR(__xludf.DUMMYFUNCTION("""COMPUTED_VALUE"""),0.0) -> 0 | AY21: =IFERROR(__xludf.DUMMYFUNCTION("""COMPUTED_VALUE"""),"") | AZ21: =IFERROR(__xludf.DUMMYFUNCTION("""COMPUTED_VALUE"""),0.0) -> 0 | BA21: =IFERROR(__xludf.DUMMYFUNCTION("""COMPUTED_VALUE"""),0.0) -> 0 | BB21: =IFERROR(__xludf.DUMMYFUNCTION("""COMPUTED_VALUE"""),"")
A22: =IFERROR(__xludf.DUMMYFUNCTION("""COMPUTED_VALUE"""),"63ced84ec5c820531c2698f6") -> 63ced84ec5c820531c2698f6 | B22: =IFERROR(__xludf.DUMMYFUNCTION("""COMPUTED_VALUE"""),"Axcex Media LLC") -> Axcex Media LLC | C22: =IFERROR(__xludf.DUMMYFUNCTION("""COMPUTED_VALUE"""),"michael-j.francis@al-enterprise.com, luigy.estevanell@al-enterprise.com, robert.stitz@al-enterprise.com") -> michael-j.francis@al-enterprise.com, luigy.estevanell@al-enterprise.com, robert.stitz@al-enterprise.com | D22: =IFERROR(__xludf.DUMMYFUNCTION("""COMPUTED_VALUE"""),"americas") -> americas | E22: =IFERROR(__xludf.DUMMYFUNCTION("""COMPUTED_VALUE"""),"US") -> US | F22: =IFERROR(__xludf.DUMMYFUNCTION("""COMPUTED_VALUE"""),"expert_200") -> expert_200 | G22: =IFERROR(__xludf.DUMMYFUNCTION("""COMPUTED_VALUE"""),0.0) -> 0 | H22: =IFERROR(__xludf.DUMMYFUNCTION("""COMPUTED_VALUE"""),1.0) -> 1 | I22: =IFERROR(__xludf.DUMMYFUNCTION("""COMPUTED_VALUE"""),0.0) -> 0 | J22: =IFERROR(__xludf.DUMMYFUNCTION("""COMPUTED_VALUE"""),14.62) -> 14.62 | K22: =IFERROR(__xludf.DUMMYFUNCTION("""COMPUTED_VALUE"""),149.6) -> 149.6 | L22: =IFERROR(__xludf.DUMMYFUNCTION("""COMPUTED_VALUE"""),0.09772727272727273) -> 0.097727273 | M22: =IFERROR(__xludf.DUMMYFUNCTION("""COMPUTED_VALUE"""),3.0) -> 3 | N22: =IFERROR(__xludf.DUMMYFUNCTION("""COMPUTED_VALUE"""),0.0) -> 0 | O22: =IFERROR(__xludf.DUMMYFUNCTION("""COMPUTED_VALUE"""),"") | P22: =IFERROR(__xludf.DUMMYFUNCTION("""COMPUTED_VALUE"""),0.0) -> 0 | Q22: =IFERROR(__xludf.DUMMYFUNCTION("""COMPUTED_VALUE"""),1.0) -> 1 | R22: =IFERROR(__xludf.DUMMYFUNCTION("""COMPUTED_VALUE"""),0.0) -> 0 | S22: =IFERROR(__xludf.DUMMYFUNCTION("""COMPUTED_VALUE"""),0.0) -> 0 | T22: =IFERROR(__xludf.DUMMYFUNCTION("""COMPUTED_VALUE"""),1.0) -> 1 | U22: =IFERROR(__xludf.DUMMYFUNCTION("""COMPUTED_VALUE"""),0.0) -> 0 | V22: =IFERROR(__xludf.DUMMYFUNCTION("""COMPUTED_VALUE"""),0.0) -> 0 | W22: =IFERROR(__xludf.DUMMYFUNCTION("""COMPUTED_VALUE"""),1.0) -> 1 | X22: =IFERROR(__xludf.DUMMYFUNCTION("""COMPUTED_VALUE"""),0.0) -> 0 | Y22: =IFERROR(__xludf.DUMMYFUNCTION("""COMPUTED_VALUE"""),0.0) -> 0 | Z22: =IFERROR(__xludf.DUMMYFUNCTION("""COMPUTED_VALUE"""),0.0) -> 0 | AA22: =IFERROR(__xludf.DUMMYFUNCTION("""COMPUTED_VALUE"""),"") | AB22: =IFERROR(__xludf.DUMMYFUNCTION("""COMPUTED_VALUE"""),0.0) -> 0 | AC22: =IFERROR(__xludf.DUMMYFUNCTION("""COMPUTED_VALUE"""),99.67) -> 99.67 | AD22: =IFERROR(__xludf.DUMMYFUNCTION("""COMPUTED_VALUE"""),0.0) -> 0 | AE22: =IFERROR(__xludf.DUMMYFUNCTION("""COMPUTED_VALUE"""),70.61) -> 70.61 | AF22: =IFERROR(__xludf.DUMMYFUNCTION("""COMPUTED_VALUE"""),149.65) -> 149.65 | AG22: =IFERROR(__xludf.DUMMYFUNCTION("""COMPUTED_VALUE"""),0.47183427998663546) -> 0.47183428 | AH22: =IFERROR(__xludf.DUMMYFUNCTION("""COMPUTED_VALUE"""),100.0) -> 100 | AI22: =IFERROR(__xludf.DUMMYFUNCTION("""COMPUTED_VALUE"""),149.65) -> 149.65 | AJ22: =IFERROR(__xludf.DUMMYFUNCTION("""COMPUTED_VALUE"""),0.6682258603407951) -> 0.66822586 | AK22: =IFERROR(__xludf.DUMMYFUNCTION("""COMPUTED_VALUE"""),170.61) -> 170.61 | AL22: =IFERROR(__xludf.DUMMYFUNCTION("""COMPUTED_VALUE"""),398.97) -> 398.97 | AM22: =IFERROR(__xludf.DUMMYFUNCTION("""COMPUTED_VALUE"""),0.42762613730355664) -> 0.42762614 | AN22: =IFERROR(__xludf.DUMMYFUNCTION("""COMPUTED_VALUE"""),0.0) -> 0 | AO22: =IFERROR(__xludf.DUMMYFUNCTION("""COMPUTED_VALUE"""),0.0) -> 0 | AP22: =IFERROR(__xludf.DUMMYFUNCTION("""COMPUTED_VALUE"""),"") | AQ22: =IFERROR(__xludf.DUMMYFUNCTION("""COMPUTED_VALUE"""),100.0) -> 100 | AR22: =IFERROR(__xludf.DUMMYFUNCTION("""COMPUTED_VALUE"""),0.0) -> 0 | AS22: =IFERROR(__xludf.DUMMYFUNCTION("""COMPUTED_VALUE"""),"") | AT22: =IFERROR(__xludf.DUMMYFUNCTION("""COMPUTED_VALUE"""),0.0) -> 0 | AU22: =IFERROR(__xludf.DUMMYFUNCTION("""COMPUTED_VALUE"""),0.0) -> 0 | AV22: =IFERROR(__xludf.DUMMYFUNCTION("""COMPUTED_VALUE"""),"") | AW22: =IFERROR(__xludf.DUMMYFUNCTION("""COMPUTED_VALUE"""),0.0) -> 0 | AX22: =IFERROR(__xludf.DUMMYFUNCTION("""COMPUTED_VALUE"""),0.0) -> 0 | AY22: =IFERROR(__xludf.DUMMYFUNCTION("""COMPUTED_VALUE"""),"") | AZ22: =IFERROR(__xludf.DUMMYFUNCTION("""COMPUTED_VALUE"""),100.0) -> 100 | BA22: =IFERROR(__xludf.DUMMYFUNCTION("""COMPUTED_VALUE"""),0.0) -> 0 | BB22: =IFERROR(__xludf.DUMMYFUNCTION("""COMPUTED_VALUE"""),"")
A23: =IFERROR(__xludf.DUMMYFUNCTION("""COMPUTED_VALUE"""),"63ced843c5c820531c2681a4") -> 63ced843c5c820531c2681a4 | B23: =IFERROR(__xludf.DUMMYFUNCTION("""COMPUTED_VALUE"""),"Axede, S.A.") -> Axede, S.A. | C23: =IFERROR(__xludf.DUMMYFUNCTION("""COMPUTED_VALUE"""),"javier.largacha@al-enterprise.com") -> javier.largacha@al-enterprise.com | D23: =IFERROR(__xludf.DUMMYFUNCTION("""COMPUTED_VALUE"""),"americas") -> americas | E23: =IFERROR(__xludf.DUMMYFUNCTION("""COMPUTED_VALUE"""),"CO") -> CO | F23: =IFERROR(__xludf.DUMMYFUNCTION("""COMPUTED_VALUE"""),"expert_1000") -> expert_1000 | G23: =IFERROR(__xludf.DUMMYFUNCTION("""COMPUTED_VALUE"""),0.0) -> 0 | H23: =IFERROR(__xludf.DUMMYFUNCTION("""COMPUTED_VALUE"""),1.0) -> 1 | I23: =IFERROR(__xludf.DUMMYFUNCTION("""COMPUTED_VALUE"""),0.0) -> 0 | J23: =IFERROR(__xludf.DUMMYFUNCTION("""COMPUTED_VALUE"""),237.1) -> 237.1 | K23: =IFERROR(__xludf.DUMMYFUNCTION("""COMPUTED_VALUE"""),1332.99) -> 1332.99 | L23: =IFERROR(__xludf.DUMMYFUNCTION("""COMPUTED_VALUE"""),0.17787080173144584) -> 0.1778708 | M23: =IFERROR(__xludf.DUMMYFUNCTION("""COMPUTED_VALUE"""),75.0) -> 75 | N23: =IFERROR(__xludf.DUMMYFUNCTION("""COMPUTED_VALUE"""),52.0) -> 52 | O23: =IFERROR(__xludf.DUMMYFUNCTION("""COMPUTED_VALUE"""),1.4423076923076923) -> 1.4423077 | P23: =IFERROR(__xludf.DUMMYFUNCTION("""COMPUTED_VALUE"""),1.0) -> 1 | Q23: =IFERROR(__xludf.DUMMYFUNCTION("""COMPUTED_VALUE"""),1.0) -> 1 | R23: =IFERROR(__xludf.DUMMYFUNCTION("""COMPUTED_VALUE"""),1.0) -> 1 | S23: =IFERROR(__xludf.DUMMYFUNCTION("""COMPUTED_VALUE"""),1.0) -> 1 | T23: =IFERROR(__xludf.DUMMYFUNCTION("""COMPUTED_VALUE"""),1.0) -> 1 | U23: =IFERROR(__xludf.DUMMYFUNCTION("""COMPUTED_VALUE"""),1.0) -> 1 | V23: =IFERROR(__xludf.DUMMYFUNCTION("""COMPUTED_VALUE"""),0.0) -> 0 | W23: =IFERROR(__xludf.DUMMYFUNCTION("""COMPUTED_VALUE"""),1.0) -> 1 | X23: =IFERROR(__xludf.DUMMYFUNCTION("""COMPUTED_VALUE"""),0.0) -> 0 | Y23: =IFERROR(__xludf.DUMMYFUNCTION("""COMPUTED_VALUE"""),2.0) -> 2 | Z23: =IFERROR(__xludf.DUMMYFUNCTION("""COMPUTED_VALUE"""),0.0) -> 0 | AA23: =IFERROR(__xludf.DUMMYFUNCTION("""COMPUTED_VALUE"""),"") | AB23: =IFERROR(__xludf.DUMMYFUNCTION("""COMPUTED_VALUE"""),3.16) -> 3.16 | AC23: =IFERROR(__xludf.DUMMYFUNCTION("""COMPUTED_VALUE"""),1260.6) -> 1260.6 | AD23: =IFERROR(__xludf.DUMMYFUNCTION("""COMPUTED_VALUE"""),0.002506742820878947) -> 0.0025067428 | AE23: =IFERROR(__xludf.DUMMYFUNCTION("""COMPUTED_VALUE"""),972.1) -> 972.1 | AF23: =IFERROR(__xludf.DUMMYFUNCTION("""COMPUTED_VALUE"""),1193.93) -> 1193.93 | AG23: =IFERROR(__xludf.DUMMYFUNCTION("""COMPUTED_VALUE"""),0.8142018376286717) -> 0.81420184 | AH23: =IFERROR(__xludf.DUMMYFUNCTION("""COMPUTED_VALUE"""),217.97) -> 217.97 | AI23: =IFERROR(__xludf.DUMMYFUNCTION("""COMPUTED_VALUE"""),1172.71) -> 1172.71 | AJ23: =IFERROR(__xludf.DUMMYFUNCTION("""COMPUTED_VALUE"""),0.1858686290728313) -> 0.18586863 | AK23: =IFERROR(__xludf.DUMMYFUNCTION("""COMPUTED_VALUE"""),1195.23) -> 1195.23 | AL23: =IFERROR(__xludf.DUMMYFUNCTION("""COMPUTED_VALUE"""),3627.24) -> 3627.24 | AM23: =IFERROR(__xludf.DUMMYFUNCTION("""COMPUTED_VALUE"""),0.3295150031428855) -> 0.329515 | AN23: =IFERROR(__xludf.DUMMYFUNCTION("""COMPUTED_VALUE"""),226.72) -> 226.72 | AO23: =IFERROR(__xludf.DUMMYFUNCTION("""COMPUTED_VALUE"""),0.0) -> 0 | AP23: =IFERROR(__xludf.DUMMYFUNCTION("""COMPUTED_VALUE"""),"") | AQ23: =IFERROR(__xludf.DUMMYFUNCTION("""COMPUTED_VALUE"""),111.89) -> 111.89 | AR23: =IFERROR(__xludf.DUMMYFUNCTION("""COMPUTED_VALUE"""),0.0) -> 0 | AS23: =IFERROR(__xludf.DUMMYFUNCTION("""COMPUTED_VALUE"""),"") | AT23: =IFERROR(__xludf.DUMMYFUNCTION("""COMPUTED_VALUE"""),3.33) -> 3.33 | AU23: =IFERROR(__xludf.DUMMYFUNCTION("""COMPUTED_VALUE"""),0.0) -> 0 | AV23: =IFERROR(__xludf.DUMMYFUNCTION("""COMPUTED_VALUE"""),"") | AW23: =IFERROR(__xludf.DUMMYFUNCTION("""COMPUTED_VALUE"""),4.22) -> 4.22 | AX23: =IFERROR(__xludf.DUMMYFUNCTION("""COMPUTED_VALUE"""),0.0) -> 0 | AY23: =IFERROR(__xludf.DUMMYFUNCTION("""COMPUTED_VALUE"""),"") | AZ23: =IFERROR(__xludf.DUMMYFUNCTION("""COMPUTED_VALUE"""),346.16) -> 346.16 | BA23: =IFERROR(__xludf.DUMMYFUNCTION("""COMPUTED_VALUE"""),0.0) -> 0 | BB23: =IFERROR(__xludf.DUMMYFUNCTION("""COMPUTED_VALUE"""),"")
A24: =IFERROR(__xludf.DUMMYFUNCTION("""COMPUTED_VALUE"""),"63ced845c5c820531c26869f") -> 63ced845c5c820531c26869f | B24: =IFERROR(__xludf.DUMMYFUNCTION("""COMPUTED_VALUE"""),"BFW Kommunikationssysteme GmbH") -> BFW Kommunikationssysteme GmbH | C24: =IFERROR(__xludf.DUMMYFUNCTION("""COMPUTED_VALUE"""),"andreas.grossheimann@al-enterprise.com, katrin.pfeiffer@al-enterprise.com, holger.viktor@al-enterprise.com, sibylle.klopfer@al-enterprise.com, igor.leko@al-enterprise.com") -> andreas.grossheimann@al-enterprise.com, katrin.pfeiffer@al-enterprise.com, holger.viktor@al-enterprise.com, sibylle.klopfer@al-enterprise.com, igor.leko@al-enterprise.com | D24: =IFERROR(__xludf.DUMMYFUNCTION("""COMPUTED_VALUE"""),"germany") -> germany | E24: =IFERROR(__xludf.DUMMYFUNCTION("""COMPUTED_VALUE"""),"DE") -> DE | F24: =IFERROR(__xludf.DUMMYFUNCTION("""COMPUTED_VALUE"""),"expert_200") -> expert_200 | G24: =IFERROR(__xludf.DUMMYFUNCTION("""COMPUTED_VALUE"""),1.0) -> 1 | H24: =IFERROR(__xludf.DUMMYFUNCTION("""COMPUTED_VALUE"""),1.0) -> 1 | I24: =IFERROR(__xludf.DUMMYFUNCTION("""COMPUTED_VALUE"""),1.0) -> 1 | J24: =IFERROR(__xludf.DUMMYFUNCTION("""COMPUTED_VALUE"""),235.23) -> 235.23 | K24: =IFERROR(__xludf.DUMMYFUNCTION("""COMPUTED_VALUE"""),448.0) -> 448 | L24: =IFERROR(__xludf.DUMMYFUNCTION("""COMPUTED_VALUE"""),0.5250669642857143) -> 0.52506696 | M24: =IFERROR(__xludf.DUMMYFUNCTION("""COMPUTED_VALUE"""),36.0) -> 36 | N24: =IFERROR(__xludf.DUMMYFUNCTION("""COMPUTED_VALUE"""),52.0) -> 52 | O24: =IFERROR(__xludf.DUMMYFUNCTION("""COMPUTED_VALUE"""),0.6923076923076923) -> 0.69230769 | P24: =IFERROR(__xludf.DUMMYFUNCTION("""COMPUTED_VALUE"""),1.0) -> 1 | Q24: =IFERROR(__xludf.DUMMYFUNCTION("""COMPUTED_VALUE"""),1.0) -> 1 | R24: =IFERROR(__xludf.DUMMYFUNCTION("""COMPUTED_VALUE"""),1.0) -> 1 | S24: =IFERROR(__xludf.DUMMYFUNCTION("""COMPUTED_VALUE"""),1.0) -> 1 | T24: =IFERROR(__xludf.DUMMYFUNCTION("""COMPUTED_VALUE"""),1.0) -> 1 | U24: =IFERROR(__xludf.DUMMYFUNCTION("""COMPUTED_VALUE"""),1.0) -> 1 | V24: =IFERROR(__xludf.DUMMYFUNCTION("""COMPUTED_VALUE"""),0.0) -> 0 | W24: =IFERROR(__xludf.DUMMYFUNCTION("""COMPUTED_VALUE"""),1.0) -> 1 | X24: =IFERROR(__xludf.DUMMYFUNCTION("""COMPUTED_VALUE"""),0.0) -> 0 | Y24: =IFERROR(__xludf.DUMMYFUNCTION("""COMPUTED_VALUE"""),8.17) -> 8.17 | Z24: =IFERROR(__xludf.DUMMYFUNCTION("""COMPUTED_VALUE"""),0.0) -> 0 | AA24: =IFERROR(__xludf.DUMMYFUNCTION("""COMPUTED_VALUE"""),"") | AB24: =IFERROR(__xludf.DUMMYFUNCTION("""COMPUTED_VALUE"""),0.76) -> 0.76 | AC24: =IFERROR(__xludf.DUMMYFUNCTION("""COMPUTED_VALUE"""),166.67) -> 166.67 | AD24: =IFERROR(__xludf.DUMMYFUNCTION("""COMPUTED_VALUE"""),0.004559908801823964) -> 0.0045599088 | AE24: =IFERROR(__xludf.DUMMYFUNCTION("""COMPUTED_VALUE"""),82.47) -> 82.47 | AF24: =IFERROR(__xludf.DUMMYFUNCTION("""COMPUTED_VALUE"""),156.52) -> 156.52 | AG24: =IFERROR(__xludf.DUMMYFUNCTION("""COMPUTED_VALUE"""),0.5268975210835676) -> 0.52689752 | AH24: =IFERROR(__xludf.DUMMYFUNCTION("""COMPUTED_VALUE"""),486.22) -> 486.22 | AI24: =IFERROR(__xludf.DUMMYFUNCTION("""COMPUTED_VALUE"""),181.16) -> 181.16 | AJ24: =IFERROR(__xludf.DUMMYFUNCTION("""COMPUTED_VALUE"""),2.6839258114374034) -> 2.6839258 | AK24: =IFERROR(__xludf.DUMMYFUNCTION("""COMPUTED_VALUE"""),577.62) -> 577.62 | AL24: =IFERROR(__xludf.DUMMYFUNCTION("""COMPUTED_VALUE"""),504.35) -> 504.35 | AM24: =IFERROR(__xludf.DUMMYFUNCTION("""COMPUTED_VALUE"""),1.1452760979478536) -> 1.1452761 | AN24: =IFERROR(__xludf.DUMMYFUNCTION("""COMPUTED_VALUE"""),66.56) -> 66.56 | AO24: =IFERROR(__xludf.DUMMYFUNCTION("""COMPUTED_VALUE"""),0.0) -> 0 | AP24: =IFERROR(__xludf.DUMMYFUNCTION("""COMPUTED_VALUE"""),"") | AQ24: =IFERROR(__xludf.DUMMYFUNCTION("""COMPUTED_VALUE"""),16.1) -> 16.1 | AR24: =IFERROR(__xludf.DUMMYFUNCTION("""COMPUTED_VALUE"""),0.0) -> 0 | AS24: =IFERROR(__xludf.DUMMYFUNCTION("""COMPUTED_VALUE"""),"") | AT24: =IFERROR(__xludf.DUMMYFUNCTION("""COMPUTED_VALUE"""),21.35) -> 21.35 | AU24: =IFERROR(__xludf.DUMMYFUNCTION("""COMPUTED_VALUE"""),0.0) -> 0 | AV24: =IFERROR(__xludf.DUMMYFUNCTION("""COMPUTED_VALUE"""),"") | AW24: =IFERROR(__xludf.DUMMYFUNCTION("""COMPUTED_VALUE"""),3.31) -> 3.31 | AX24: =IFERROR(__xludf.DUMMYFUNCTION("""COMPUTED_VALUE"""),0.0) -> 0 | AY24: =IFERROR(__xludf.DUMMYFUNCTION("""COMPUTED_VALUE"""),"") | AZ24: =IFERROR(__xludf.DUMMYFUNCTION("""COMPUTED_VALUE"""),107.32) -> 107.32 | BA24: =IFERROR(__xludf.DUMMYFUNCTION("""COMPUTED_VALUE"""),0.0) -> 0 | BB24: =IFERROR(__xludf.DUMMYFUNCTION("""COMPUTED_VALUE"""),"")
A25: =IFERROR(__xludf.DUMMYFUNCTION("""COMPUTED_VALUE"""),"63ced848c5c820531c268d3e") -> 63ced848c5c820531c268d3e | B25: =IFERROR(__xludf.DUMMYFUNCTION("""COMPUTED_VALUE"""),"Binder Systemhaus GmbH") -> Binder Systemhaus GmbH | C25: =IFERROR(__xludf.DUMMYFUNCTION("""COMPUTED_VALUE"""),"robert.weinberger@al-enterprise.com, andreas.grossheimann@al-enterprise.com, katrin.pfeiffer@al-enterprise.com, sibylle.klopfer@al-enterprise.com, igor.leko@al-enterprise.com") -> robert.weinberger@al-enterprise.com, andreas.grossheimann@al-enterprise.com, katrin.pfeiffer@al-enterprise.com, sibylle.klopfer@al-enterprise.com, igor.leko@al-enterprise.com | D25: =IFERROR(__xludf.DUMMYFUNCTION("""COMPUTED_VALUE"""),"germany") -> germany | E25: =IFERROR(__xludf.DUMMYFUNCTION("""COMPUTED_VALUE"""),"DE") -> DE | F25: =IFERROR(__xludf.DUMMYFUNCTION("""COMPUTED_VALUE"""),"expert_1000") -> expert_1000 | G25: =IFERROR(__xludf.DUMMYFUNCTION("""COMPUTED_VALUE"""),1.0) -> 1 | H25: =IFERROR(__xludf.DUMMYFUNCTION("""COMPUTED_VALUE"""),1.0) -> 1 | I25: =IFERROR(__xludf.DUMMYFUNCTION("""COMPUTED_VALUE"""),1.0) -> 1 | J25: =IFERROR(__xludf.DUMMYFUNCTION("""COMPUTED_VALUE"""),497.73) -> 497.73 | K25: =IFERROR(__xludf.DUMMYFUNCTION("""COMPUTED_VALUE"""),1300.0) -> 1300 | L25: =IFERROR(__xludf.DUMMYFUNCTION("""COMPUTED_VALUE"""),0.3828692307692308) -> 0.38286923 | M25: =IFERROR(__xludf.DUMMYFUNCTION("""COMPUTED_VALUE"""),27.0) -> 27 | N25: =IFERROR(__xludf.DUMMYFUNCTION("""COMPUTED_VALUE"""),52.0) -> 52 | O25: =IFERROR(__xludf.DUMMYFUNCTION("""COMPUTED_VALUE"""),0.5192307692307693) -> 0.51923077 | P25: =IFERROR(__xludf.DUMMYFUNCTION("""COMPUTED_VALUE"""),1.0) -> 1 | Q25: =IFERROR(__xludf.DUMMYFUNCTION("""COMPUTED_VALUE"""),1.0) -> 1 | R25: =IFERROR(__xludf.DUMMYFUNCTION("""COMPUTED_VALUE"""),1.0) -> 1 | S25: =IFERROR(__xludf.DUMMYFUNCTION("""COMPUTED_VALUE"""),0.0) -> 0 | T25: =IFERROR(__xludf.DUMMYFUNCTION("""COMPUTED_VALUE"""),1.0) -> 1 | U25: =IFERROR(__xludf.DUMMYFUNCTION("""COMPUTED_VALUE"""),0.0) -> 0 | V25: =IFERROR(__xludf.DUMMYFUNCTION("""COMPUTED_VALUE"""),0.0) -> 0 | W25: =IFERROR(__xludf.DUMMYFUNCTION("""COMPUTED_VALUE"""),1.0) -> 1 | X25: =IFERROR(__xludf.DUMMYFUNCTION("""COMPUTED_VALUE"""),0.0) -> 0 | Y25: =IFERROR(__xludf.DUMMYFUNCTION("""COMPUTED_VALUE"""),4.1) -> 4.1 | Z25: =IFERROR(__xludf.DUMMYFUNCTION("""COMPUTED_VALUE"""),0.0) -> 0 | AA25: =IFERROR(__xludf.DUMMYFUNCTION("""COMPUTED_VALUE"""),"") | AB25: =IFERROR(__xludf.DUMMYFUNCTION("""COMPUTED_VALUE"""),21.09) -> 21.09 | AC25: =IFERROR(__xludf.DUMMYFUNCTION("""COMPUTED_VALUE"""),702.7) -> 702.7 | AD25: =IFERROR(__xludf.DUMMYFUNCTION("""COMPUTED_VALUE"""),0.030012807741568236) -> 0.030012808 | AE25: =IFERROR(__xludf.DUMMYFUNCTION("""COMPUTED_VALUE"""),285.01) -> 285.01 | AF25: =IFERROR(__xludf.DUMMYFUNCTION("""COMPUTED_VALUE"""),1054.05) -> 1054.05 | AG25: =IFERROR(__xludf.DUMMYFUNCTION("""COMPUTED_VALUE"""),0.2703951425454201) -> 0.27039514 | AH25: =IFERROR(__xludf.DUMMYFUNCTION("""COMPUTED_VALUE"""),446.86) -> 446.86 | AI25: =IFERROR(__xludf.DUMMYFUNCTION("""COMPUTED_VALUE"""),1054.05) -> 1054.05 | AJ25: =IFERROR(__xludf.DUMMYFUNCTION("""COMPUTED_VALUE"""),0.4239457331246146) -> 0.42394573 | AK25: =IFERROR(__xludf.DUMMYFUNCTION("""COMPUTED_VALUE"""),757.06) -> 757.06 | AL25: =IFERROR(__xludf.DUMMYFUNCTION("""COMPUTED_VALUE"""),2810.8) -> 2810.8 | AM25: =IFERROR(__xludf.DUMMYFUNCTION("""COMPUTED_VALUE"""),0.2693396897680375) -> 0.26933969 | AN25: =IFERROR(__xludf.DUMMYFUNCTION("""COMPUTED_VALUE"""),116.21) -> 116.21 | AO25: =IFERROR(__xludf.DUMMYFUNCTION("""COMPUTED_VALUE"""),0.0) -> 0 | AP25: =IFERROR(__xludf.DUMMYFUNCTION("""COMPUTED_VALUE"""),"") | AQ25: =IFERROR(__xludf.DUMMYFUNCTION("""COMPUTED_VALUE"""),74.66) -> 74.66 | AR25: =IFERROR(__xludf.DUMMYFUNCTION("""COMPUTED_VALUE"""),0.0) -> 0 | AS25: =IFERROR(__xludf.DUMMYFUNCTION("""COMPUTED_VALUE"""),"") | AT25: =IFERROR(__xludf.DUMMYFUNCTION("""COMPUTED_VALUE"""),18.34) -> 18.34 | AU25: =IFERROR(__xludf.DUMMYFUNCTION("""COMPUTED_VALUE"""),0.0) -> 0 | AV25: =IFERROR(__xludf.DUMMYFUNCTION("""COMPUTED_VALUE"""),"") | AW25: =IFERROR(__xludf.DUMMYFUNCTION("""COMPUTED_VALUE"""),3.05) -> 3.05 | AX25: =IFERROR(__xludf.DUMMYFUNCTION("""COMPUTED_VALUE"""),0.0) -> 0 | AY25: =IFERROR(__xludf.DUMMYFUNCTION("""COMPUTED_VALUE"""),"") | AZ25: =IFERROR(__xludf.DUMMYFUNCTION("""COMPUTED_VALUE"""),212.26000000000002) -> 212.26 | BA25: =IFERROR(__xludf.DUMMYFUNCTION("""COMPUTED_VALUE"""),0.0) -> 0 | BB25: =IFERROR(__xludf.DUMMYFUNCTION("""COMPUTED_VALUE"""),"")
A26: =IFERROR(__xludf.DUMMYFUNCTION("""COMPUTED_VALUE"""),"67a5db6dfa14f2068a0eaf22") -> 67a5db6dfa14f2068a0eaf22 | B26: =IFERROR(__xludf.DUMMYFUNCTION("""COMPUTED_VALUE"""),"Blue Spruce Technologies") -> Blue Spruce Technologies | C26: =IFERROR(__xludf.DUMMYFUNCTION("""COMPUTED_VALUE"""),"brendan.flaherty@al-enterprise.com, michael-j.francis@al-enterprise.com") -> brendan.flaherty@al-enterprise.com, michael-j.francis@al-enterprise.com | D26: =IFERROR(__xludf.DUMMYFUNCTION("""COMPUTED_VALUE"""),"americas") -> americas | E26: =IFERROR(__xludf.DUMMYFUNCTION("""COMPUTED_VALUE"""),"US") -> US | F26: =IFERROR(__xludf.DUMMYFUNCTION("""COMPUTED_VALUE"""),"expert_200") -> expert_200 | G26: =IFERROR(__xludf.DUMMYFUNCTION("""COMPUTED_VALUE"""),1.0) -> 1 | H26: =IFERROR(__xludf.DUMMYFUNCTION("""COMPUTED_VALUE"""),1.0) -> 1 | I26: =IFERROR(__xludf.DUMMYFUNCTION("""COMPUTED_VALUE"""),1.0) -> 1 | J26: =IFERROR(__xludf.DUMMYFUNCTION("""COMPUTED_VALUE"""),6.13) -> 6.13 | K26: =IFERROR(__xludf.DUMMYFUNCTION("""COMPUTED_VALUE"""),550.0) -> 550 | L26: =IFERROR(__xludf.DUMMYFUNCTION("""COMPUTED_VALUE"""),0.011145454545454545) -> 0.011145455 | M26: =IFERROR(__xludf.DUMMYFUNCTION("""COMPUTED_VALUE"""),0.0) -> 0 | N26: =IFERROR(__xludf.DUMMYFUNCTION("""COMPUTED_VALUE"""),0.0) -> 0 | O26: =IFERROR(__xludf.DUMMYFUNCTION("""COMPUTED_VALUE"""),"") | P26: =IFERROR(__xludf.DUMMYFUNCTION("""COMPUTED_VALUE"""),0.0) -> 0 | Q26: =IFERROR(__xludf.DUMMYFUNCTION("""COMPUTED_VALUE"""),1.0) -> 1 | R26: =IFERROR(__xludf.DUMMYFUNCTION("""COMPUTED_VALUE"""),0.0) -> 0 | S26: =IFERROR(__xludf.DUMMYFUNCTION("""COMPUTED_VALUE"""),0.0) -> 0 | T26: =IFERROR(__xludf.DUMMYFUNCTION("""COMPUTED_VALUE"""),1.0) -> 1 | U26: =IFERROR(__xludf.DUMMYFUNCTION("""COMPUTED_VALUE"""),0.0) -> 0 | V26: =IFERROR(__xludf.DUMMYFUNCTION("""COMPUTED_VALUE"""),0.0) -> 0 | W26: =IFERROR(__xludf.DUMMYFUNCTION("""COMPUTED_VALUE"""),1.0) -> 1 | X26: =IFERROR(__xludf.DUMMYFUNCTION("""COMPUTED_VALUE"""),0.0) -> 0 | Y26: =IFERROR(__xludf.DUMMYFUNCTION("""COMPUTED_VALUE"""),115.0) -> 115 | Z26: =IFERROR(__xludf.DUMMYFUNCTION("""COMPUTED_VALUE"""),0.0) -> 0 | AA26: =IFERROR(__xludf.DUMMYFUNCTION("""COMPUTED_VALUE"""),"") | AB26: =IFERROR(__xludf.DUMMYFUNCTION("""COMPUTED_VALUE"""),66.0) -> 66 | AC26: =IFERROR(__xludf.DUMMYFUNCTION("""COMPUTED_VALUE"""),533.33) -> 533.33 | AD26: =IFERROR(__xludf.DUMMYFUNCTION("""COMPUTED_VALUE"""),0.12375077344233401) -> 0.12375077 | AE26: =IFERROR(__xludf.DUMMYFUNCTION("""COMPUTED_VALUE"""),367.93) -> 367.93 | AF26: =IFERROR(__xludf.DUMMYFUNCTION("""COMPUTED_VALUE"""),633.33) -> 633.33 | AG26: =IFERROR(__xludf.DUMMYFUNCTION("""COMPUTED_VALUE"""),0.5809451628692782) -> 0.58094516 | AH26: =IFERROR(__xludf.DUMMYFUNCTION("""COMPUTED_VALUE"""),115.0) -> 115 | AI26: =IFERROR(__xludf.DUMMYFUNCTION("""COMPUTED_VALUE"""),499.98) -> 499.98 | AJ26: =IFERROR(__xludf.DUMMYFUNCTION("""COMPUTED_VALUE"""),0.2300092003680147) -> 0.2300092 | AK26: =IFERROR(__xludf.DUMMYFUNCTION("""COMPUTED_VALUE"""),663.9300000000001) -> 663.93 | AL26: =IFERROR(__xludf.DUMMYFUNCTION("""COMPUTED_VALUE"""),1666.64) -> 1666.64 | AM26: =IFERROR(__xludf.DUMMYFUNCTION("""COMPUTED_VALUE"""),0.3983643738299813) -> 0.39836437 | AN26: =IFERROR(__xludf.DUMMYFUNCTION("""COMPUTED_VALUE"""),0.0) -> 0 | AO26: =IFERROR(__xludf.DUMMYFUNCTION("""COMPUTED_VALUE"""),0.0) -> 0 | AP26: =IFERROR(__xludf.DUMMYFUNCTION("""COMPUTED_VALUE"""),"") | AQ26: =IFERROR(__xludf.DUMMYFUNCTION("""COMPUTED_VALUE"""),929.0) -> 929 | AR26: =IFERROR(__xludf.DUMMYFUNCTION("""COMPUTED_VALUE"""),0.0) -> 0 | AS26: =IFERROR(__xludf.DUMMYFUNCTION("""COMPUTED_VALUE"""),"") | AT26: =IFERROR(__xludf.DUMMYFUNCTION("""COMPUTED_VALUE"""),13.55) -> 13.55 | AU26: =IFERROR(__xludf.DUMMYFUNCTION("""COMPUTED_VALUE"""),0.0) -> 0 | AV26: =IFERROR(__xludf.DUMMYFUNCTION("""COMPUTED_VALUE"""),"") | AW26: =IFERROR(__xludf.DUMMYFUNCTION("""COMPUTED_VALUE"""),40.0) -> 40 | AX26: =IFERROR(__xludf.DUMMYFUNCTION("""COMPUTED_VALUE"""),0.0) -> 0 | AY26: =IFERROR(__xludf.DUMMYFUNCTION("""COMPUTED_VALUE"""),"") | AZ26: =IFERROR(__xludf.DUMMYFUNCTION("""COMPUTED_VALUE"""),982.55) -> 982.55 | BA26: =IFERROR(__xludf.DUMMYFUNCTION("""COMPUTED_VALUE"""),0.0) -> 0 | BB26: =IFERROR(__xludf.DUMMYFUNCTION("""COMPUTED_VALUE"""),"")
A27: =IFERROR(__xludf.DUMMYFUNCTION("""COMPUTED_VALUE"""),"63ea6e9352ad6968805ceab7") -> 63ea6e9352ad6968805ceab7 | B27: =IFERROR(__xludf.DUMMYFUNCTION("""COMPUTED_VALUE"""),"BTD Service GmbH") -> BTD Service GmbH | C27: =IFERROR(__xludf.DUMMYFUNCTION("""COMPUTED_VALUE"""),"thomas.ullmann@al-enterprise.com, andreas.grossheimann@al-enterprise.com, katrin.pfeiffer@al-enterprise.com, sibylle.klopfer@al-enterprise.com, igor.leko@al-enterprise.com") -> thomas.ullmann@al-enterprise.com, andreas.grossheimann@al-enterprise.com, katrin.pfeiffer@al-enterprise.com, sibylle.klopfer@al-enterprise.com, igor.leko@al-enterprise.com | D27: =IFERROR(__xludf.DUMMYFUNCTION("""COMPUTED_VALUE"""),"germany") -> germany | E27: =IFERROR(__xludf.DUMMYFUNCTION("""COMPUTED_VALUE"""),"DE") -> DE | F27: =IFERROR(__xludf.DUMMYFUNCTION("""COMPUTED_VALUE"""),"expert_200") -> expert_200 | G27: =IFERROR(__xludf.DUMMYFUNCTION("""COMPUTED_VALUE"""),1.0) -> 1 | H27: =IFERROR(__xludf.DUMMYFUNCTION("""COMPUTED_VALUE"""),1.0) -> 1 | I27: =IFERROR(__xludf.DUMMYFUNCTION("""COMPUTED_VALUE"""),1.0) -> 1 | J27: =IFERROR(__xludf.DUMMYFUNCTION("""COMPUTED_VALUE"""),424.36) -> 424.36 | K27: =IFERROR(__xludf.DUMMYFUNCTION("""COMPUTED_VALUE"""),612.0) -> 612 | L27: =IFERROR(__xludf.DUMMYFUNCTION("""COMPUTED_VALUE"""),0.6933986928104575) -> 0.69339869 | M27: =IFERROR(__xludf.DUMMYFUNCTION("""COMPUTED_VALUE"""),56.0) -> 56 | N27: =IFERROR(__xludf.DUMMYFUNCTION("""COMPUTED_VALUE"""),52.0) -> 52 | O27: =IFERROR(__xludf.DUMMYFUNCTION("""COMPUTED_VALUE"""),1.0769230769230769) -> 1.0769231 | P27: =IFERROR(__xludf.DUMMYFUNCTION("""COMPUTED_VALUE"""),1.0) -> 1 | Q27: =IFERROR(__xludf.DUMMYFUNCTION("""COMPUTED_VALUE"""),1.0) -> 1 | R27: =IFERROR(__xludf.DUMMYFUNCTION("""COMPUTED_VALUE"""),1.0) -> 1 | S27: =IFERROR(__xludf.DUMMYFUNCTION("""COMPUTED_VALUE"""),1.0) -> 1 | T27: =IFERROR(__xludf.DUMMYFUNCTION("""COMPUTED_VALUE"""),1.0) -> 1 | U27: =IFERROR(__xludf.DUMMYFUNCTION("""COMPUTED_VALUE"""),1.0) -> 1 | V27: =IFERROR(__xludf.DUMMYFUNCTION("""COMPUTED_VALUE"""),0.0) -> 0 | W27: =IFERROR(__xludf.DUMMYFUNCTION("""COMPUTED_VALUE"""),1.0) -> 1 | X27: =IFERROR(__xludf.DUMMYFUNCTION("""COMPUTED_VALUE"""),0.0) -> 0 | Y27: =IFERROR(__xludf.DUMMYFUNCTION("""COMPUTED_VALUE"""),2.49) -> 2.49 | Z27: =IFERROR(__xludf.DUMMYFUNCTION("""COMPUTED_VALUE"""),0.0) -> 0 | AA27: =IFERROR(__xludf.DUMMYFUNCTION("""COMPUTED_VALUE"""),"") | AB27: =IFERROR(__xludf.DUMMYFUNCTION("""COMPUTED_VALUE"""),2.49) -> 2.49 | AC27: =IFERROR(__xludf.DUMMYFUNCTION("""COMPUTED_VALUE"""),313.85) -> 313.85 | AD27: =IFERROR(__xludf.DUMMYFUNCTION("""COMPUTED_VALUE"""),0.007933726302373746) -> 0.0079337263 | AE27: =IFERROR(__xludf.DUMMYFUNCTION("""COMPUTED_VALUE"""),35.79) -> 35.79 | AF27: =IFERROR(__xludf.DUMMYFUNCTION("""COMPUTED_VALUE"""),470.77) -> 470.77 | AG27: =IFERROR(__xludf.DUMMYFUNCTION("""COMPUTED_VALUE"""),0.07602438558106932) -> 0.076024386 | AH27: =IFERROR(__xludf.DUMMYFUNCTION("""COMPUTED_VALUE"""),630.0) -> 630 | AI27: =IFERROR(__xludf.DUMMYFUNCTION("""COMPUTED_VALUE"""),470.77) -> 470.77 | AJ27: =IFERROR(__xludf.DUMMYFUNCTION("""COMPUTED_VALUE"""),1.3382331074622427) -> 1.3382331 | AK27: =IFERROR(__xludf.DUMMYFUNCTION("""COMPUTED_VALUE"""),670.77) -> 670.77 | AL27: =IFERROR(__xludf.DUMMYFUNCTION("""COMPUTED_VALUE"""),1255.3899999999999) -> 1255.39 | AM27: =IFERROR(__xludf.DUMMYFUNCTION("""COMPUTED_VALUE"""),0.5343120464556831) -> 0.53431205 | AN27: =IFERROR(__xludf.DUMMYFUNCTION("""COMPUTED_VALUE"""),300.0) -> 300 | AO27: =IFERROR(__xludf.DUMMYFUNCTION("""COMPUTED_VALUE"""),0.0) -> 0 | AP27: =IFERROR(__xludf.DUMMYFUNCTION("""COMPUTED_VALUE"""),"") | AQ27: =IFERROR(__xludf.DUMMYFUNCTION("""COMPUTED_VALUE"""),0.0) -> 0 | AR27: =IFERROR(__xludf.DUMMYFUNCTION("""COMPUTED_VALUE"""),0.0) -> 0 | AS27: =IFERROR(__xludf.DUMMYFUNCTION("""COMPUTED_VALUE"""),"") | AT27: =IFERROR(__xludf.DUMMYFUNCTION("""COMPUTED_VALUE"""),0.0) -> 0 | AU27: =IFERROR(__xludf.DUMMYFUNCTION("""COMPUTED_VALUE"""),0.0) -> 0 | AV27: =IFERROR(__xludf.DUMMYFUNCTION("""COMPUTED_VALUE"""),"") | AW27: =IFERROR(__xludf.DUMMYFUNCTION("""COMPUTED_VALUE"""),432.0) -> 432 | AX27: =IFERROR(__xludf.DUMMYFUNCTION("""COMPUTED_VALUE"""),0.0) -> 0 | AY27: =IFERROR(__xludf.DUMMYFUNCTION("""COMPUTED_VALUE"""),"") | AZ27: =IFERROR(__xludf.DUMMYFUNCTION("""COMPUTED_VALUE"""),732.0) -> 732 | BA27: =IFERROR(__xludf.DUMMYFUNCTION("""COMPUTED_VALUE"""),0.0) -> 0 | BB27: =IFERROR(__xludf.DUMMYFUNCTION("""COMPUTED_VALUE"""),"")
A28: =IFERROR(__xludf.DUMMYFUNCTION("""COMPUTED_VALUE"""),"63ea6e9352ad6968805ceb0b") -> 63ea6e9352ad6968805ceb0b | B28: =IFERROR(__xludf.DUMMYFUNCTION("""COMPUTED_VALUE"""),"Bunsieck & Partner GmbH") -> Bunsieck & Partner GmbH | C28: =IFERROR(__xludf.DUMMYFUNCTION("""COMPUTED_VALUE"""),"ralf.kloeppels@al-enterprise.com, andreas.grossheimann@al-enterprise.com, katrin.pfeiffer@al-enterprise.com, sibylle.klopfer@al-enterprise.com, igor.leko@al-enterprise.com") -> ralf.kloeppels@al-enterprise.com, andreas.grossheimann@al-enterprise.com, katrin.pfeiffer@al-enterprise.com, sibylle.klopfer@al-enterprise.com, igor.leko@al-enterprise.com | D28: =IFERROR(__xludf.DUMMYFUNCTION("""COMPUTED_VALUE"""),"germany") -> germany | E28: =IFERROR(__xludf.DUMMYFUNCTION("""COMPUTED_VALUE"""),"DE") -> DE | F28: =IFERROR(__xludf.DUMMYFUNCTION("""COMPUTED_VALUE"""),"expert_200") -> expert_200 | G28: =IFERROR(__xludf.DUMMYFUNCTION("""COMPUTED_VALUE"""),1.0) -> 1 | H28: =IFERROR(__xludf.DUMMYFUNCTION("""COMPUTED_VALUE"""),1.0) -> 1 | I28: =IFERROR(__xludf.DUMMYFUNCTION("""COMPUTED_VALUE"""),1.0) -> 1 | J28: =IFERROR(__xludf.DUMMYFUNCTION("""COMPUTED_VALUE"""),128.59) -> 128.59 | K28: =IFERROR(__xludf.DUMMYFUNCTION("""COMPUTED_VALUE"""),345.0) -> 345 | L28: =IFERROR(__xludf.DUMMYFUNCTION("""COMPUTED_VALUE"""),0.37272463768115943) -> 0.37272464 | M28: =IFERROR(__xludf.DUMMYFUNCTION("""COMPUTED_VALUE"""),31.0) -> 31 | N28: =IFERROR(__xludf.DUMMYFUNCTION("""COMPUTED_VALUE"""),52.0) -> 52 | O28: =IFERROR(__xludf.DUMMYFUNCTION("""COMPUTED_VALUE"""),0.5961538461538461) -> 0.59615385 | P28: =IFERROR(__xludf.DUMMYFUNCTION("""COMPUTED_VALUE"""),1.0) -> 1 | Q28: =IFERROR(__xludf.DUMMYFUNCTION("""COMPUTED_VALUE"""),1.0) -> 1 | R28: =IFERROR(__xludf.DUMMYFUNCTION("""COMPUTED_VALUE"""),1.0) -> 1 | S28: =IFERROR(__xludf.DUMMYFUNCTION("""COMPUTED_VALUE"""),1.0) -> 1 | T28: =IFERROR(__xludf.DUMMYFUNCTION("""COMPUTED_VALUE"""),1.0) -> 1 | U28: =IFERROR(__xludf.DUMMYFUNCTION("""COMPUTED_VALUE"""),1.0) -> 1 | V28: =IFERROR(__xludf.DUMMYFUNCTION("""COMPUTED_VALUE"""),1.0) -> 1 | W28: =IFERROR(__xludf.DUMMYFUNCTION("""COMPUTED_VALUE"""),1.0) -> 1 | X28: =IFERROR(__xludf.DUMMYFUNCTION("""COMPUTED_VALUE"""),1.0) -> 1 | Y28: =IFERROR(__xludf.DUMMYFUNCTION("""COMPUTED_VALUE"""),21.9) -> 21.9 | Z28: =IFERROR(__xludf.DUMMYFUNCTION("""COMPUTED_VALUE"""),0.0) -> 0 | AA28: =IFERROR(__xludf.DUMMYFUNCTION("""COMPUTED_VALUE"""),"") | AB28: =IFERROR(__xludf.DUMMYFUNCTION("""COMPUTED_VALUE"""),19.83) -> 19.83 | AC28: =IFERROR(__xludf.DUMMYFUNCTION("""COMPUTED_VALUE"""),230.0) -> 230 | AD28: =IFERROR(__xludf.DUMMYFUNCTION("""COMPUTED_VALUE"""),0.08621739130434782) -> 0.086217391 | AE28: =IFERROR(__xludf.DUMMYFUNCTION("""COMPUTED_VALUE"""),42.27) -> 42.27 | AF28: =IFERROR(__xludf.DUMMYFUNCTION("""COMPUTED_VALUE"""),326.67) -> 326.67 | AG28: =IFERROR(__xludf.DUMMYFUNCTION("""COMPUTED_VALUE"""),0.12939663880980806) -> 0.12939664 | AH28: =IFERROR(__xludf.DUMMYFUNCTION("""COMPUTED_VALUE"""),338.62) -> 338.62 | AI28: =IFERROR(__xludf.DUMMYFUNCTION("""COMPUTED_VALUE"""),363.33) -> 363.33 | AJ28: =IFERROR(__xludf.DUMMYFUNCTION("""COMPUTED_VALUE"""),0.9319902017449702) -> 0.9319902 | AK28: =IFERROR(__xludf.DUMMYFUNCTION("""COMPUTED_VALUE"""),422.62) -> 422.62 | AL28: =IFERROR(__xludf.DUMMYFUNCTION("""COMPUTED_VALUE"""),920.0) -> 920 | AM28: =IFERROR(__xludf.DUMMYFUNCTION("""COMPUTED_VALUE"""),0.4593695652173913) -> 0.45936957 | AN28: =IFERROR(__xludf.DUMMYFUNCTION("""COMPUTED_VALUE"""),0.0) -> 0 | AO28: =IFERROR(__xludf.DUMMYFUNCTION("""COMPUTED_VALUE"""),0.0) -> 0 | AP28: =IFERROR(__xludf.DUMMYFUNCTION("""COMPUTED_VALUE"""),"") | AQ28: =IFERROR(__xludf.DUMMYFUNCTION("""COMPUTED_VALUE"""),0.0) -> 0 | AR28: =IFERROR(__xludf.DUMMYFUNCTION("""COMPUTED_VALUE"""),0.0) -> 0 | AS28: =IFERROR(__xludf.DUMMYFUNCTION("""COMPUTED_VALUE"""),"") | AT28: =IFERROR(__xludf.DUMMYFUNCTION("""COMPUTED_VALUE"""),15.0) -> 15 | AU28: =IFERROR(__xludf.DUMMYFUNCTION("""COMPUTED_VALUE"""),0.0) -> 0 | AV28: =IFERROR(__xludf.DUMMYFUNCTION("""COMPUTED_VALUE"""),"") | AW28: =IFERROR(__xludf.DUMMYFUNCTION("""COMPUTED_VALUE"""),110.3) -> 110.3 | AX28: =IFERROR(__xludf.DUMMYFUNCTION("""COMPUTED_VALUE"""),0.0) -> 0 | AY28: =IFERROR(__xludf.DUMMYFUNCTION("""COMPUTED_VALUE"""),"") | AZ28: =IFERROR(__xludf.DUMMYFUNCTION("""COMPUTED_VALUE"""),125.3) -> 125.3 | BA28: =IFERROR(__xludf.DUMMYFUNCTION("""COMPUTED_VALUE"""),0.0) -> 0 | BB28: =IFERROR(__xludf.DUMMYFUNCTION("""COMPUTED_VALUE"""),"")
A29: =IFERROR(__xludf.DUMMYFUNCTION("""COMPUTED_VALUE"""),"63ced848c5c820531c268d7a") -> 63ced848c5c820531c268d7a | B29: =IFERROR(__xludf.DUMMYFUNCTION("""COMPUTED_VALUE"""),"Burgess Computer Decisions") -> Burgess Computer Decisions | C29: =IFERROR(__xludf.DUMMYFUNCTION("""COMPUTED_VALUE"""),"holly.berger@al-enterprise.com") -> holly.berger@al-enterprise.com | D29: =IFERROR(__xludf.DUMMYFUNCTION("""COMPUTED_VALUE"""),"americas") -> americas | E29: =IFERROR(__xludf.DUMMYFUNCTION("""COMPUTED_VALUE"""),"US") -> US | F29: =IFERROR(__xludf.DUMMYFUNCTION("""COMPUTED_VALUE"""),"distributor") -> distributor | G29: =IFERROR(__xludf.DUMMYFUNCTION("""COMPUTED_VALUE"""),0.0) -> 0 | H29: =IFERROR(__xludf.DUMMYFUNCTION("""COMPUTED_VALUE"""),1.0) -> 1 | I29: =IFERROR(__xludf.DUMMYFUNCTION("""COMPUTED_VALUE"""),0.0) -> 0 | J29: =IFERROR(__xludf.DUMMYFUNCTION("""COMPUTED_VALUE"""),582.88) -> 582.88 | K29: =IFERROR(__xludf.DUMMYFUNCTION("""COMPUTED_VALUE"""),1143.99) -> 1143.99 | L29: =IFERROR(__xludf.DUMMYFUNCTION("""COMPUTED_VALUE"""),0.5095149433124415) -> 0.50951494 | M29: =IFERROR(__xludf.DUMMYFUNCTION("""COMPUTED_VALUE"""),38.0) -> 38 | N29: =IFERROR(__xludf.DUMMYFUNCTION("""COMPUTED_VALUE"""),56.0) -> 56 | O29: =IFERROR(__xludf.DUMMYFUNCTION("""COMPUTED_VALUE"""),0.6785714285714286) -> 0.67857143 | P29: =IFERROR(__xludf.DUMMYFUNCTION("""COMPUTED_VALUE"""),0.0) -> 0 | Q29: =IFERROR(__xludf.DUMMYFUNCTION("""COMPUTED_VALUE"""),1.0) -> 1 | R29: =IFERROR(__xludf.DUMMYFUNCTION("""COMPUTED_VALUE"""),0.0) -> 0 | S29: =IFERROR(__xludf.DUMMYFUNCTION("""COMPUTED_VALUE"""),0.0) -> 0 | T29: =IFERROR(__xludf.DUMMYFUNCTION("""COMPUTED_VALUE"""),1.0) -> 1 | U29: =IFERROR(__xludf.DUMMYFUNCTION("""COMPUTED_VALUE"""),0.0) -> 0 | V29: =IFERROR(__xludf.DUMMYFUNCTION("""COMPUTED_VALUE"""),0.0) -> 0 | W29: =IFERROR(__xludf.DUMMYFUNCTION("""COMPUTED_VALUE"""),1.0) -> 1 | X29: =IFERROR(__xludf.DUMMYFUNCTION("""COMPUTED_VALUE"""),0.0) -> 0 | Y29: =IFERROR(__xludf.DUMMYFUNCTION("""COMPUTED_VALUE"""),19.83) -> 19.83 | Z29: =IFERROR(__xludf.DUMMYFUNCTION("""COMPUTED_VALUE"""),0.0) -> 0 | AA29: =IFERROR(__xludf.DUMMYFUNCTION("""COMPUTED_VALUE"""),"") | AB29: =IFERROR(__xludf.DUMMYFUNCTION("""COMPUTED_VALUE"""),56.78) -> 56.78 | AC29: =IFERROR(__xludf.DUMMYFUNCTION("""COMPUTED_VALUE"""),759.99) -> 759.99 | AD29: =IFERROR(__xludf.DUMMYFUNCTION("""COMPUTED_VALUE"""),0.07471150936196529) -> 0.074711509 | AE29: =IFERROR(__xludf.DUMMYFUNCTION("""COMPUTED_VALUE"""),157.12) -> 157.12 | AF29: =IFERROR(__xludf.DUMMYFUNCTION("""COMPUTED_VALUE"""),1143.32) -> 1143.32 | AG29: =IFERROR(__xludf.DUMMYFUNCTION("""COMPUTED_VALUE"""),0.1374243431410279) -> 0.13742434 | AH29: =IFERROR(__xludf.DUMMYFUNCTION("""COMPUTED_VALUE"""),1009.5) -> 1009.5 | AI29: =IFERROR(__xludf.DUMMYFUNCTION("""COMPUTED_VALUE"""),1146.66) -> 1146.66 | AJ29: =IFERROR(__xludf.DUMMYFUNCTION("""COMPUTED_VALUE"""),0.8803830254827062) -> 0.88038303 | AK29: =IFERROR(__xludf.DUMMYFUNCTION("""COMPUTED_VALUE"""),1243.23) -> 1243.23 | AL29: =IFERROR(__xludf.DUMMYFUNCTION("""COMPUTED_VALUE"""),3049.9700000000003) -> 3049.97 | AM29: =IFERROR(__xludf.DUMMYFUNCTION("""COMPUTED_VALUE"""),0.4076204028236343) -> 0.4076204 | AN29: =IFERROR(__xludf.DUMMYFUNCTION("""COMPUTED_VALUE"""),0.0) -> 0 | AO29: =IFERROR(__xludf.DUMMYFUNCTION("""COMPUTED_VALUE"""),0.0) -> 0 | AP29: =IFERROR(__xludf.DUMMYFUNCTION("""COMPUTED_VALUE"""),"") | AQ29: =IFERROR(__xludf.DUMMYFUNCTION("""COMPUTED_VALUE"""),0.0) -> 0 | AR29: =IFERROR(__xludf.DUMMYFUNCTION("""COMPUTED_VALUE"""),0.0) -> 0 | AS29: =IFERROR(__xludf.DUMMYFUNCTION("""COMPUTED_VALUE"""),"") | AT29: =IFERROR(__xludf.DUMMYFUNCTION("""COMPUTED_VALUE"""),0.0) -> 0 | AU29: =IFERROR(__xludf.DUMMYFUNCTION("""COMPUTED_VALUE"""),0.0) -> 0 | AV29: =IFERROR(__xludf.DUMMYFUNCTION("""COMPUTED_VALUE"""),"") | AW29: =IFERROR(__xludf.DUMMYFUNCTION("""COMPUTED_VALUE"""),0.0) -> 0 | AX29: =IFERROR(__xludf.DUMMYFUNCTION("""COMPUTED_VALUE"""),0.0) -> 0 | AY29: =IFERROR(__xludf.DUMMYFUNCTION("""COMPUTED_VALUE"""),"") | AZ29: =IFERROR(__xludf.DUMMYFUNCTION("""COMPUTED_VALUE"""),0.0) -> 0 | BA29: =IFERROR(__xludf.DUMMYFUNCTION("""COMPUTED_VALUE"""),0.0) -> 0 | BB29: =IFERROR(__xludf.DUMMYFUNCTION("""COMPUTED_VALUE"""),"")
A30: =IFERROR(__xludf.DUMMYFUNCTION("""COMPUTED_VALUE"""),"633dbc6cec522e697b5af915") -> 633dbc6cec522e697b5af915 | B30: =IFERROR(__xludf.DUMMYFUNCTION("""COMPUTED_VALUE"""),"C.H.T. Heinemann GmbH") -> C.H.T. Heinemann GmbH | C30: =IFERROR(__xludf.DUMMYFUNCTION("""COMPUTED_VALUE"""),"philippe.girard@al-enterprise.com, rui.silva@al-enterprise.com, ralf.kloeppels@al-enterprise.com, andreas.grossheimann@al-enterprise.com, katrin.pfeiffer@al-enterprise.com, sibylle.klopfer@al-enterprise.com, igor.leko@al-enterprise.com") -> philippe.girard@al-enterprise.com, rui.silva@al-enterprise.com, ralf.kloeppels@al-enterprise.com, andreas.grossheimann@al-enterprise.com, katrin.pfeiffer@al-enterprise.com, sibylle.klopfer@al-enterprise.com, igor.leko@al-enterprise.com | D30: =IFERROR(__xludf.DUMMYFUNCTION("""COMPUTED_VALUE"""),"germany") -> germany | E30: =IFERROR(__xludf.DUMMYFUNCTION("""COMPUTED_VALUE"""),"DE") -> DE | F30: =IFERROR(__xludf.DUMMYFUNCTION("""COMPUTED_VALUE"""),"expert_200") -> expert_200 | G30: =IFERROR(__xludf.DUMMYFUNCTION("""COMPUTED_VALUE"""),1.0) -> 1 | H30: =IFERROR(__xludf.DUMMYFUNCTION("""COMPUTED_VALUE"""),1.0) -> 1 | I30: =IFERROR(__xludf.DUMMYFUNCTION("""COMPUTED_VALUE"""),1.0) -> 1 | J30: =IFERROR(__xludf.DUMMYFUNCTION("""COMPUTED_VALUE"""),153.16) -> 153.16 | K30: =IFERROR(__xludf.DUMMYFUNCTION("""COMPUTED_VALUE"""),407.0) -> 407 | L30: =IFERROR(__xludf.DUMMYFUNCTION("""COMPUTED_VALUE"""),0.3763144963144963) -> 0.3763145 | M30: =IFERROR(__xludf.DUMMYFUNCTION("""COMPUTED_VALUE"""),42.0) -> 42 | N30: =IFERROR(__xludf.DUMMYFUNCTION("""COMPUTED_VALUE"""),52.0) -> 52 | O30: =IFERROR(__xludf.DUMMYFUNCTION("""COMPUTED_VALUE"""),0.8076923076923077) -> 0.80769231 | P30: =IFERROR(__xludf.DUMMYFUNCTION("""COMPUTED_VALUE"""),1.0) -> 1 | Q30: =IFERROR(__xludf.DUMMYFUNCTION("""COMPUTED_VALUE"""),1.0) -> 1 | R30: =IFERROR(__xludf.DUMMYFUNCTION("""COMPUTED_VALUE"""),1.0) -> 1 | S30: =IFERROR(__xludf.DUMMYFUNCTION("""COMPUTED_VALUE"""),1.0) -> 1 | T30: =IFERROR(__xludf.DUMMYFUNCTION("""COMPUTED_VALUE"""),1.0) -> 1 | U30: =IFERROR(__xludf.DUMMYFUNCTION("""COMPUTED_VALUE"""),1.0) -> 1 | V30: =IFERROR(__xludf.DUMMYFUNCTION("""COMPUTED_VALUE"""),1.0) -> 1 | W30: =IFERROR(__xludf.DUMMYFUNCTION("""COMPUTED_VALUE"""),1.0) -> 1 | X30: =IFERROR(__xludf.DUMMYFUNCTION("""COMPUTED_VALUE"""),1.0) -> 1 | Y30: =IFERROR(__xludf.DUMMYFUNCTION("""COMPUTED_VALUE"""),4.68) -> 4.68 | Z30: =IFERROR(__xludf.DUMMYFUNCTION("""COMPUTED_VALUE"""),0.0) -> 0 | AA30: =IFERROR(__xludf.DUMMYFUNCTION("""COMPUTED_VALUE"""),"") | AB30: =IFERROR(__xludf.DUMMYFUNCTION("""COMPUTED_VALUE"""),2.42) -> 2.42 | AC30: =IFERROR(__xludf.DUMMYFUNCTION("""COMPUTED_VALUE"""),186.36) -> 186.36 | AD30: =IFERROR(__xludf.DUMMYFUNCTION("""COMPUTED_VALUE"""),0.012985619231594761) -> 0.012985619 | AE30: =IFERROR(__xludf.DUMMYFUNCTION("""COMPUTED_VALUE"""),4.68) -> 4.68 | AF30: =IFERROR(__xludf.DUMMYFUNCTION("""COMPUTED_VALUE"""),231.82) -> 231.82 | AG30: =IFERROR(__xludf.DUMMYFUNCTION("""COMPUTED_VALUE"""),0.020188076956259165) -> 0.020188077 | AH30: =IFERROR(__xludf.DUMMYFUNCTION("""COMPUTED_VALUE"""),229.03) -> 229.03 | AI30: =IFERROR(__xludf.DUMMYFUNCTION("""COMPUTED_VALUE"""),322.73) -> 322.73 | AJ30: =IFERROR(__xludf.DUMMYFUNCTION("""COMPUTED_VALUE"""),0.7096644253710531) -> 0.70966443 | AK30: =IFERROR(__xludf.DUMMYFUNCTION("""COMPUTED_VALUE"""),240.81) -> 240.81 | AL30: =IFERROR(__xludf.DUMMYFUNCTION("""COMPUTED_VALUE"""),740.9100000000001) -> 740.91 | AM30: =IFERROR(__xludf.DUMMYFUNCTION("""COMPUTED_VALUE"""),0.3250192331052354) -> 0.32501923 | AN30: =IFERROR(__xludf.DUMMYFUNCTION("""COMPUTED_VALUE"""),0.0) -> 0 | AO30: =IFERROR(__xludf.DUMMYFUNCTION("""COMPUTED_VALUE"""),0.0) -> 0 | AP30: =IFERROR(__xludf.DUMMYFUNCTION("""COMPUTED_VALUE"""),"") | AQ30: =IFERROR(__xludf.DUMMYFUNCTION("""COMPUTED_VALUE"""),0.0) -> 0 | AR30: =IFERROR(__xludf.DUMMYFUNCTION("""COMPUTED_VALUE"""),0.0) -> 0 | AS30: =IFERROR(__xludf.DUMMYFUNCTION("""COMPUTED_VALUE"""),"") | AT30: =IFERROR(__xludf.DUMMYFUNCTION("""COMPUTED_VALUE"""),0.0) -> 0 | AU30: =IFERROR(__xludf.DUMMYFUNCTION("""COMPUTED_VALUE"""),0.0) -> 0 | AV30: =IFERROR(__xludf.DUMMYFUNCTION("""COMPUTED_VALUE"""),"") | AW30: =IFERROR(__xludf.DUMMYFUNCTION("""COMPUTED_VALUE"""),0.0) -> 0 | AX30: =IFERROR(__xludf.DUMMYFUNCTION("""COMPUTED_VALUE"""),0.0) -> 0 | AY30: =IFERROR(__xludf.DUMMYFUNCTION("""COMPUTED_VALUE"""),"") | AZ30: =IFERROR(__xludf.DUMMYFUNCTION("""COMPUTED_VALUE"""),0.0) -> 0 | BA30: =IFERROR(__xludf.DUMMYFUNCTION("""COMPUTED_VALUE"""),0.0) -> 0 | BB30: =IFERROR(__xludf.DUMMYFUNCTION("""COMPUTED_VALUE"""),"")
A31: =IFERROR(__xludf.DUMMYFUNCTION("""COMPUTED_VALUE"""),"63ea6e9352ad6968805ceaa9") -> 63ea6e9352ad6968805ceaa9 | B31: =IFERROR(__xludf.DUMMYFUNCTION("""COMPUTED_VALUE"""),"Call-Data-Systems GmbH") -> Call-Data-Systems GmbH | C31: =IFERROR(__xludf.DUMMYFUNCTION("""COMPUTED_VALUE"""),"andreas.grossheimann@al-enterprise.com, katrin.pfeiffer@al-enterprise.com, sibylle.klopfer@al-enterprise.com, igor.leko@al-enterprise.com, hakan.adiguezel@al-enterprise.com") -> andreas.grossheimann@al-enterprise.com, katrin.pfeiffer@al-enterprise.com, sibylle.klopfer@al-enterprise.com, igor.leko@al-enterprise.com, hakan.adiguezel@al-enterprise.com | D31: =IFERROR(__xludf.DUMMYFUNCTION("""COMPUTED_VALUE"""),"germany") -> germany | E31: =IFERROR(__xludf.DUMMYFUNCTION("""COMPUTED_VALUE"""),"DE") -> DE | F31: =IFERROR(__xludf.DUMMYFUNCTION("""COMPUTED_VALUE"""),"expert_200") -> expert_200 | G31: =IFERROR(__xludf.DUMMYFUNCTION("""COMPUTED_VALUE"""),1.0) -> 1 | H31: =IFERROR(__xludf.DUMMYFUNCTION("""COMPUTED_VALUE"""),1.0) -> 1 | I31: =IFERROR(__xludf.DUMMYFUNCTION("""COMPUTED_VALUE"""),1.0) -> 1 | J31: =IFERROR(__xludf.DUMMYFUNCTION("""COMPUTED_VALUE"""),289.89) -> 289.89 | K31: =IFERROR(__xludf.DUMMYFUNCTION("""COMPUTED_VALUE"""),926.0) -> 926 | L31: =IFERROR(__xludf.DUMMYFUNCTION("""COMPUTED_VALUE"""),0.3130561555075594) -> 0.31305616 | M31: =IFERROR(__xludf.DUMMYFUNCTION("""COMPUTED_VALUE"""),40.0) -> 40 | N31: =IFERROR(__xludf.DUMMYFUNCTION("""COMPUTED_VALUE"""),52.0) -> 52 | O31: =IFERROR(__xludf.DUMMYFUNCTION("""COMPUTED_VALUE"""),0.7692307692307693) -> 0.76923077 | P31: =IFERROR(__xludf.DUMMYFUNCTION("""COMPUTED_VALUE"""),1.0) -> 1 | Q31: =IFERROR(__xludf.DUMMYFUNCTION("""COMPUTED_VALUE"""),1.0) -> 1 | R31: =IFERROR(__xludf.DUMMYFUNCTION("""COMPUTED_VALUE"""),1.0) -> 1 | S31: =IFERROR(__xludf.DUMMYFUNCTION("""COMPUTED_VALUE"""),1.0) -> 1 | T31: =IFERROR(__xludf.DUMMYFUNCTION("""COMPUTED_VALUE"""),1.0) -> 1 | U31: =IFERROR(__xludf.DUMMYFUNCTION("""COMPUTED_VALUE"""),1.0) -> 1 | V31: =IFERROR(__xludf.DUMMYFUNCTION("""COMPUTED_VALUE"""),1.0) -> 1 | W31: =IFERROR(__xludf.DUMMYFUNCTION("""COMPUTED_VALUE"""),1.0) -> 1 | X31: =IFERROR(__xludf.DUMMYFUNCTION("""COMPUTED_VALUE"""),1.0) -> 1 | Y31: =IFERROR(__xludf.DUMMYFUNCTION("""COMPUTED_VALUE"""),0.59) -> 0.59 | Z31: =IFERROR(__xludf.DUMMYFUNCTION("""COMPUTED_VALUE"""),0.0) -> 0 | AA31: =IFERROR(__xludf.DUMMYFUNCTION("""COMPUTED_VALUE"""),"") | AB31: =IFERROR(__xludf.DUMMYFUNCTION("""COMPUTED_VALUE"""),12.97) -> 12.97 | AC31: =IFERROR(__xludf.DUMMYFUNCTION("""COMPUTED_VALUE"""),440.95) -> 440.95 | AD31: =IFERROR(__xludf.DUMMYFUNCTION("""COMPUTED_VALUE"""),0.029413765733076316) -> 0.029413766 | AE31: =IFERROR(__xludf.DUMMYFUNCTION("""COMPUTED_VALUE"""),90.97) -> 90.97 | AF31: =IFERROR(__xludf.DUMMYFUNCTION("""COMPUTED_VALUE"""),661.43) -> 661.43 | AG31: =IFERROR(__xludf.DUMMYFUNCTION("""COMPUTED_VALUE"""),0.13753534009645768) -> 0.13753534 | AH31: =IFERROR(__xludf.DUMMYFUNCTION("""COMPUTED_VALUE"""),340.9) -> 340.9 | AI31: =IFERROR(__xludf.DUMMYFUNCTION("""COMPUTED_VALUE"""),661.43) -> 661.43 | AJ31: =IFERROR(__xludf.DUMMYFUNCTION("""COMPUTED_VALUE"""),0.5153984548629484) -> 0.51539845 | AK31: =IFERROR(__xludf.DUMMYFUNCTION("""COMPUTED_VALUE"""),445.42999999999995) -> 445.43 | AL31: =IFERROR(__xludf.DUMMYFUNCTION("""COMPUTED_VALUE"""),1763.81) -> 1763.81 | AM31: =IFERROR(__xludf.DUMMYFUNCTION("""COMPUTED_VALUE"""),0.252538538731496) -> 0.25253854 | AN31: =IFERROR(__xludf.DUMMYFUNCTION("""COMPUTED_VALUE"""),25.0) -> 25 | AO31: =IFERROR(__xludf.DUMMYFUNCTION("""COMPUTED_VALUE"""),0.0) -> 0 | AP31: =IFERROR(__xludf.DUMMYFUNCTION("""COMPUTED_VALUE"""),"") | AQ31: =IFERROR(__xludf.DUMMYFUNCTION("""COMPUTED_VALUE"""),567.55) -> 567.55 | AR31: =IFERROR(__xludf.DUMMYFUNCTION("""COMPUTED_VALUE"""),0.0) -> 0 | AS31: =IFERROR(__xludf.DUMMYFUNCTION("""COMPUTED_VALUE"""),"") | AT31: =IFERROR(__xludf.DUMMYFUNCTION("""COMPUTED_VALUE"""),0.46) -> 0.46 | AU31: =IFERROR(__xludf.DUMMYFUNCTION("""COMPUTED_VALUE"""),0.0) -> 0 | AV31: =IFERROR(__xludf.DUMMYFUNCTION("""COMPUTED_VALUE"""),"") | AW31: =IFERROR(__xludf.DUMMYFUNCTION("""COMPUTED_VALUE"""),0.0) -> 0 | AX31: =IFERROR(__xludf.DUMMYFUNCTION("""COMPUTED_VALUE"""),0.0) -> 0 | AY31: =IFERROR(__xludf.DUMMYFUNCTION("""COMPUTED_VALUE"""),"") | AZ31: =IFERROR(__xludf.DUMMYFUNCTION("""COMPUTED_VALUE"""),593.01) -> 593.01 | BA31: =IFERROR(__xludf.DUMMYFUNCTION("""COMPUTED_VALUE"""),0.0) -> 0 | BB31: =IFERROR(__xludf.DUMMYFUNCTION("""COMPUTED_VALUE"""),"")
A32: =IFERROR(__xludf.DUMMYFUNCTION("""COMPUTED_VALUE"""),"63fcbb84a107c871cf565293") -> 63fcbb84a107c871cf565293 | B32: =IFERROR(__xludf.DUMMYFUNCTION("""COMPUTED_VALUE"""),"Christmann Informationstechnik") -> Christmann Informationstechnik | C32: =IFERROR(__xludf.DUMMYFUNCTION("""COMPUTED_VALUE"""),"michael.moog@al-enterprise.com, philipp.bode@al-enterprise.com") -> michael.moog@al-enterprise.com, philipp.bode@al-enterprise.com | D32: =IFERROR(__xludf.DUMMYFUNCTION("""COMPUTED_VALUE"""),"germany") -> germany | E32: =IFERROR(__xludf.DUMMYFUNCTION("""COMPUTED_VALUE"""),"DE") -> DE | F32: =IFERROR(__xludf.DUMMYFUNCTION("""COMPUTED_VALUE"""),"expert_200") -> expert_200 | G32: =IFERROR(__xludf.DUMMYFUNCTION("""COMPUTED_VALUE"""),1.0) -> 1 | H32: =IFERROR(__xludf.DUMMYFUNCTION("""COMPUTED_VALUE"""),1.0) -> 1 | I32: =IFERROR(__xludf.DUMMYFUNCTION("""COMPUTED_VALUE"""),1.0) -> 1 | J32: =IFERROR(__xludf.DUMMYFUNCTION("""COMPUTED_VALUE"""),36.18) -> 36.18 | K32: =IFERROR(__xludf.DUMMYFUNCTION("""COMPUTED_VALUE"""),205.0) -> 205 | L32: =IFERROR(__xludf.DUMMYFUNCTION("""COMPUTED_VALUE"""),0.17648780487804877) -> 0.1764878 | M32: =IFERROR(__xludf.DUMMYFUNCTION("""COMPUTED_VALUE"""),9.0) -> 9 | N32: =IFERROR(__xludf.DUMMYFUNCTION("""COMPUTED_VALUE"""),0.0) -> 0 | O32: =IFERROR(__xludf.DUMMYFUNCTION("""COMPUTED_VALUE"""),"") | P32: =IFERROR(__xludf.DUMMYFUNCTION("""COMPUTED_VALUE"""),0.0) -> 0 | Q32: =IFERROR(__xludf.DUMMYFUNCTION("""COMPUTED_VALUE"""),1.0) -> 1 | R32: =IFERROR(__xludf.DUMMYFUNCTION("""COMPUTED_VALUE"""),0.0) -> 0 | S32: =IFERROR(__xludf.DUMMYFUNCTION("""COMPUTED_VALUE"""),1.0) -> 1 | T32: =IFERROR(__xludf.DUMMYFUNCTION("""COMPUTED_VALUE"""),1.0) -> 1 | U32: =IFERROR(__xludf.DUMMYFUNCTION("""COMPUTED_VALUE"""),1.0) -> 1 | V32: =IFERROR(__xludf.DUMMYFUNCTION("""COMPUTED_VALUE"""),0.0) -> 0 | W32: =IFERROR(__xludf.DUMMYFUNCTION("""COMPUTED_VALUE"""),1.0) -> 1 | X32: =IFERROR(__xludf.DUMMYFUNCTION("""COMPUTED_VALUE"""),0.0) -> 0 | Y32: =IFERROR(__xludf.DUMMYFUNCTION("""COMPUTED_VALUE"""),0.0) -> 0 | Z32: =IFERROR(__xludf.DUMMYFUNCTION("""COMPUTED_VALUE"""),0.0) -> 0 | AA32: =IFERROR(__xludf.DUMMYFUNCTION("""COMPUTED_VALUE"""),"") | AB32: =IFERROR(__xludf.DUMMYFUNCTION("""COMPUTED_VALUE"""),6.5) -> 6.5 | AC32: =IFERROR(__xludf.DUMMYFUNCTION("""COMPUTED_VALUE"""),89.13) -> 89.13 | AD32: =IFERROR(__xludf.DUMMYFUNCTION("""COMPUTED_VALUE"""),0.07292718501065859) -> 0.072927185 | AE32: =IFERROR(__xludf.DUMMYFUNCTION("""COMPUTED_VALUE"""),6.5) -> 6.5 | AF32: =IFERROR(__xludf.DUMMYFUNCTION("""COMPUTED_VALUE"""),205.0) -> 205 | AG32: =IFERROR(__xludf.DUMMYFUNCTION("""COMPUTED_VALUE"""),0.03170731707317073) -> 0.031707317 | AH32: =IFERROR(__xludf.DUMMYFUNCTION("""COMPUTED_VALUE"""),66.4) -> 66.4 | AI32: =IFERROR(__xludf.DUMMYFUNCTION("""COMPUTED_VALUE"""),205.0) -> 205 | AJ32: =IFERROR(__xludf.DUMMYFUNCTION("""COMPUTED_VALUE"""),0.32390243902439025) -> 0.32390244 | AK32: =IFERROR(__xludf.DUMMYFUNCTION("""COMPUTED_VALUE"""),79.4) -> 79.4 | AL32: =IFERROR(__xludf.DUMMYFUNCTION("""COMPUTED_VALUE"""),499.13) -> 499.13 | AM32: =IFERROR(__xludf.DUMMYFUNCTION("""COMPUTED_VALUE"""),0.15907679362090038) -> 0.15907679 | AN32: =IFERROR(__xludf.DUMMYFUNCTION("""COMPUTED_VALUE"""),0.0) -> 0 | AO32: =IFERROR(__xludf.DUMMYFUNCTION("""COMPUTED_VALUE"""),0.0) -> 0 | AP32: =IFERROR(__xludf.DUMMYFUNCTION("""COMPUTED_VALUE"""),"") | AQ32: =IFERROR(__xludf.DUMMYFUNCTION("""COMPUTED_VALUE"""),0.0) -> 0 | AR32: =IFERROR(__xludf.DUMMYFUNCTION("""COMPUTED_VALUE"""),0.0) -> 0 | AS32: =IFERROR(__xludf.DUMMYFUNCTION("""COMPUTED_VALUE"""),"") | AT32: =IFERROR(__xludf.DUMMYFUNCTION("""COMPUTED_VALUE"""),0.0) -> 0 | AU32: =IFERROR(__xludf.DUMMYFUNCTION("""COMPUTED_VALUE"""),0.0) -> 0 | AV32: =IFERROR(__xludf.DUMMYFUNCTION("""COMPUTED_VALUE"""),"") | AW32: =IFERROR(__xludf.DUMMYFUNCTION("""COMPUTED_VALUE"""),0.0) -> 0 | AX32: =IFERROR(__xludf.DUMMYFUNCTION("""COMPUTED_VALUE"""),0.0) -> 0 | AY32: =IFERROR(__xludf.DUMMYFUNCTION("""COMPUTED_VALUE"""),"") | AZ32: =IFERROR(__xludf.DUMMYFUNCTION("""COMPUTED_VALUE"""),0.0) -> 0 | BA32: =IFERROR(__xludf.DUMMYFUNCTION("""COMPUTED_VALUE"""),0.0) -> 0 | BB32: =IFERROR(__xludf.DUMMYFUNCTION("""COMPUTED_VALUE"""),"")
A33: =IFERROR(__xludf.DUMMYFUNCTION("""COMPUTED_VALUE"""),"63ced847c5c820531c2689ab") -> 63ced847c5c820531c2689ab | B33: =IFERROR(__xludf.DUMMYFUNCTION("""COMPUTED_VALUE"""),"COM plan + service GmbH") -> COM plan + service GmbH | C33: =IFERROR(__xludf.DUMMYFUNCTION("""COMPUTED_VALUE"""),"thomas.ullmann@al-enterprise.com, silke.fraedrich@al-enterprise.com, andreas.grossheimann@al-enterprise.com, samantha.hunt@al-enterprise.com, katrin.pfeiffer@al-enterprise.com, sibylle.klopfer@al-enterprise.com, igor.leko@al-enterprise.com") -> thomas.ullmann@al-enterprise.com, silke.fraedrich@al-enterprise.com, andreas.grossheimann@al-enterprise.com, samantha.hunt@al-enterprise.com, katrin.pfeiffer@al-enterprise.com, sibylle.klopfer@al-enterprise.com, igor.leko@al-enterprise.com | D33: =IFERROR(__xludf.DUMMYFUNCTION("""COMPUTED_VALUE"""),"germany") -> germany | E33: =IFERROR(__xludf.DUMMYFUNCTION("""COMPUTED_VALUE"""),"DE") -> DE | F33: =IFERROR(__xludf.DUMMYFUNCTION("""COMPUTED_VALUE"""),"yes") -> yes | G33: =IFERROR(__xludf.DUMMYFUNCTION("""COMPUTED_VALUE"""),1.0) -> 1 | H33: =IFERROR(__xludf.DUMMYFUNCTION("""COMPUTED_VALUE"""),1.0) -> 1 | I33: =IFERROR(__xludf.DUMMYFUNCTION("""COMPUTED_VALUE"""),1.0) -> 1 | J33: =IFERROR(__xludf.DUMMYFUNCTION("""COMPUTED_VALUE"""),1802.04) -> 1802.04 | K33: =IFERROR(__xludf.DUMMYFUNCTION("""COMPUTED_VALUE"""),4600.0) -> 4600 | L33: =IFERROR(__xludf.DUMMYFUNCTION("""COMPUTED_VALUE"""),0.3917478260869565) -> 0.39174783 | M33: =IFERROR(__xludf.DUMMYFUNCTION("""COMPUTED_VALUE"""),178.0) -> 178 | N33: =IFERROR(__xludf.DUMMYFUNCTION("""COMPUTED_VALUE"""),52.0) -> 52 | O33: =IFERROR(__xludf.DUMMYFUNCTION("""COMPUTED_VALUE"""),3.423076923076923) -> 3.4230769 | P33: =IFERROR(__xludf.DUMMYFUNCTION("""COMPUTED_VALUE"""),1.0) -> 1 | Q33: =IFERROR(__xludf.DUMMYFUNCTION("""COMPUTED_VALUE"""),1.0) -> 1 | R33: =IFERROR(__xludf.DUMMYFUNCTION("""COMPUTED_VALUE"""),1.0) -> 1 | S33: =IFERROR(__xludf.DUMMYFUNCTION("""COMPUTED_VALUE"""),1.0) -> 1 | T33: =IFERROR(__xludf.DUMMYFUNCTION("""COMPUTED_VALUE"""),1.0) -> 1 | U33: =IFERROR(__xludf.DUMMYFUNCTION("""COMPUTED_VALUE"""),1.0) -> 1 | V33: =IFERROR(__xludf.DUMMYFUNCTION("""COMPUTED_VALUE"""),0.0) -> 0 | W33: =IFERROR(__xludf.DUMMYFUNCTION("""COMPUTED_VALUE"""),1.0) -> 1 | X33: =IFERROR(__xludf.DUMMYFUNCTION("""COMPUTED_VALUE"""),0.0) -> 0 | Y33: =IFERROR(__xludf.DUMMYFUNCTION("""COMPUTED_VALUE"""),40.01) -> 40.01 | Z33: =IFERROR(__xludf.DUMMYFUNCTION("""COMPUTED_VALUE"""),0.0) -> 0 | AA33: =IFERROR(__xludf.DUMMYFUNCTION("""COMPUTED_VALUE"""),"") | AB33: =IFERROR(__xludf.DUMMYFUNCTION("""COMPUTED_VALUE"""),7.06) -> 7.06 | AC33: =IFERROR(__xludf.DUMMYFUNCTION("""COMPUTED_VALUE"""),2000.0) -> 2000 | AD33: =IFERROR(__xludf.DUMMYFUNCTION("""COMPUTED_VALUE"""),0.0035299999999999997) -> 0.00353 | AE33: =IFERROR(__xludf.DUMMYFUNCTION("""COMPUTED_VALUE"""),570.13) -> 570.13 | AF33: =IFERROR(__xludf.DUMMYFUNCTION("""COMPUTED_VALUE"""),3000.0) -> 3000 | AG33: =IFERROR(__xludf.DUMMYFUNCTION("""COMPUTED_VALUE"""),0.19004333333333334) -> 0.19004333 | AH33: =IFERROR(__xludf.DUMMYFUNCTION("""COMPUTED_VALUE"""),3865.78) -> 3865.78 | AI33: =IFERROR(__xludf.DUMMYFUNCTION("""COMPUTED_VALUE"""),3000.0) -> 3000 | AJ33: =IFERROR(__xludf.DUMMYFUNCTION("""COMPUTED_VALUE"""),1.2885933333333335) -> 1.2885933 | AK33: =IFERROR(__xludf.DUMMYFUNCTION("""COMPUTED_VALUE"""),4482.9800000000005) -> 4482.98 | AL33: =IFERROR(__xludf.DUMMYFUNCTION("""COMPUTED_VALUE"""),8000.0) -> 8000 | AM33: =IFERROR(__xludf.DUMMYFUNCTION("""COMPUTED_VALUE"""),0.5603725) -> 0.5603725 | AN33: =IFERROR(__xludf.DUMMYFUNCTION("""COMPUTED_VALUE"""),401.38) -> 401.38 | AO33: =IFERROR(__xludf.DUMMYFUNCTION("""COMPUTED_VALUE"""),0.0) -> 0 | AP33: =IFERROR(__xludf.DUMMYFUNCTION("""COMPUTED_VALUE"""),"") | AQ33: =IFERROR(__xludf.DUMMYFUNCTION("""COMPUTED_VALUE"""),7809.37) -> 7809.37 | AR33: =IFERROR(__xludf.DUMMYFUNCTION("""COMPUTED_VALUE"""),0.0) -> 0 | AS33: =IFERROR(__xludf.DUMMYFUNCTION("""COMPUTED_VALUE"""),"") | AT33: =IFERROR(__xludf.DUMMYFUNCTION("""COMPUTED_VALUE"""),134.85) -> 134.85 | AU33: =IFERROR(__xludf.DUMMYFUNCTION("""COMPUTED_VALUE"""),0.0) -> 0 | AV33: =IFERROR(__xludf.DUMMYFUNCTION("""COMPUTED_VALUE"""),"") | AW33: =IFERROR(__xludf.DUMMYFUNCTION("""COMPUTED_VALUE"""),3301.26) -> 3301.26 | AX33: =IFERROR(__xludf.DUMMYFUNCTION("""COMPUTED_VALUE"""),0.0) -> 0 | AY33: =IFERROR(__xludf.DUMMYFUNCTION("""COMPUTED_VALUE"""),"") | AZ33: =IFERROR(__xludf.DUMMYFUNCTION("""COMPUTED_VALUE"""),11646.86) -> 11646.86 | BA33: =IFERROR(__xludf.DUMMYFUNCTION("""COMPUTED_VALUE"""),0.0) -> 0 | BB33: =IFERROR(__xludf.DUMMYFUNCTION("""COMPUTED_VALUE"""),"")
A34: =IFERROR(__xludf.DUMMYFUNCTION("""COMPUTED_VALUE"""),"63fcbb7fa107c871cf56491d") -> 63fcbb7fa107c871cf56491d | B34: =IFERROR(__xludf.DUMMYFUNCTION("""COMPUTED_VALUE"""),"Comfica Soluciones Integrales SL") -> Comfica Soluciones Integrales SL | C34: =IFERROR(__xludf.DUMMYFUNCTION("""COMPUTED_VALUE"""),"mario.madrid-bustos@al-enterprise.com, astrid.savorani@al-enterprise.com, marcos.rodriguez@al-enterprise.com, borja.gonzalvez@al-enterprise.com") -> mario.madrid-bustos@al-enterprise.com, astrid.savorani@al-enterprise.com, marcos.rodriguez@al-enterprise.com, borja.gonzalvez@al-enterprise.com | D34: =IFERROR(__xludf.DUMMYFUNCTION("""COMPUTED_VALUE"""),"emea") -> emea | E34: =IFERROR(__xludf.DUMMYFUNCTION("""COMPUTED_VALUE"""),"ES") -> ES | F34: =IFERROR(__xludf.DUMMYFUNCTION("""COMPUTED_VALUE"""),"expert_200") -> expert_200 | G34: =IFERROR(__xludf.DUMMYFUNCTION("""COMPUTED_VALUE"""),1.0) -> 1 | H34: =IFERROR(__xludf.DUMMYFUNCTION("""COMPUTED_VALUE"""),1.0) -> 1 | I34: =IFERROR(__xludf.DUMMYFUNCTION("""COMPUTED_VALUE"""),1.0) -> 1 | J34: =IFERROR(__xludf.DUMMYFUNCTION("""COMPUTED_VALUE"""),15.84) -> 15.84 | K34: =IFERROR(__xludf.DUMMYFUNCTION("""COMPUTED_VALUE"""),500.0) -> 500 | L34: =IFERROR(__xludf.DUMMYFUNCTION("""COMPUTED_VALUE"""),0.03168) -> 0.03168 | M34: =IFERROR(__xludf.DUMMYFUNCTION("""COMPUTED_VALUE"""),7.0) -> 7 | N34: =IFERROR(__xludf.DUMMYFUNCTION("""COMPUTED_VALUE"""),52.0) -> 52 | O34: =IFERROR(__xludf.DUMMYFUNCTION("""COMPUTED_VALUE"""),0.1346153846153846) -> 0.13461538 | P34: =IFERROR(__xludf.DUMMYFUNCTION("""COMPUTED_VALUE"""),0.0) -> 0 | Q34: =IFERROR(__xludf.DUMMYFUNCTION("""COMPUTED_VALUE"""),1.0) -> 1 | R34: =IFERROR(__xludf.DUMMYFUNCTION("""COMPUTED_VALUE"""),0.0) -> 0 | S34: =IFERROR(__xludf.DUMMYFUNCTION("""COMPUTED_VALUE"""),1.0) -> 1 | T34: =IFERROR(__xludf.DUMMYFUNCTION("""COMPUTED_VALUE"""),1.0) -> 1 | U34: =IFERROR(__xludf.DUMMYFUNCTION("""COMPUTED_VALUE"""),1.0) -> 1 | V34: =IFERROR(__xludf.DUMMYFUNCTION("""COMPUTED_VALUE"""),0.0) -> 0 | W34: =IFERROR(__xludf.DUMMYFUNCTION("""COMPUTED_VALUE"""),1.0) -> 1 | X34: =IFERROR(__xludf.DUMMYFUNCTION("""COMPUTED_VALUE"""),0.0) -> 0 | Y34: =IFERROR(__xludf.DUMMYFUNCTION("""COMPUTED_VALUE"""),110.0) -> 110 | Z34: =IFERROR(__xludf.DUMMYFUNCTION("""COMPUTED_VALUE"""),0.0) -> 0 | AA34: =IFERROR(__xludf.DUMMYFUNCTION("""COMPUTED_VALUE"""),"") | AB34: =IFERROR(__xludf.DUMMYFUNCTION("""COMPUTED_VALUE"""),14.0) -> 14 | AC34: =IFERROR(__xludf.DUMMYFUNCTION("""COMPUTED_VALUE"""),215.52) -> 215.52 | AD34: =IFERROR(__xludf.DUMMYFUNCTION("""COMPUTED_VALUE"""),0.06495916852264291) -> 0.064959169 | AE34: =IFERROR(__xludf.DUMMYFUNCTION("""COMPUTED_VALUE"""),110.0) -> 110 | AF34: =IFERROR(__xludf.DUMMYFUNCTION("""COMPUTED_VALUE"""),215.52) -> 215.52 | AG34: =IFERROR(__xludf.DUMMYFUNCTION("""COMPUTED_VALUE"""),0.5103934669636229) -> 0.51039347 | AH34: =IFERROR(__xludf.DUMMYFUNCTION("""COMPUTED_VALUE"""),340.0) -> 340 | AI34: =IFERROR(__xludf.DUMMYFUNCTION("""COMPUTED_VALUE"""),215.52) -> 215.52 | AJ34: =IFERROR(__xludf.DUMMYFUNCTION("""COMPUTED_VALUE"""),1.5775798069784706) -> 1.5775798 | AK34: =IFERROR(__xludf.DUMMYFUNCTION("""COMPUTED_VALUE"""),574.0) -> 574 | AL34: =IFERROR(__xludf.DUMMYFUNCTION("""COMPUTED_VALUE"""),646.5600000000001) -> 646.56 | AM34: =IFERROR(__xludf.DUMMYFUNCTION("""COMPUTED_VALUE"""),0.8877753031427864) -> 0.8877753 | AN34: =IFERROR(__xludf.DUMMYFUNCTION("""COMPUTED_VALUE"""),630.0) -> 630 | AO34: =IFERROR(__xludf.DUMMYFUNCTION("""COMPUTED_VALUE"""),0.0) -> 0 | AP34: =IFERROR(__xludf.DUMMYFUNCTION("""COMPUTED_VALUE"""),"") | AQ34: =IFERROR(__xludf.DUMMYFUNCTION("""COMPUTED_VALUE"""),0.0) -> 0 | AR34: =IFERROR(__xludf.DUMMYFUNCTION("""COMPUTED_VALUE"""),0.0) -> 0 | AS34: =IFERROR(__xludf.DUMMYFUNCTION("""COMPUTED_VALUE"""),"") | AT34: =IFERROR(__xludf.DUMMYFUNCTION("""COMPUTED_VALUE"""),150.0) -> 150 | AU34: =IFERROR(__xludf.DUMMYFUNCTION("""COMPUTED_VALUE"""),0.0) -> 0 | AV34: =IFERROR(__xludf.DUMMYFUNCTION("""COMPUTED_VALUE"""),"") | AW34: =IFERROR(__xludf.DUMMYFUNCTION("""COMPUTED_VALUE"""),0.0) -> 0 | AX34: =IFERROR(__xludf.DUMMYFUNCTION("""COMPUTED_VALUE"""),0.0) -> 0 | AY34: =IFERROR(__xludf.DUMMYFUNCTION("""COMPUTED_VALUE"""),"") | AZ34: =IFERROR(__xludf.DUMMYFUNCTION("""COMPUTED_VALUE"""),780.0) -> 780 | BA34: =IFERROR(__xludf.DUMMYFUNCTION("""COMPUTED_VALUE"""),0.0) -> 0 | BB34: =IFERROR(__xludf.DUMMYFUNCTION("""COMPUTED_VALUE"""),"")
A35: =IFERROR(__xludf.DUMMYFUNCTION("""COMPUTED_VALUE"""),"63ced84dc5c820531c2696da") -> 63ced84dc5c820531c2696da | B35: =IFERROR(__xludf.DUMMYFUNCTION("""COMPUTED_VALUE"""),"Communications Consulting Inc.") -> Communications Consulting Inc. | C35: =IFERROR(__xludf.DUMMYFUNCTION("""COMPUTED_VALUE"""),"brendan.flaherty@al-enterprise.com, michael-j.francis@al-enterprise.com, jon.taylor@al-enterprise.com") -> brendan.flaherty@al-enterprise.com, michael-j.francis@al-enterprise.com, jon.taylor@al-enterprise.com | D35: =IFERROR(__xludf.DUMMYFUNCTION("""COMPUTED_VALUE"""),"americas") -> americas | E35: =IFERROR(__xludf.DUMMYFUNCTION("""COMPUTED_VALUE"""),"US") -> US | F35: =IFERROR(__xludf.DUMMYFUNCTION("""COMPUTED_VALUE"""),"expert_1000") -> expert_1000 | G35: =IFERROR(__xludf.DUMMYFUNCTION("""COMPUTED_VALUE"""),1.0) -> 1 | H35: =IFERROR(__xludf.DUMMYFUNCTION("""COMPUTED_VALUE"""),1.0) -> 1 | I35: =IFERROR(__xludf.DUMMYFUNCTION("""COMPUTED_VALUE"""),1.0) -> 1 | J35: =IFERROR(__xludf.DUMMYFUNCTION("""COMPUTED_VALUE"""),383.74) -> 383.74 | K35: =IFERROR(__xludf.DUMMYFUNCTION("""COMPUTED_VALUE"""),1379.99) -> 1379.99 | L35: =IFERROR(__xludf.DUMMYFUNCTION("""COMPUTED_VALUE"""),0.278074478800571) -> 0.27807448 | M35: =IFERROR(__xludf.DUMMYFUNCTION("""COMPUTED_VALUE"""),40.0) -> 40 | N35: =IFERROR(__xludf.DUMMYFUNCTION("""COMPUTED_VALUE"""),52.0) -> 52 | O35: =IFERROR(__xludf.DUMMYFUNCTION("""COMPUTED_VALUE"""),0.7692307692307693) -> 0.76923077 | P35: =IFERROR(__xludf.DUMMYFUNCTION("""COMPUTED_VALUE"""),1.0) -> 1 | Q35: =IFERROR(__xludf.DUMMYFUNCTION("""COMPUTED_VALUE"""),1.0) -> 1 | R35: =IFERROR(__xludf.DUMMYFUNCTION("""COMPUTED_VALUE"""),1.0) -> 1 | S35: =IFERROR(__xludf.DUMMYFUNCTION("""COMPUTED_VALUE"""),1.0) -> 1 | T35: =IFERROR(__xludf.DUMMYFUNCTION("""COMPUTED_VALUE"""),1.0) -> 1 | U35: =IFERROR(__xludf.DUMMYFUNCTION("""COMPUTED_VALUE"""),1.0) -> 1 | V35: =IFERROR(__xludf.DUMMYFUNCTION("""COMPUTED_VALUE"""),1.0) -> 1 | W35: =IFERROR(__xludf.DUMMYFUNCTION("""COMPUTED_VALUE"""),1.0) -> 1 | X35: =IFERROR(__xludf.DUMMYFUNCTION("""COMPUTED_VALUE"""),1.0) -> 1 | Y35: =IFERROR(__xludf.DUMMYFUNCTION("""COMPUTED_VALUE"""),21.7) -> 21.7 | Z35: =IFERROR(__xludf.DUMMYFUNCTION("""COMPUTED_VALUE"""),0.0) -> 0 | AA35: =IFERROR(__xludf.DUMMYFUNCTION("""COMPUTED_VALUE"""),"") | AB35: =IFERROR(__xludf.DUMMYFUNCTION("""COMPUTED_VALUE"""),256.74) -> 256.74 | AC35: =IFERROR(__xludf.DUMMYFUNCTION("""COMPUTED_VALUE"""),1679.07) -> 1679.07 | AD35: =IFERROR(__xludf.DUMMYFUNCTION("""COMPUTED_VALUE"""),0.15290607300469905) -> 0.15290607 | AE35: =IFERROR(__xludf.DUMMYFUNCTION("""COMPUTED_VALUE"""),330.68) -> 330.68 | AF35: =IFERROR(__xludf.DUMMYFUNCTION("""COMPUTED_VALUE"""),848.83) -> 848.83 | AG35: =IFERROR(__xludf.DUMMYFUNCTION("""COMPUTED_VALUE"""),0.38957152786777094) -> 0.38957153 | AH35: =IFERROR(__xludf.DUMMYFUNCTION("""COMPUTED_VALUE"""),18.11) -> 18.11 | AI35: =IFERROR(__xludf.DUMMYFUNCTION("""COMPUTED_VALUE"""),302.31) -> 302.31 | AJ35: =IFERROR(__xludf.DUMMYFUNCTION("""COMPUTED_VALUE"""),0.059905395124210246) -> 0.059905395 | AK35: =IFERROR(__xludf.DUMMYFUNCTION("""COMPUTED_VALUE"""),627.23) -> 627.23 | AL35: =IFERROR(__xludf.DUMMYFUNCTION("""COMPUTED_VALUE"""),2830.21) -> 2830.21 | AM35: =IFERROR(__xludf.DUMMYFUNCTION("""COMPUTED_VALUE"""),0.22161959713236828) -> 0.2216196 | AN35: =IFERROR(__xludf.DUMMYFUNCTION("""COMPUTED_VALUE"""),8.21) -> 8.21 | AO35: =IFERROR(__xludf.DUMMYFUNCTION("""COMPUTED_VALUE"""),0.0) -> 0 | AP35: =IFERROR(__xludf.DUMMYFUNCTION("""COMPUTED_VALUE"""),"") | AQ35: =IFERROR(__xludf.DUMMYFUNCTION("""COMPUTED_VALUE"""),0.0) -> 0 | AR35: =IFERROR(__xludf.DUMMYFUNCTION("""COMPUTED_VALUE"""),0.0) -> 0 | AS35: =IFERROR(__xludf.DUMMYFUNCTION("""COMPUTED_VALUE"""),"") | AT35: =IFERROR(__xludf.DUMMYFUNCTION("""COMPUTED_VALUE"""),0.0) -> 0 | AU35: =IFERROR(__xludf.DUMMYFUNCTION("""COMPUTED_VALUE"""),0.0) -> 0 | AV35: =IFERROR(__xludf.DUMMYFUNCTION("""COMPUTED_VALUE"""),"") | AW35: =IFERROR(__xludf.DUMMYFUNCTION("""COMPUTED_VALUE"""),0.0) -> 0 | AX35: =IFERROR(__xludf.DUMMYFUNCTION("""COMPUTED_VALUE"""),0.0) -> 0 | AY35: =IFERROR(__xludf.DUMMYFUNCTION("""COMPUTED_VALUE"""),"") | AZ35: =IFERROR(__xludf.DUMMYFUNCTION("""COMPUTED_VALUE"""),8.21) -> 8.21 | BA35: =IFERROR(__xludf.DUMMYFUNCTION("""COMPUTED_VALUE"""),0.0) -> 0 | BB35: =IFERROR(__xludf.DUMMYFUNCTION("""COMPUTED_VALUE"""),"")
A36: =IFERROR(__xludf.DUMMYFUNCTION("""COMPUTED_VALUE"""),"63ea6e9352ad6968805cea63") -> 63ea6e9352ad6968805cea63 | B36: =IFERROR(__xludf.DUMMYFUNCTION("""COMPUTED_VALUE"""),"Controlware GmbH") -> Controlware GmbH | C36: =IFERROR(__xludf.DUMMYFUNCTION("""COMPUTED_VALUE"""),"katrin.pfeiffer@al-enterprise.com, sibylle.klopfer@al-enterprise.com, igor.leko@al-enterprise.com, philipp.bode@al-enterprise.com") -> katrin.pfeiffer@al-enterprise.com, sibylle.klopfer@al-enterprise.com, igor.leko@al-enterprise.com, philipp.bode@al-enterprise.com | D36: =IFERROR(__xludf.DUMMYFUNCTION("""COMPUTED_VALUE"""),"germany") -> germany | E36: =IFERROR(__xludf.DUMMYFUNCTION("""COMPUTED_VALUE"""),"DE") -> DE | F36: =IFERROR(__xludf.DUMMYFUNCTION("""COMPUTED_VALUE"""),"yes") -> yes | G36: =IFERROR(__xludf.DUMMYFUNCTION("""COMPUTED_VALUE"""),1.0) -> 1 | H36: =IFERROR(__xludf.DUMMYFUNCTION("""COMPUTED_VALUE"""),1.0) -> 1 | I36: =IFERROR(__xludf.DUMMYFUNCTION("""COMPUTED_VALUE"""),1.0) -> 1 | J36: =IFERROR(__xludf.DUMMYFUNCTION("""COMPUTED_VALUE"""),2061.6) -> 2061.6 | K36: =IFERROR(__xludf.DUMMYFUNCTION("""COMPUTED_VALUE"""),4350.0) -> 4350 | L36: =IFERROR(__xludf.DUMMYFUNCTION("""COMPUTED_VALUE"""),0.4739310344827586) -> 0.47393103 | M36: =IFERROR(__xludf.DUMMYFUNCTION("""COMPUTED_VALUE"""),36.0) -> 36 | N36: =IFERROR(__xludf.DUMMYFUNCTION("""COMPUTED_VALUE"""),63.0) -> 63 | O36: =IFERROR(__xludf.DUMMYFUNCTION("""COMPUTED_VALUE"""),0.5714285714285714) -> 0.57142857 | P36: =IFERROR(__xludf.DUMMYFUNCTION("""COMPUTED_VALUE"""),0.0) -> 0 | Q36: =IFERROR(__xludf.DUMMYFUNCTION("""COMPUTED_VALUE"""),1.0) -> 1 | R36: =IFERROR(__xludf.DUMMYFUNCTION("""COMPUTED_VALUE"""),0.0) -> 0 | S36: =IFERROR(__xludf.DUMMYFUNCTION("""COMPUTED_VALUE"""),1.0) -> 1 | T36: =IFERROR(__xludf.DUMMYFUNCTION("""COMPUTED_VALUE"""),1.0) -> 1 | U36: =IFERROR(__xludf.DUMMYFUNCTION("""COMPUTED_VALUE"""),1.0) -> 1 | V36: =IFERROR(__xludf.DUMMYFUNCTION("""COMPUTED_VALUE"""),0.0) -> 0 | W36: =IFERROR(__xludf.DUMMYFUNCTION("""COMPUTED_VALUE"""),1.0) -> 1 | X36: =IFERROR(__xludf.DUMMYFUNCTION("""COMPUTED_VALUE"""),0.0) -> 0 | Y36: =IFERROR(__xludf.DUMMYFUNCTION("""COMPUTED_VALUE"""),13.6) -> 13.6 | Z36: =IFERROR(__xludf.DUMMYFUNCTION("""COMPUTED_VALUE"""),0.0) -> 0 | AA36: =IFERROR(__xludf.DUMMYFUNCTION("""COMPUTED_VALUE"""),"") | AB36: =IFERROR(__xludf.DUMMYFUNCTION("""COMPUTED_VALUE"""),50.0) -> 50 | AC36: =IFERROR(__xludf.DUMMYFUNCTION("""COMPUTED_VALUE"""),1705.88) -> 1705.88 | AD36: =IFERROR(__xludf.DUMMYFUNCTION("""COMPUTED_VALUE"""),0.0293103852557038) -> 0.029310385 | AE36: =IFERROR(__xludf.DUMMYFUNCTION("""COMPUTED_VALUE"""),700.0) -> 700 | AF36: =IFERROR(__xludf.DUMMYFUNCTION("""COMPUTED_VALUE"""),2558.82) -> 2558.82 | AG36: =IFERROR(__xludf.DUMMYFUNCTION("""COMPUTED_VALUE"""),0.27356359571990213) -> 0.2735636 | AH36: =IFERROR(__xludf.DUMMYFUNCTION("""COMPUTED_VALUE"""),541.5) -> 541.5 | AI36: =IFERROR(__xludf.DUMMYFUNCTION("""COMPUTED_VALUE"""),2558.82) -> 2558.82 | AJ36: =IFERROR(__xludf.DUMMYFUNCTION("""COMPUTED_VALUE"""),0.21162098154618142) -> 0.21162098 | AK36: =IFERROR(__xludf.DUMMYFUNCTION("""COMPUTED_VALUE"""),1305.1) -> 1305.1 | AL36: =IFERROR(__xludf.DUMMYFUNCTION("""COMPUTED_VALUE"""),6823.52) -> 6823.52 | AM36: =IFERROR(__xludf.DUMMYFUNCTION("""COMPUTED_VALUE"""),0.19126491898609513) -> 0.19126492 | AN36: =IFERROR(__xludf.DUMMYFUNCTION("""COMPUTED_VALUE"""),70.0) -> 70 | AO36: =IFERROR(__xludf.DUMMYFUNCTION("""COMPUTED_VALUE"""),0.0) -> 0 | AP36: =IFERROR(__xludf.DUMMYFUNCTION("""COMPUTED_VALUE"""),"") | AQ36: =IFERROR(__xludf.DUMMYFUNCTION("""COMPUTED_VALUE"""),0.0) -> 0 | AR36: =IFERROR(__xludf.DUMMYFUNCTION("""COMPUTED_VALUE"""),0.0) -> 0 | AS36: =IFERROR(__xludf.DUMMYFUNCTION("""COMPUTED_VALUE"""),"") | AT36: =IFERROR(__xludf.DUMMYFUNCTION("""COMPUTED_VALUE"""),0.0) -> 0 | AU36: =IFERROR(__xludf.DUMMYFUNCTION("""COMPUTED_VALUE"""),0.0) -> 0 | AV36: =IFERROR(__xludf.DUMMYFUNCTION("""COMPUTED_VALUE"""),"") | AW36: =IFERROR(__xludf.DUMMYFUNCTION("""COMPUTED_VALUE"""),75.0) -> 75 | AX36: =IFERROR(__xludf.DUMMYFUNCTION("""COMPUTED_VALUE"""),0.0) -> 0 | AY36: =IFERROR(__xludf.DUMMYFUNCTION("""COMPUTED_VALUE"""),"") | AZ36: =IFERROR(__xludf.DUMMYFUNCTION("""COMPUTED_VALUE"""),145.0) -> 145 | BA36: =IFERROR(__xludf.DUMMYFUNCTION("""COMPUTED_VALUE"""),0.0) -> 0 | BB36: =IFERROR(__xludf.DUMMYFUNCTION("""COMPUTED_VALUE"""),"")
A37: =IFERROR(__xludf.DUMMYFUNCTION("""COMPUTED_VALUE"""),"63ea6e9352ad6968805cea8d") -> 63ea6e9352ad6968805cea8d | B37: =IFERROR(__xludf.DUMMYFUNCTION("""COMPUTED_VALUE"""),"cosmotel IT GmbH") -> cosmotel IT GmbH | C37: =IFERROR(__xludf.DUMMYFUNCTION("""COMPUTED_VALUE"""),"ralf.kloeppels@al-enterprise.com, katrin.pfeiffer@al-enterprise.com, sibylle.klopfer@al-enterprise.com, igor.leko@al-enterprise.com") -> ralf.kloeppels@al-enterprise.com, katrin.pfeiffer@al-enterprise.com, sibylle.klopfer@al-enterprise.com, igor.leko@al-enterprise.com | D37: =IFERROR(__xludf.DUMMYFUNCTION("""COMPUTED_VALUE"""),"germany") -> germany | E37: =IFERROR(__xludf.DUMMYFUNCTION("""COMPUTED_VALUE"""),"DE") -> DE | F37: =IFERROR(__xludf.DUMMYFUNCTION("""COMPUTED_VALUE"""),"expert_1000") -> expert_1000 | G37: =IFERROR(__xludf.DUMMYFUNCTION("""COMPUTED_VALUE"""),0.0) -> 0 | H37: =IFERROR(__xludf.DUMMYFUNCTION("""COMPUTED_VALUE"""),1.0) -> 1 | I37: =IFERROR(__xludf.DUMMYFUNCTION("""COMPUTED_VALUE"""),0.0) -> 0 | J37: =IFERROR(__xludf.DUMMYFUNCTION("""COMPUTED_VALUE"""),321.97) -> 321.97 | K37: =IFERROR(__xludf.DUMMYFUNCTION("""COMPUTED_VALUE"""),1325.0) -> 1325 | L37: =IFERROR(__xludf.DUMMYFUNCTION("""COMPUTED_VALUE"""),0.24299622641509436) -> 0.24299623 | M37: =IFERROR(__xludf.DUMMYFUNCTION("""COMPUTED_VALUE"""),103.0) -> 103 | N37: =IFERROR(__xludf.DUMMYFUNCTION("""COMPUTED_VALUE"""),53.0) -> 53 | O37: =IFERROR(__xludf.DUMMYFUNCTION("""COMPUTED_VALUE"""),1.9433962264150944) -> 1.9433962 | P37: =IFERROR(__xludf.DUMMYFUNCTION("""COMPUTED_VALUE"""),1.0) -> 1 | Q37: =IFERROR(__xludf.DUMMYFUNCTION("""COMPUTED_VALUE"""),1.0) -> 1 | R37: =IFERROR(__xludf.DUMMYFUNCTION("""COMPUTED_VALUE"""),1.0) -> 1 | S37: =IFERROR(__xludf.DUMMYFUNCTION("""COMPUTED_VALUE"""),1.0) -> 1 | T37: =IFERROR(__xludf.DUMMYFUNCTION("""COMPUTED_VALUE"""),1.0) -> 1 | U37: =IFERROR(__xludf.DUMMYFUNCTION("""COMPUTED_VALUE"""),1.0) -> 1 | V37: =IFERROR(__xludf.DUMMYFUNCTION("""COMPUTED_VALUE"""),1.0) -> 1 | W37: =IFERROR(__xludf.DUMMYFUNCTION("""COMPUTED_VALUE"""),1.0) -> 1 | X37: =IFERROR(__xludf.DUMMYFUNCTION("""COMPUTED_VALUE"""),1.0) -> 1 | Y37: =IFERROR(__xludf.DUMMYFUNCTION("""COMPUTED_VALUE"""),0.0) -> 0 | Z37: =IFERROR(__xludf.DUMMYFUNCTION("""COMPUTED_VALUE"""),0.0) -> 0 | AA37: =IFERROR(__xludf.DUMMYFUNCTION("""COMPUTED_VALUE"""),"") | AB37: =IFERROR(__xludf.DUMMYFUNCTION("""COMPUTED_VALUE"""),3.03) -> 3.03 | AC37: =IFERROR(__xludf.DUMMYFUNCTION("""COMPUTED_VALUE"""),519.61) -> 519.61 | AD37: =IFERROR(__xludf.DUMMYFUNCTION("""COMPUTED_VALUE"""),0.005831296549335078) -> 0.0058312965 | AE37: =IFERROR(__xludf.DUMMYFUNCTION("""COMPUTED_VALUE"""),218.14) -> 218.14 | AF37: =IFERROR(__xludf.DUMMYFUNCTION("""COMPUTED_VALUE"""),803.92) -> 803.92 | AG37: =IFERROR(__xludf.DUMMYFUNCTION("""COMPUTED_VALUE"""),0.27134540750323416) -> 0.27134541 | AH37: =IFERROR(__xludf.DUMMYFUNCTION("""COMPUTED_VALUE"""),388.0) -> 388 | AI37: =IFERROR(__xludf.DUMMYFUNCTION("""COMPUTED_VALUE"""),754.9) -> 754.9 | AJ37: =IFERROR(__xludf.DUMMYFUNCTION("""COMPUTED_VALUE"""),0.5139753609749635) -> 0.51397536 | AK37: =IFERROR(__xludf.DUMMYFUNCTION("""COMPUTED_VALUE"""),609.17) -> 609.17 | AL37: =IFERROR(__xludf.DUMMYFUNCTION("""COMPUTED_VALUE"""),2078.43) -> 2078.43 | AM37: =IFERROR(__xludf.DUMMYFUNCTION("""COMPUTED_VALUE"""),0.29309141996603205) -> 0.29309142 | AN37: =IFERROR(__xludf.DUMMYFUNCTION("""COMPUTED_VALUE"""),30.0) -> 30 | AO37: =IFERROR(__xludf.DUMMYFUNCTION("""COMPUTED_VALUE"""),0.0) -> 0 | AP37: =IFERROR(__xludf.DUMMYFUNCTION("""COMPUTED_VALUE"""),"") | AQ37: =IFERROR(__xludf.DUMMYFUNCTION("""COMPUTED_VALUE"""),566.2) -> 566.2 | AR37: =IFERROR(__xludf.DUMMYFUNCTION("""COMPUTED_VALUE"""),0.0) -> 0 | AS37: =IFERROR(__xludf.DUMMYFUNCTION("""COMPUTED_VALUE"""),"") | AT37: =IFERROR(__xludf.DUMMYFUNCTION("""COMPUTED_VALUE"""),20.0) -> 20 | AU37: =IFERROR(__xludf.DUMMYFUNCTION("""COMPUTED_VALUE"""),0.0) -> 0 | AV37: =IFERROR(__xludf.DUMMYFUNCTION("""COMPUTED_VALUE"""),"") | AW37: =IFERROR(__xludf.DUMMYFUNCTION("""COMPUTED_VALUE"""),0.0) -> 0 | AX37: =IFERROR(__xludf.DUMMYFUNCTION("""COMPUTED_VALUE"""),0.0) -> 0 | AY37: =IFERROR(__xludf.DUMMYFUNCTION("""COMPUTED_VALUE"""),"") | AZ37: =IFERROR(__xludf.DUMMYFUNCTION("""COMPUTED_VALUE"""),616.2) -> 616.2 | BA37: =IFERROR(__xludf.DUMMYFUNCTION("""COMPUTED_VALUE"""),0.0) -> 0 | BB37: =IFERROR(__xludf.DUMMYFUNCTION("""COMPUTED_VALUE"""),"")
A38: =IFERROR(__xludf.DUMMYFUNCTION("""COMPUTED_VALUE"""),"63ced841c5c820531c267eb6") -> 63ced841c5c820531c267eb6 | B38: =IFERROR(__xludf.DUMMYFUNCTION("""COMPUTED_VALUE"""),"COVERGINT Comercio e Servicos de Tecnologia Ltda") -> COVERGINT Comercio e Servicos de Tecnologia Ltda | C38: =IFERROR(__xludf.DUMMYFUNCTION("""COMPUTED_VALUE"""),"vinicius.costa@al-enterprise.com") -> vinicius.costa@al-enterprise.com | D38: =IFERROR(__xludf.DUMMYFUNCTION("""COMPUTED_VALUE"""),"americas") -> americas | E38: =IFERROR(__xludf.DUMMYFUNCTION("""COMPUTED_VALUE"""),"BR") -> BR | F38: =IFERROR(__xludf.DUMMYFUNCTION("""COMPUTED_VALUE"""),"expert_1000") -> expert_1000 | G38: =IFERROR(__xludf.DUMMYFUNCTION("""COMPUTED_VALUE"""),0.0) -> 0 | H38: =IFERROR(__xludf.DUMMYFUNCTION("""COMPUTED_VALUE"""),1.0) -> 1 | I38: =IFERROR(__xludf.DUMMYFUNCTION("""COMPUTED_VALUE"""),0.0) -> 0 | J38: =IFERROR(__xludf.DUMMYFUNCTION("""COMPUTED_VALUE"""),9.87) -> 9.87 | K38: =IFERROR(__xludf.DUMMYFUNCTION("""COMPUTED_VALUE"""),1519.99) -> 1519.99 | L38: =IFERROR(__xludf.DUMMYFUNCTION("""COMPUTED_VALUE"""),0.006493463772787978) -> 0.0064934638 | M38: =IFERROR(__xludf.DUMMYFUNCTION("""COMPUTED_VALUE"""),13.0) -> 13 | N38: =IFERROR(__xludf.DUMMYFUNCTION("""COMPUTED_VALUE"""),52.0) -> 52 | O38: =IFERROR(__xludf.DUMMYFUNCTION("""COMPUTED_VALUE"""),0.25) -> 0.25 | P38: =IFERROR(__xludf.DUMMYFUNCTION("""COMPUTED_VALUE"""),0.0) -> 0 | Q38: =IFERROR(__xludf.DUMMYFUNCTION("""COMPUTED_VALUE"""),1.0) -> 1 | R38: =IFERROR(__xludf.DUMMYFUNCTION("""COMPUTED_VALUE"""),0.0) -> 0 | S38: =IFERROR(__xludf.DUMMYFUNCTION("""COMPUTED_VALUE"""),1.0) -> 1 | T38: =IFERROR(__xludf.DUMMYFUNCTION("""COMPUTED_VALUE"""),1.0) -> 1 | U38: =IFERROR(__xludf.DUMMYFUNCTION("""COMPUTED_VALUE"""),1.0) -> 1 | V38: =IFERROR(__xludf.DUMMYFUNCTION("""COMPUTED_VALUE"""),0.0) -> 0 | W38: =IFERROR(__xludf.DUMMYFUNCTION("""COMPUTED_VALUE"""),1.0) -> 1 | X38: =IFERROR(__xludf.DUMMYFUNCTION("""COMPUTED_VALUE"""),0.0) -> 0 | Y38: =IFERROR(__xludf.DUMMYFUNCTION("""COMPUTED_VALUE"""),1893.99) -> 1893.99 | Z38: =IFERROR(__xludf.DUMMYFUNCTION("""COMPUTED_VALUE"""),0.0) -> 0 | AA38: =IFERROR(__xludf.DUMMYFUNCTION("""COMPUTED_VALUE"""),"") | AB38: =IFERROR(__xludf.DUMMYFUNCTION("""COMPUTED_VALUE"""),168.0) -> 168 | AC38: =IFERROR(__xludf.DUMMYFUNCTION("""COMPUTED_VALUE"""),899.98) -> 899.98 | AD38: =IFERROR(__xludf.DUMMYFUNCTION("""COMPUTED_VALUE"""),0.18667081490699794) -> 0.18667081 | AE38: =IFERROR(__xludf.DUMMYFUNCTION("""COMPUTED_VALUE"""),460.0) -> 460 | AF38: =IFERROR(__xludf.DUMMYFUNCTION("""COMPUTED_VALUE"""),1633.33) -> 1633.33 | AG38: =IFERROR(__xludf.DUMMYFUNCTION("""COMPUTED_VALUE"""),0.28163322782291395) -> 0.28163323 | AH38: =IFERROR(__xludf.DUMMYFUNCTION("""COMPUTED_VALUE"""),1965.99) -> 1965.99 | AI38: =IFERROR(__xludf.DUMMYFUNCTION("""COMPUTED_VALUE"""),1633.33) -> 1633.33 | AJ38: =IFERROR(__xludf.DUMMYFUNCTION("""COMPUTED_VALUE"""),1.2036698034077622) -> 1.2036698 | AK38: =IFERROR(__xludf.DUMMYFUNCTION("""COMPUTED_VALUE"""),4487.98) -> 4487.98 | AL38: =IFERROR(__xludf.DUMMYFUNCTION("""COMPUTED_VALUE"""),4166.639999999999) -> 4166.64 | AM38: =IFERROR(__xludf.DUMMYFUNCTION("""COMPUTED_VALUE"""),1.077122093581399) -> 1.0771221 | AN38: =IFERROR(__xludf.DUMMYFUNCTION("""COMPUTED_VALUE"""),0.0) -> 0 | AO38: =IFERROR(__xludf.DUMMYFUNCTION("""COMPUTED_VALUE"""),0.0) -> 0 | AP38: =IFERROR(__xludf.DUMMYFUNCTION("""COMPUTED_VALUE"""),"") | AQ38: =IFERROR(__xludf.DUMMYFUNCTION("""COMPUTED_VALUE"""),0.0) -> 0 | AR38: =IFERROR(__xludf.DUMMYFUNCTION("""COMPUTED_VALUE"""),0.0) -> 0 | AS38: =IFERROR(__xludf.DUMMYFUNCTION("""COMPUTED_VALUE"""),"") | AT38: =IFERROR(__xludf.DUMMYFUNCTION("""COMPUTED_VALUE"""),0.0) -> 0 | AU38: =IFERROR(__xludf.DUMMYFUNCTION("""COMPUTED_VALUE"""),0.0) -> 0 | AV38: =IFERROR(__xludf.DUMMYFUNCTION("""COMPUTED_VALUE"""),"") | AW38: =IFERROR(__xludf.DUMMYFUNCTION("""COMPUTED_VALUE"""),0.0) -> 0 | AX38: =IFERROR(__xludf.DUMMYFUNCTION("""COMPUTED_VALUE"""),0.0) -> 0 | AY38: =IFERROR(__xludf.DUMMYFUNCTION("""COMPUTED_VALUE"""),"") | AZ38: =IFERROR(__xludf.DUMMYFUNCTION("""COMPUTED_VALUE"""),0.0) -> 0 | BA38: =IFERROR(__xludf.DUMMYFUNCTION("""COMPUTED_VALUE"""),0.0) -> 0 | BB38: =IFERROR(__xludf.DUMMYFUNCTION("""COMPUTED_VALUE"""),"")
A39: =IFERROR(__xludf.DUMMYFUNCTION("""COMPUTED_VALUE"""),"63ced840c5c820531c267d30") -> 63ced840c5c820531c267d30 | B39: =IFERROR(__xludf.DUMMYFUNCTION("""COMPUTED_VALUE"""),"Crystal Communications, Inc.") -> Crystal Communications, Inc. | C39: =IFERROR(__xludf.DUMMYFUNCTION("""COMPUTED_VALUE"""),"michael-j.francis@al-enterprise.com, luigy.estevanell@al-enterprise.com, steve.aliberti@al-enterprise.com, robert.stitz@al-enterprise.com") -> michael-j.francis@al-enterprise.com, luigy.estevanell@al-enterprise.com, steve.aliberti@al-enterprise.com, robert.stitz@al-enterprise.com | D39: =IFERROR(__xludf.DUMMYFUNCTION("""COMPUTED_VALUE"""),"americas") -> americas | E39: =IFERROR(__xludf.DUMMYFUNCTION("""COMPUTED_VALUE"""),"US") -> US | F39: =IFERROR(__xludf.DUMMYFUNCTION("""COMPUTED_VALUE"""),"expert_200") -> expert_200 | G39: =IFERROR(__xludf.DUMMYFUNCTION("""COMPUTED_VALUE"""),1.0) -> 1 | H39: =IFERROR(__xludf.DUMMYFUNCTION("""COMPUTED_VALUE"""),1.0) -> 1 | I39: =IFERROR(__xludf.DUMMYFUNCTION("""COMPUTED_VALUE"""),1.0) -> 1 | J39: =IFERROR(__xludf.DUMMYFUNCTION("""COMPUTED_VALUE"""),373.86) -> 373.86 | K39: =IFERROR(__xludf.DUMMYFUNCTION("""COMPUTED_VALUE"""),1497.29) -> 1497.29 | L39: =IFERROR(__xludf.DUMMYFUNCTION("""COMPUTED_VALUE"""),0.24969110860287588) -> 0.24969111 | M39: =IFERROR(__xludf.DUMMYFUNCTION("""COMPUTED_VALUE"""),11.0) -> 11 | N39: =IFERROR(__xludf.DUMMYFUNCTION("""COMPUTED_VALUE"""),52.0) -> 52 | O39: =IFERROR(__xludf.DUMMYFUNCTION("""COMPUTED_VALUE"""),0.21153846153846154) -> 0.21153846 | P39: =IFERROR(__xludf.DUMMYFUNCTION("""COMPUTED_VALUE"""),0.0) -> 0 | Q39: =IFERROR(__xludf.DUMMYFUNCTION("""COMPUTED_VALUE"""),1.0) -> 1 | R39: =IFERROR(__xludf.DUMMYFUNCTION("""COMPUTED_VALUE"""),0.0) -> 0 | S39: =IFERROR(__xludf.DUMMYFUNCTION("""COMPUTED_VALUE"""),0.0) -> 0 | T39: =IFERROR(__xludf.DUMMYFUNCTION("""COMPUTED_VALUE"""),1.0) -> 1 | U39: =IFERROR(__xludf.DUMMYFUNCTION("""COMPUTED_VALUE"""),0.0) -> 0 | V39: =IFERROR(__xludf.DUMMYFUNCTION("""COMPUTED_VALUE"""),0.0) -> 0 | W39: =IFERROR(__xludf.DUMMYFUNCTION("""COMPUTED_VALUE"""),1.0) -> 1 | X39: =IFERROR(__xludf.DUMMYFUNCTION("""COMPUTED_VALUE"""),0.0) -> 0 | Y39: =IFERROR(__xludf.DUMMYFUNCTION("""COMPUTED_VALUE"""),33.12) -> 33.12 | Z39: =IFERROR(__xludf.DUMMYFUNCTION("""COMPUTED_VALUE"""),0.0) -> 0 | AA39: =IFERROR(__xludf.DUMMYFUNCTION("""COMPUTED_VALUE"""),"") | AB39: =IFERROR(__xludf.DUMMYFUNCTION("""COMPUTED_VALUE"""),8.15) -> 8.15 | AC39: =IFERROR(__xludf.DUMMYFUNCTION("""COMPUTED_VALUE"""),1008.16) -> 1008.16 | AD39: =IFERROR(__xludf.DUMMYFUNCTION("""COMPUTED_VALUE"""),0.008084034280272974) -> 0.0080840343 | AE39: =IFERROR(__xludf.DUMMYFUNCTION("""COMPUTED_VALUE"""),2.83) -> 2.83 | AF39: =IFERROR(__xludf.DUMMYFUNCTION("""COMPUTED_VALUE"""),1521.82) -> 1521.82 | AG39: =IFERROR(__xludf.DUMMYFUNCTION("""COMPUTED_VALUE"""),0.0018596154604355313) -> 0.0018596155 | AH39: =IFERROR(__xludf.DUMMYFUNCTION("""COMPUTED_VALUE"""),104.26) -> 104.26 | AI39: =IFERROR(__xludf.DUMMYFUNCTION("""COMPUTED_VALUE"""),1452.82) -> 1452.82 | AJ39: =IFERROR(__xludf.DUMMYFUNCTION("""COMPUTED_VALUE"""),0.07176387990253438) -> 0.07176388 | AK39: =IFERROR(__xludf.DUMMYFUNCTION("""COMPUTED_VALUE"""),148.36) -> 148.36 | AL39: =IFERROR(__xludf.DUMMYFUNCTION("""COMPUTED_VALUE"""),3982.8) -> 3982.8 | AM39: =IFERROR(__xludf.DUMMYFUNCTION("""COMPUTED_VALUE"""),0.03725017575574972) -> 0.037250176 | AN39: =IFERROR(__xludf.DUMMYFUNCTION("""COMPUTED_VALUE"""),41.81) -> 41.81 | AO39: =IFERROR(__xludf.DUMMYFUNCTION("""COMPUTED_VALUE"""),0.0) -> 0 | AP39: =IFERROR(__xludf.DUMMYFUNCTION("""COMPUTED_VALUE"""),"") | AQ39: =IFERROR(__xludf.DUMMYFUNCTION("""COMPUTED_VALUE"""),0.0) -> 0 | AR39: =IFERROR(__xludf.DUMMYFUNCTION("""COMPUTED_VALUE"""),0.0) -> 0 | AS39: =IFERROR(__xludf.DUMMYFUNCTION("""COMPUTED_VALUE"""),"") | AT39: =IFERROR(__xludf.DUMMYFUNCTION("""COMPUTED_VALUE"""),0.0) -> 0 | AU39: =IFERROR(__xludf.DUMMYFUNCTION("""COMPUTED_VALUE"""),0.0) -> 0 | AV39: =IFERROR(__xludf.DUMMYFUNCTION("""COMPUTED_VALUE"""),"") | AW39: =IFERROR(__xludf.DUMMYFUNCTION("""COMPUTED_VALUE"""),0.0) -> 0 | AX39: =IFERROR(__xludf.DUMMYFUNCTION("""COMPUTED_VALUE"""),0.0) -> 0 | AY39: =IFERROR(__xludf.DUMMYFUNCTION("""COMPUTED_VALUE"""),"") | AZ39: =IFERROR(__xludf.DUMMYFUNCTION("""COMPUTED_VALUE"""),41.81) -> 41.81 | BA39: =IFERROR(__xludf.DUMMYFUNCTION("""COMPUTED_VALUE"""),0.0) -> 0 | BB39: =IFERROR(__xludf.DUMMYFUNCTION("""COMPUTED_VALUE"""),"")
A40: =IFERROR(__xludf.DUMMYFUNCTION("""COMPUTED_VALUE"""),"63fcbb7ca107c871cf564511") -> 63fcbb7ca107c871cf564511 | B40: =IFERROR(__xludf.DUMMYFUNCTION("""COMPUTED_VALUE"""),"Cyclo X Solucoes em TI Ltda") -> Cyclo X Solucoes em TI Ltda | C40: =IFERROR(__xludf.DUMMYFUNCTION("""COMPUTED_VALUE"""),"gabriel.pires@al-enterprise.com") -> gabriel.pires@al-enterprise.com | D40: =IFERROR(__xludf.DUMMYFUNCTION("""COMPUTED_VALUE"""),"americas") -> americas | E40: =IFERROR(__xludf.DUMMYFUNCTION("""COMPUTED_VALUE"""),"BR") -> BR | F40: =IFERROR(__xludf.DUMMYFUNCTION("""COMPUTED_VALUE"""),"expert_1000") -> expert_1000 | G40: =IFERROR(__xludf.DUMMYFUNCTION("""COMPUTED_VALUE"""),1.0) -> 1 | H40: =IFERROR(__xludf.DUMMYFUNCTION("""COMPUTED_VALUE"""),1.0) -> 1 | I40: =IFERROR(__xludf.DUMMYFUNCTION("""COMPUTED_VALUE"""),1.0) -> 1 | J40: =IFERROR(__xludf.DUMMYFUNCTION("""COMPUTED_VALUE"""),2908.71) -> 2908.71 | K40: =IFERROR(__xludf.DUMMYFUNCTION("""COMPUTED_VALUE"""),0.0) -> 0 | L40: =IFERROR(__xludf.DUMMYFUNCTION("""COMPUTED_VALUE"""),"") | M40: =IFERROR(__xludf.DUMMYFUNCTION("""COMPUTED_VALUE"""),13.0) -> 13 | N40: =IFERROR(__xludf.DUMMYFUNCTION("""COMPUTED_VALUE"""),64.0) -> 64 | O40: =IFERROR(__xludf.DUMMYFUNCTION("""COMPUTED_VALUE"""),0.203125) -> 0.203125 | P40: =IFERROR(__xludf.DUMMYFUNCTION("""COMPUTED_VALUE"""),0.0) -> 0 | Q40: =IFERROR(__xludf.DUMMYFUNCTION("""COMPUTED_VALUE"""),1.0) -> 1 | R40: =IFERROR(__xludf.DUMMYFUNCTION("""COMPUTED_VALUE"""),0.0) -> 0 | S40: =IFERROR(__xludf.DUMMYFUNCTION("""COMPUTED_VALUE"""),0.0) -> 0 | T40: =IFERROR(__xludf.DUMMYFUNCTION("""COMPUTED_VALUE"""),1.0) -> 1 | U40: =IFERROR(__xludf.DUMMYFUNCTION("""COMPUTED_VALUE"""),0.0) -> 0 | V40: =IFERROR(__xludf.DUMMYFUNCTION("""COMPUTED_VALUE"""),1.0) -> 1 | W40: =IFERROR(__xludf.DUMMYFUNCTION("""COMPUTED_VALUE"""),1.0) -> 1 | X40: =IFERROR(__xludf.DUMMYFUNCTION("""COMPUTED_VALUE"""),1.0) -> 1 | Y40: =IFERROR(__xludf.DUMMYFUNCTION("""COMPUTED_VALUE"""),50.0) -> 50 | Z40: =IFERROR(__xludf.DUMMYFUNCTION("""COMPUTED_VALUE"""),0.0) -> 0 | AA40: =IFERROR(__xludf.DUMMYFUNCTION("""COMPUTED_VALUE"""),"") | AB40: =IFERROR(__xludf.DUMMYFUNCTION("""COMPUTED_VALUE"""),104.99) -> 104.99 | AC40: =IFERROR(__xludf.DUMMYFUNCTION("""COMPUTED_VALUE"""),0.0) -> 0 | AD40: =IFERROR(__xludf.DUMMYFUNCTION("""COMPUTED_VALUE"""),"") | AE40: =IFERROR(__xludf.DUMMYFUNCTION("""COMPUTED_VALUE"""),2562.98) -> 2562.98 | AF40: =IFERROR(__xludf.DUMMYFUNCTION("""COMPUTED_VALUE"""),0.0) -> 0 | AG40: =IFERROR(__xludf.DUMMYFUNCTION("""COMPUTED_VALUE"""),"") | AH40: =IFERROR(__xludf.DUMMYFUNCTION("""COMPUTED_VALUE"""),4760.96) -> 4760.96 | AI40: =IFERROR(__xludf.DUMMYFUNCTION("""COMPUTED_VALUE"""),0.0) -> 0 | AJ40: =IFERROR(__xludf.DUMMYFUNCTION("""COMPUTED_VALUE"""),"") | AK40: =IFERROR(__xludf.DUMMYFUNCTION("""COMPUTED_VALUE"""),7478.93) -> 7478.93 | AL40: =IFERROR(__xludf.DUMMYFUNCTION("""COMPUTED_VALUE"""),0.0) -> 0 | AM40: =IFERROR(__xludf.DUMMYFUNCTION("""COMPUTED_VALUE"""),"") | AN40: =IFERROR(__xludf.DUMMYFUNCTION("""COMPUTED_VALUE"""),289.99) -> 289.99 | AO40: =IFERROR(__xludf.DUMMYFUNCTION("""COMPUTED_VALUE"""),0.0) -> 0 | AP40: =IFERROR(__xludf.DUMMYFUNCTION("""COMPUTED_VALUE"""),"") | AQ40: =IFERROR(__xludf.DUMMYFUNCTION("""COMPUTED_VALUE"""),0.0) -> 0 | AR40: =IFERROR(__xludf.DUMMYFUNCTION("""COMPUTED_VALUE"""),0.0) -> 0 | AS40: =IFERROR(__xludf.DUMMYFUNCTION("""COMPUTED_VALUE"""),"") | AT40: =IFERROR(__xludf.DUMMYFUNCTION("""COMPUTED_VALUE"""),0.0) -> 0 | AU40: =IFERROR(__xludf.DUMMYFUNCTION("""COMPUTED_VALUE"""),0.0) -> 0 | AV40: =IFERROR(__xludf.DUMMYFUNCTION("""COMPUTED_VALUE"""),"") | AW40: =IFERROR(__xludf.DUMMYFUNCTION("""COMPUTED_VALUE"""),0.0) -> 0 | AX40: =IFERROR(__xludf.DUMMYFUNCTION("""COMPUTED_VALUE"""),0.0) -> 0 | AY40: =IFERROR(__xludf.DUMMYFUNCTION("""COMPUTED_VALUE"""),"") | AZ40: =IFERROR(__xludf.DUMMYFUNCTION("""COMPUTED_VALUE"""),289.99) -> 289.99 | BA40: =IFERROR(__xludf.DUMMYFUNCTION("""COMPUTED_VALUE"""),0.0) -> 0 | BB40: =IFERROR(__xludf.DUMMYFUNCTION("""COMPUTED_VALUE"""),"")
A41: =IFERROR(__xludf.DUMMYFUNCTION("""COMPUTED_VALUE"""),"63ced849c5c820531c268ea6") -> 63ced849c5c820531c268ea6 | B41: =IFERROR(__xludf.DUMMYFUNCTION("""COMPUTED_VALUE"""),"DACAS Colombia") -> DACAS Colombia | C41: =IFERROR(__xludf.DUMMYFUNCTION("""COMPUTED_VALUE"""),"philippe.girard@al-enterprise.com, rui.silva@al-enterprise.com, carolina.rodriguez@al-enterprise.com") -> philippe.girard@al-enterprise.com, rui.silva@al-enterprise.com, carolina.rodriguez@al-enterprise.com | D41: =IFERROR(__xludf.DUMMYFUNCTION("""COMPUTED_VALUE"""),"americas") -> americas | E41: =IFERROR(__xludf.DUMMYFUNCTION("""COMPUTED_VALUE"""),"CO") -> CO | F41: =IFERROR(__xludf.DUMMYFUNCTION("""COMPUTED_VALUE"""),"distributor") -> distributor | G41: =IFERROR(__xludf.DUMMYFUNCTION("""COMPUTED_VALUE"""),0.0) -> 0 | H41: =IFERROR(__xludf.DUMMYFUNCTION("""COMPUTED_VALUE"""),1.0) -> 1 | I41: =IFERROR(__xludf.DUMMYFUNCTION("""COMPUTED_VALUE"""),0.0) -> 0 | J41: =IFERROR(__xludf.DUMMYFUNCTION("""COMPUTED_VALUE"""),132.47) -> 132.47 | K41: =IFERROR(__xludf.DUMMYFUNCTION("""COMPUTED_VALUE"""),430.0) -> 430 | L41: =IFERROR(__xludf.DUMMYFUNCTION("""COMPUTED_VALUE"""),0.3080697674418605) -> 0.30806977 | M41: =IFERROR(__xludf.DUMMYFUNCTION("""COMPUTED_VALUE"""),13.0) -> 13 | N41: =IFERROR(__xludf.DUMMYFUNCTION("""COMPUTED_VALUE"""),60.0) -> 60 | O41: =IFERROR(__xludf.DUMMYFUNCTION("""COMPUTED_VALUE"""),0.21666666666666667) -> 0.21666667 | P41: =IFERROR(__xludf.DUMMYFUNCTION("""COMPUTED_VALUE"""),0.0) -> 0 | Q41: =IFERROR(__xludf.DUMMYFUNCTION("""COMPUTED_VALUE"""),1.0) -> 1 | R41: =IFERROR(__xludf.DUMMYFUNCTION("""COMPUTED_VALUE"""),0.0) -> 0 | S41: =IFERROR(__xludf.DUMMYFUNCTION("""COMPUTED_VALUE"""),1.0) -> 1 | T41: =IFERROR(__xludf.DUMMYFUNCTION("""COMPUTED_VALUE"""),1.0) -> 1 | U41: =IFERROR(__xludf.DUMMYFUNCTION("""COMPUTED_VALUE"""),1.0) -> 1 | V41: =IFERROR(__xludf.DUMMYFUNCTION("""COMPUTED_VALUE"""),0.0) -> 0 | W41: =IFERROR(__xludf.DUMMYFUNCTION("""COMPUTED_VALUE"""),1.0) -> 1 | X41: =IFERROR(__xludf.DUMMYFUNCTION("""COMPUTED_VALUE"""),0.0) -> 0 | Y41: =IFERROR(__xludf.DUMMYFUNCTION("""COMPUTED_VALUE"""),7.0) -> 7 | Z41: =IFERROR(__xludf.DUMMYFUNCTION("""COMPUTED_VALUE"""),0.0) -> 0 | AA41: =IFERROR(__xludf.DUMMYFUNCTION("""COMPUTED_VALUE"""),"") | AB41: =IFERROR(__xludf.DUMMYFUNCTION("""COMPUTED_VALUE"""),12.96) -> 12.96 | AC41: =IFERROR(__xludf.DUMMYFUNCTION("""COMPUTED_VALUE"""),366.65) -> 366.65 | AD41: =IFERROR(__xludf.DUMMYFUNCTION("""COMPUTED_VALUE"""),0.03534706123005592) -> 0.035347061 | AE41: =IFERROR(__xludf.DUMMYFUNCTION("""COMPUTED_VALUE"""),126.86) -> 126.86 | AF41: =IFERROR(__xludf.DUMMYFUNCTION("""COMPUTED_VALUE"""),566.68) -> 566.68 | AG41: =IFERROR(__xludf.DUMMYFUNCTION("""COMPUTED_VALUE"""),0.22386532081598082) -> 0.22386532 | AH41: =IFERROR(__xludf.DUMMYFUNCTION("""COMPUTED_VALUE"""),289.99) -> 289.99 | AI41: =IFERROR(__xludf.DUMMYFUNCTION("""COMPUTED_VALUE"""),796.68) -> 796.68 | AJ41: =IFERROR(__xludf.DUMMYFUNCTION("""COMPUTED_VALUE"""),0.3639980920821409) -> 0.36399809 | AK41: =IFERROR(__xludf.DUMMYFUNCTION("""COMPUTED_VALUE"""),436.81) -> 436.81 | AL41: =IFERROR(__xludf.DUMMYFUNCTION("""COMPUTED_VALUE"""),1730.0099999999998) -> 1730.01 | AM41: =IFERROR(__xludf.DUMMYFUNCTION("""COMPUTED_VALUE"""),0.25248987000075146) -> 0.25248987 | AN41: =IFERROR(__xludf.DUMMYFUNCTION("""COMPUTED_VALUE"""),0.0) -> 0 | AO41: =IFERROR(__xludf.DUMMYFUNCTION("""COMPUTED_VALUE"""),0.0) -> 0 | AP41: =IFERROR(__xludf.DUMMYFUNCTION("""COMPUTED_VALUE"""),"") | AQ41: =IFERROR(__xludf.DUMMYFUNCTION("""COMPUTED_VALUE"""),0.0) -> 0 | AR41: =IFERROR(__xludf.DUMMYFUNCTION("""COMPUTED_VALUE"""),0.0) -> 0 | AS41: =IFERROR(__xludf.DUMMYFUNCTION("""COMPUTED_VALUE"""),"") | AT41: =IFERROR(__xludf.DUMMYFUNCTION("""COMPUTED_VALUE"""),0.0) -> 0 | AU41: =IFERROR(__xludf.DUMMYFUNCTION("""COMPUTED_VALUE"""),0.0) -> 0 | AV41: =IFERROR(__xludf.DUMMYFUNCTION("""COMPUTED_VALUE"""),"") | AW41: =IFERROR(__xludf.DUMMYFUNCTION("""COMPUTED_VALUE"""),0.0) -> 0 | AX41: =IFERROR(__xludf.DUMMYFUNCTION("""COMPUTED_VALUE"""),0.0) -> 0 | AY41: =IFERROR(__xludf.DUMMYFUNCTION("""COMPUTED_VALUE"""),"") | AZ41: =IFERROR(__xludf.DUMMYFUNCTION("""COMPUTED_VALUE"""),0.0) -> 0 | BA41: =IFERROR(__xludf.DUMMYFUNCTION("""COMPUTED_VALUE"""),0.0) -> 0 | BB41: =IFERROR(__xludf.DUMMYFUNCTION("""COMPUTED_VALUE"""),"")
A42: =IFERROR(__xludf.DUMMYFUNCTION("""COMPUTED_VALUE"""),"65dcd9bc019929778f07c73f") -> 65dcd9bc019929778f07c73f | B42: =IFERROR(__xludf.DUMMYFUNCTION("""COMPUTED_VALUE"""),"Dacas Distri Mexico") -> Dacas Distri Mexico | C42: =IFERROR(__xludf.DUMMYFUNCTION("""COMPUTED_VALUE"""),"joaquin.flores@al-enterprise.com") -> joaquin.flores@al-enterprise.com | D42: =IFERROR(__xludf.DUMMYFUNCTION("""COMPUTED_VALUE"""),"americas") -> americas | E42: =IFERROR(__xludf.DUMMYFUNCTION("""COMPUTED_VALUE"""),"MX") -> MX | F42: =IFERROR(__xludf.DUMMYFUNCTION("""COMPUTED_VALUE"""),"distributor") -> distributor | G42: =IFERROR(__xludf.DUMMYFUNCTION("""COMPUTED_VALUE"""),0.0) -> 0 | H42: =IFERROR(__xludf.DUMMYFUNCTION("""COMPUTED_VALUE"""),1.0) -> 1 | I42: =IFERROR(__xludf.DUMMYFUNCTION("""COMPUTED_VALUE"""),0.0) -> 0 | J42: =IFERROR(__xludf.DUMMYFUNCTION("""COMPUTED_VALUE"""),83.6) -> 83.6 | K42: =IFERROR(__xludf.DUMMYFUNCTION("""COMPUTED_VALUE"""),505.0) -> 505 | L42: =IFERROR(__xludf.DUMMYFUNCTION("""COMPUTED_VALUE"""),0.16554455445544553) -> 0.16554455 | M42: =IFERROR(__xludf.DUMMYFUNCTION("""COMPUTED_VALUE"""),15.0) -> 15 | N42: =IFERROR(__xludf.DUMMYFUNCTION("""COMPUTED_VALUE"""),0.0) -> 0 | O42: =IFERROR(__xludf.DUMMYFUNCTION("""COMPUTED_VALUE"""),"") | P42: =IFERROR(__xludf.DUMMYFUNCTION("""COMPUTED_VALUE"""),0.0) -> 0 | Q42: =IFERROR(__xludf.DUMMYFUNCTION("""COMPUTED_VALUE"""),1.0) -> 1 | R42: =IFERROR(__xludf.DUMMYFUNCTION("""COMPUTED_VALUE"""),0.0) -> 0 | S42: =IFERROR(__xludf.DUMMYFUNCTION("""COMPUTED_VALUE"""),0.0) -> 0 | T42: =IFERROR(__xludf.DUMMYFUNCTION("""COMPUTED_VALUE"""),1.0) -> 1 | U42: =IFERROR(__xludf.DUMMYFUNCTION("""COMPUTED_VALUE"""),0.0) -> 0 | V42: =IFERROR(__xludf.DUMMYFUNCTION("""COMPUTED_VALUE"""),0.0) -> 0 | W42: =IFERROR(__xludf.DUMMYFUNCTION("""COMPUTED_VALUE"""),1.0) -> 1 | X42: =IFERROR(__xludf.DUMMYFUNCTION("""COMPUTED_VALUE"""),0.0) -> 0 | Y42: =IFERROR(__xludf.DUMMYFUNCTION("""COMPUTED_VALUE"""),1.89) -> 1.89 | Z42: =IFERROR(__xludf.DUMMYFUNCTION("""COMPUTED_VALUE"""),0.0) -> 0 | AA42: =IFERROR(__xludf.DUMMYFUNCTION("""COMPUTED_VALUE"""),"") | AB42: =IFERROR(__xludf.DUMMYFUNCTION("""COMPUTED_VALUE"""),1.89) -> 1.89 | AC42: =IFERROR(__xludf.DUMMYFUNCTION("""COMPUTED_VALUE"""),333.35) -> 333.35 | AD42: =IFERROR(__xludf.DUMMYFUNCTION("""COMPUTED_VALUE"""),0.005669716514174291) -> 0.0056697165 | AE42: =IFERROR(__xludf.DUMMYFUNCTION("""COMPUTED_VALUE"""),0.0) -> 0 | AF42: =IFERROR(__xludf.DUMMYFUNCTION("""COMPUTED_VALUE"""),400.0) -> 400 | AG42: =IFERROR(__xludf.DUMMYFUNCTION("""COMPUTED_VALUE"""),0.0) -> 0 | AH42: =IFERROR(__xludf.DUMMYFUNCTION("""COMPUTED_VALUE"""),26.19) -> 26.19 | AI42: =IFERROR(__xludf.DUMMYFUNCTION("""COMPUTED_VALUE"""),700.0) -> 700 | AJ42: =IFERROR(__xludf.DUMMYFUNCTION("""COMPUTED_VALUE"""),0.03741428571428572) -> 0.037414286 | AK42: =IFERROR(__xludf.DUMMYFUNCTION("""COMPUTED_VALUE"""),29.970000000000002) -> 29.97 | AL42: =IFERROR(__xludf.DUMMYFUNCTION("""COMPUTED_VALUE"""),1433.35) -> 1433.35 | AM42: =IFERROR(__xludf.DUMMYFUNCTION("""COMPUTED_VALUE"""),0.020909059196986084) -> 0.020909059 | AN42: =IFERROR(__xludf.DUMMYFUNCTION("""COMPUTED_VALUE"""),21.79) -> 21.79 | AO42: =IFERROR(__xludf.DUMMYFUNCTION("""COMPUTED_VALUE"""),0.0) -> 0 | AP42: =IFERROR(__xludf.DUMMYFUNCTION("""COMPUTED_VALUE"""),"") | AQ42: =IFERROR(__xludf.DUMMYFUNCTION("""COMPUTED_VALUE"""),4.13) -> 4.13 | AR42: =IFERROR(__xludf.DUMMYFUNCTION("""COMPUTED_VALUE"""),0.0) -> 0 | AS42: =IFERROR(__xludf.DUMMYFUNCTION("""COMPUTED_VALUE"""),"") | AT42: =IFERROR(__xludf.DUMMYFUNCTION("""COMPUTED_VALUE"""),0.0) -> 0 | AU42: =IFERROR(__xludf.DUMMYFUNCTION("""COMPUTED_VALUE"""),0.0) -> 0 | AV42: =IFERROR(__xludf.DUMMYFUNCTION("""COMPUTED_VALUE"""),"") | AW42: =IFERROR(__xludf.DUMMYFUNCTION("""COMPUTED_VALUE"""),0.0) -> 0 | AX42: =IFERROR(__xludf.DUMMYFUNCTION("""COMPUTED_VALUE"""),0.0) -> 0 | AY42: =IFERROR(__xludf.DUMMYFUNCTION("""COMPUTED_VALUE"""),"") | AZ42: =IFERROR(__xludf.DUMMYFUNCTION("""COMPUTED_VALUE"""),25.919999999999998) -> 25.92 | BA42: =IFERROR(__xludf.DUMMYFUNCTION("""COMPUTED_VALUE"""),0.0) -> 0 | BB42: =IFERROR(__xludf.DUMMYFUNCTION("""COMPUTED_VALUE"""),"")
A43: =IFERROR(__xludf.DUMMYFUNCTION("""COMPUTED_VALUE"""),"63ced84dc5c820531c26969e") -> 63ced84dc5c820531c26969e | B43: =IFERROR(__xludf.DUMMYFUNCTION("""COMPUTED_VALUE"""),"Dagostino Electronic Services, Inc.") -> Dagostino Electronic Services, Inc. | C43: =IFERROR(__xludf.DUMMYFUNCTION("""COMPUTED_VALUE"""),"brendan.flaherty@al-enterprise.com, michael-j.francis@al-enterprise.com, tracy.dupree@al-enterprise.com, jon.taylor@al-enterprise.com") -> brendan.flaherty@al-enterprise.com, michael-j.francis@al-enterprise.com, tracy.dupree@al-enterprise.com, jon.taylor@al-enterprise.com | D43: =IFERROR(__xludf.DUMMYFUNCTION("""COMPUTED_VALUE"""),"americas") -> americas | E43: =IFERROR(__xludf.DUMMYFUNCTION("""COMPUTED_VALUE"""),"US") -> US | F43: =IFERROR(__xludf.DUMMYFUNCTION("""COMPUTED_VALUE"""),"expert_1000") -> expert_1000 | G43: =IFERROR(__xludf.DUMMYFUNCTION("""COMPUTED_VALUE"""),1.0) -> 1 | H43: =IFERROR(__xludf.DUMMYFUNCTION("""COMPUTED_VALUE"""),1.0) -> 1 | I43: =IFERROR(__xludf.DUMMYFUNCTION("""COMPUTED_VALUE"""),1.0) -> 1 | J43: =IFERROR(__xludf.DUMMYFUNCTION("""COMPUTED_VALUE"""),158.29) -> 158.29 | K43: =IFERROR(__xludf.DUMMYFUNCTION("""COMPUTED_VALUE"""),1453.69) -> 1453.69 | L43: =IFERROR(__xludf.DUMMYFUNCTION("""COMPUTED_VALUE"""),0.10888841499907131) -> 0.10888842 | M43: =IFERROR(__xludf.DUMMYFUNCTION("""COMPUTED_VALUE"""),31.0) -> 31 | N43: =IFERROR(__xludf.DUMMYFUNCTION("""COMPUTED_VALUE"""),52.0) -> 52 | O43: =IFERROR(__xludf.DUMMYFUNCTION("""COMPUTED_VALUE"""),0.5961538461538461) -> 0.59615385 | P43: =IFERROR(__xludf.DUMMYFUNCTION("""COMPUTED_VALUE"""),1.0) -> 1 | Q43: =IFERROR(__xludf.DUMMYFUNCTION("""COMPUTED_VALUE"""),1.0) -> 1 | R43: =IFERROR(__xludf.DUMMYFUNCTION("""COMPUTED_VALUE"""),1.0) -> 1 | S43: =IFERROR(__xludf.DUMMYFUNCTION("""COMPUTED_VALUE"""),1.0) -> 1 | T43: =IFERROR(__xludf.DUMMYFUNCTION("""COMPUTED_VALUE"""),1.0) -> 1 | U43: =IFERROR(__xludf.DUMMYFUNCTION("""COMPUTED_VALUE"""),1.0) -> 1 | V43: =IFERROR(__xludf.DUMMYFUNCTION("""COMPUTED_VALUE"""),0.0) -> 0 | W43: =IFERROR(__xludf.DUMMYFUNCTION("""COMPUTED_VALUE"""),1.0) -> 1 | X43: =IFERROR(__xludf.DUMMYFUNCTION("""COMPUTED_VALUE"""),0.0) -> 0 | Y43: =IFERROR(__xludf.DUMMYFUNCTION("""COMPUTED_VALUE"""),0.33) -> 0.33 | Z43: =IFERROR(__xludf.DUMMYFUNCTION("""COMPUTED_VALUE"""),0.0) -> 0 | AA43: =IFERROR(__xludf.DUMMYFUNCTION("""COMPUTED_VALUE"""),"") | AB43: =IFERROR(__xludf.DUMMYFUNCTION("""COMPUTED_VALUE"""),0.64) -> 0.64 | AC43: =IFERROR(__xludf.DUMMYFUNCTION("""COMPUTED_VALUE"""),969.33) -> 969.33 | AD43: =IFERROR(__xludf.DUMMYFUNCTION("""COMPUTED_VALUE"""),6.602498633076454E-4) -> 0.00066024986 | AE43: =IFERROR(__xludf.DUMMYFUNCTION("""COMPUTED_VALUE"""),487.98) -> 487.98 | AF43: =IFERROR(__xludf.DUMMYFUNCTION("""COMPUTED_VALUE"""),1453.32) -> 1453.32 | AG43: =IFERROR(__xludf.DUMMYFUNCTION("""COMPUTED_VALUE"""),0.33576913549665593) -> 0.33576914 | AH43: =IFERROR(__xludf.DUMMYFUNCTION("""COMPUTED_VALUE"""),131.09) -> 131.09 | AI43: =IFERROR(__xludf.DUMMYFUNCTION("""COMPUTED_VALUE"""),1453.67) -> 1453.67 | AJ43: =IFERROR(__xludf.DUMMYFUNCTION("""COMPUTED_VALUE"""),0.09017865127573658) -> 0.090178651 | AK43: =IFERROR(__xludf.DUMMYFUNCTION("""COMPUTED_VALUE"""),620.0400000000001) -> 620.04 | AL43: =IFERROR(__xludf.DUMMYFUNCTION("""COMPUTED_VALUE"""),3876.32) -> 3876.32 | AM43: =IFERROR(__xludf.DUMMYFUNCTION("""COMPUTED_VALUE"""),0.1599558343996368) -> 0.15995583 | AN43: =IFERROR(__xludf.DUMMYFUNCTION("""COMPUTED_VALUE"""),349.59) -> 349.59 | AO43: =IFERROR(__xludf.DUMMYFUNCTION("""COMPUTED_VALUE"""),0.0) -> 0 | AP43: =IFERROR(__xludf.DUMMYFUNCTION("""COMPUTED_VALUE"""),"") | AQ43: =IFERROR(__xludf.DUMMYFUNCTION("""COMPUTED_VALUE"""),0.0) -> 0 | AR43: =IFERROR(__xludf.DUMMYFUNCTION("""COMPUTED_VALUE"""),0.0) -> 0 | AS43: =IFERROR(__xludf.DUMMYFUNCTION("""COMPUTED_VALUE"""),"") | AT43: =IFERROR(__xludf.DUMMYFUNCTION("""COMPUTED_VALUE"""),0.0) -> 0 | AU43: =IFERROR(__xludf.DUMMYFUNCTION("""COMPUTED_VALUE"""),0.0) -> 0 | AV43: =IFERROR(__xludf.DUMMYFUNCTION("""COMPUTED_VALUE"""),"") | AW43: =IFERROR(__xludf.DUMMYFUNCTION("""COMPUTED_VALUE"""),0.0) -> 0 | AX43: =IFERROR(__xludf.DUMMYFUNCTION("""COMPUTED_VALUE"""),0.0) -> 0 | AY43: =IFERROR(__xludf.DUMMYFUNCTION("""COMPUTED_VALUE"""),"") | AZ43: =IFERROR(__xludf.DUMMYFUNCTION("""COMPUTED_VALUE"""),349.59) -> 349.59 | BA43: =IFERROR(__xludf.DUMMYFUNCTION("""COMPUTED_VALUE"""),0.0) -> 0 | BB43: =IFERROR(__xludf.DUMMYFUNCTION("""COMPUTED_VALUE"""),"")
A44: =IFERROR(__xludf.DUMMYFUNCTION("""COMPUTED_VALUE"""),"679366fcb35503f3000f3c14") -> 679366fcb35503f3000f3c14 | B44: =IFERROR(__xludf.DUMMYFUNCTION("""COMPUTED_VALUE"""),"DATAGROUP Stuttgart GmbH") -> DATAGROUP Stuttgart GmbH | C44: =IFERROR(__xludf.DUMMYFUNCTION("""COMPUTED_VALUE"""),"robert.weinberger@al-enterprise.com") -> robert.weinberger@al-enterprise.com | D44: =IFERROR(__xludf.DUMMYFUNCTION("""COMPUTED_VALUE"""),"germany") -> germany | E44: =IFERROR(__xludf.DUMMYFUNCTION("""COMPUTED_VALUE"""),"DE") -> DE | F44: =IFERROR(__xludf.DUMMYFUNCTION("""COMPUTED_VALUE"""),"expert_200") -> expert_200 | G44: =IFERROR(__xludf.DUMMYFUNCTION("""COMPUTED_VALUE"""),0.0) -> 0 | H44: =IFERROR(__xludf.DUMMYFUNCTION("""COMPUTED_VALUE"""),1.0) -> 1 | I44: =IFERROR(__xludf.DUMMYFUNCTION("""COMPUTED_VALUE"""),0.0) -> 0 | J44: =IFERROR(__xludf.DUMMYFUNCTION("""COMPUTED_VALUE"""),0.0) -> 0 | K44: =IFERROR(__xludf.DUMMYFUNCTION("""COMPUTED_VALUE"""),0.0) -> 0 | L44: =IFERROR(__xludf.DUMMYFUNCTION("""COMPUTED_VALUE"""),"") | M44: =IFERROR(__xludf.DUMMYFUNCTION("""COMPUTED_VALUE"""),0.0) -> 0 | N44: =IFERROR(__xludf.DUMMYFUNCTION("""COMPUTED_VALUE"""),0.0) -> 0 | O44: =IFERROR(__xludf.DUMMYFUNCTION("""COMPUTED_VALUE"""),"") | P44: =IFERROR(__xludf.DUMMYFUNCTION("""COMPUTED_VALUE"""),0.0) -> 0 | Q44: =IFERROR(__xludf.DUMMYFUNCTION("""COMPUTED_VALUE"""),1.0) -> 1 | R44: =IFERROR(__xludf.DUMMYFUNCTION("""COMPUTED_VALUE"""),0.0) -> 0 | S44: =IFERROR(__xludf.DUMMYFUNCTION("""COMPUTED_VALUE"""),0.0) -> 0 | T44: =IFERROR(__xludf.DUMMYFUNCTION("""COMPUTED_VALUE"""),1.0) -> 1 | U44: =IFERROR(__xludf.DUMMYFUNCTION("""COMPUTED_VALUE"""),0.0) -> 0 | V44: =IFERROR(__xludf.DUMMYFUNCTION("""COMPUTED_VALUE"""),0.0) -> 0 | W44: =IFERROR(__xludf.DUMMYFUNCTION("""COMPUTED_VALUE"""),1.0) -> 1 | X44: =IFERROR(__xludf.DUMMYFUNCTION("""COMPUTED_VALUE"""),0.0) -> 0 | Y44: =IFERROR(__xludf.DUMMYFUNCTION("""COMPUTED_VALUE"""),0.0) -> 0 | Z44: =IFERROR(__xludf.DUMMYFUNCTION("""COMPUTED_VALUE"""),0.0) -> 0 | AA44: =IFERROR(__xludf.DUMMYFUNCTION("""COMPUTED_VALUE"""),"") | AB44: =IFERROR(__xludf.DUMMYFUNCTION("""COMPUTED_VALUE"""),0.0) -> 0 | AC44: =IFERROR(__xludf.DUMMYFUNCTION("""COMPUTED_VALUE"""),0.0) -> 0 | AD44: =IFERROR(__xludf.DUMMYFUNCTION("""COMPUTED_VALUE"""),"") | AE44: =IFERROR(__xludf.DUMMYFUNCTION("""COMPUTED_VALUE"""),0.0) -> 0 | AF44: =IFERROR(__xludf.DUMMYFUNCTION("""COMPUTED_VALUE"""),0.0) -> 0 | AG44: =IFERROR(__xludf.DUMMYFUNCTION("""COMPUTED_VALUE"""),"") | AH44: =IFERROR(__xludf.DUMMYFUNCTION("""COMPUTED_VALUE"""),0.0) -> 0 | AI44: =IFERROR(__xludf.DUMMYFUNCTION("""COMPUTED_VALUE"""),0.0) -> 0 | AJ44: =IFERROR(__xludf.DUMMYFUNCTION("""COMPUTED_VALUE"""),"") | AK44: =IFERROR(__xludf.DUMMYFUNCTION("""COMPUTED_VALUE"""),0.0) -> 0 | AL44: =IFERROR(__xludf.DUMMYFUNCTION("""COMPUTED_VALUE"""),0.0) -> 0 | AM44: =IFERROR(__xludf.DUMMYFUNCTION("""COMPUTED_VALUE"""),"") | AN44: =IFERROR(__xludf.DUMMYFUNCTION("""COMPUTED_VALUE"""),0.0) -> 0 | AO44: =IFERROR(__xludf.DUMMYFUNCTION("""COMPUTED_VALUE"""),0.0) -> 0 | AP44: =IFERROR(__xludf.DUMMYFUNCTION("""COMPUTED_VALUE"""),"") | AQ44: =IFERROR(__xludf.DUMMYFUNCTION("""COMPUTED_VALUE"""),0.0) -> 0 | AR44: =IFERROR(__xludf.DUMMYFUNCTION("""COMPUTED_VALUE"""),0.0) -> 0 | AS44: =IFERROR(__xludf.DUMMYFUNCTION("""COMPUTED_VALUE"""),"") | AT44: =IFERROR(__xludf.DUMMYFUNCTION("""COMPUTED_VALUE"""),0.0) -> 0 | AU44: =IFERROR(__xludf.DUMMYFUNCTION("""COMPUTED_VALUE"""),0.0) -> 0 | AV44: =IFERROR(__xludf.DUMMYFUNCTION("""COMPUTED_VALUE"""),"") | AW44: =IFERROR(__xludf.DUMMYFUNCTION("""COMPUTED_VALUE"""),0.0) -> 0 | AX44: =IFERROR(__xludf.DUMMYFUNCTION("""COMPUTED_VALUE"""),0.0) -> 0 | AY44: =IFERROR(__xludf.DUMMYFUNCTION("""COMPUTED_VALUE"""),"") | AZ44: =IFERROR(__xludf.DUMMYFUNCTION("""COMPUTED_VALUE"""),0.0) -> 0 | BA44: =IFERROR(__xludf.DUMMYFUNCTION("""COMPUTED_VALUE"""),0.0) -> 0 | BB44: =IFERROR(__xludf.DUMMYFUNCTION("""COMPUTED_VALUE"""),"")
A45: =IFERROR(__xludf.DUMMYFUNCTION("""COMPUTED_VALUE"""),"63ef9d61384f27260c1bb24d") -> 63ef9d61384f27260c1bb24d | B45: =IFERROR(__xludf.DUMMYFUNCTION("""COMPUTED_VALUE"""),"Deloitte Consulting") -> Deloitte Consulting | C45: =IFERROR(__xludf.DUMMYFUNCTION("""COMPUTED_VALUE"""),"luigy.estevanell@al-enterprise.com") -> luigy.estevanell@al-enterprise.com | D45: =IFERROR(__xludf.DUMMYFUNCTION("""COMPUTED_VALUE"""),"americas") -> americas | E45: =IFERROR(__xludf.DUMMYFUNCTION("""COMPUTED_VALUE"""),"US") -> US | F45: =IFERROR(__xludf.DUMMYFUNCTION("""COMPUTED_VALUE"""),"expert_200") -> expert_200 | G45: =IFERROR(__xludf.DUMMYFUNCTION("""COMPUTED_VALUE"""),0.0) -> 0 | H45: =IFERROR(__xludf.DUMMYFUNCTION("""COMPUTED_VALUE"""),1.0) -> 1 | I45: =IFERROR(__xludf.DUMMYFUNCTION("""COMPUTED_VALUE"""),0.0) -> 0 | J45: =IFERROR(__xludf.DUMMYFUNCTION("""COMPUTED_VALUE"""),1986.62) -> 1986.62 | K45: =IFERROR(__xludf.DUMMYFUNCTION("""COMPUTED_VALUE"""),0.0) -> 0 | L45: =IFERROR(__xludf.DUMMYFUNCTION("""COMPUTED_VALUE"""),"") | M45: =IFERROR(__xludf.DUMMYFUNCTION("""COMPUTED_VALUE"""),0.0) -> 0 | N45: =IFERROR(__xludf.DUMMYFUNCTION("""COMPUTED_VALUE"""),0.0) -> 0 | O45: =IFERROR(__xludf.DUMMYFUNCTION("""COMPUTED_VALUE"""),"") | P45: =IFERROR(__xludf.DUMMYFUNCTION("""COMPUTED_VALUE"""),0.0) -> 0 | Q45: =IFERROR(__xludf.DUMMYFUNCTION("""COMPUTED_VALUE"""),1.0) -> 1 | R45: =IFERROR(__xludf.DUMMYFUNCTION("""COMPUTED_VALUE"""),0.0) -> 0 | S45: =IFERROR(__xludf.DUMMYFUNCTION("""COMPUTED_VALUE"""),0.0) -> 0 | T45: =IFERROR(__xludf.DUMMYFUNCTION("""COMPUTED_VALUE"""),1.0) -> 1 | U45: =IFERROR(__xludf.DUMMYFUNCTION("""COMPUTED_VALUE"""),0.0) -> 0 | V45: =IFERROR(__xludf.DUMMYFUNCTION("""COMPUTED_VALUE"""),0.0) -> 0 | W45: =IFERROR(__xludf.DUMMYFUNCTION("""COMPUTED_VALUE"""),1.0) -> 1 | X45: =IFERROR(__xludf.DUMMYFUNCTION("""COMPUTED_VALUE"""),0.0) -> 0 | Y45: =IFERROR(__xludf.DUMMYFUNCTION("""COMPUTED_VALUE"""),183.57) -> 183.57 | Z45: =IFERROR(__xludf.DUMMYFUNCTION("""COMPUTED_VALUE"""),0.0) -> 0 | AA45: =IFERROR(__xludf.DUMMYFUNCTION("""COMPUTED_VALUE"""),"") | AB45: =IFERROR(__xludf.DUMMYFUNCTION("""COMPUTED_VALUE"""),3253.86) -> 3253.86 | AC45: =IFERROR(__xludf.DUMMYFUNCTION("""COMPUTED_VALUE"""),0.0) -> 0 | AD45: =IFERROR(__xludf.DUMMYFUNCTION("""COMPUTED_VALUE"""),"") | AE45: =IFERROR(__xludf.DUMMYFUNCTION("""COMPUTED_VALUE"""),458.28) -> 458.28 | AF45: =IFERROR(__xludf.DUMMYFUNCTION("""COMPUTED_VALUE"""),0.0) -> 0 | AG45: =IFERROR(__xludf.DUMMYFUNCTION("""COMPUTED_VALUE"""),"") | AH45: =IFERROR(__xludf.DUMMYFUNCTION("""COMPUTED_VALUE"""),350.62) -> 350.62 | AI45: =IFERROR(__xludf.DUMMYFUNCTION("""COMPUTED_VALUE"""),0.0) -> 0 | AJ45: =IFERROR(__xludf.DUMMYFUNCTION("""COMPUTED_VALUE"""),"") | AK45: =IFERROR(__xludf.DUMMYFUNCTION("""COMPUTED_VALUE"""),4246.33) -> 4246.33 | AL45: =IFERROR(__xludf.DUMMYFUNCTION("""COMPUTED_VALUE"""),0.0) -> 0 | AM45: =IFERROR(__xludf.DUMMYFUNCTION("""COMPUTED_VALUE"""),"") | AN45: =IFERROR(__xludf.DUMMYFUNCTION("""COMPUTED_VALUE"""),0.0) -> 0 | AO45: =IFERROR(__xludf.DUMMYFUNCTION("""COMPUTED_VALUE"""),0.0) -> 0 | AP45: =IFERROR(__xludf.DUMMYFUNCTION("""COMPUTED_VALUE"""),"") | AQ45: =IFERROR(__xludf.DUMMYFUNCTION("""COMPUTED_VALUE"""),0.0) -> 0 | AR45: =IFERROR(__xludf.DUMMYFUNCTION("""COMPUTED_VALUE"""),0.0) -> 0 | AS45: =IFERROR(__xludf.DUMMYFUNCTION("""COMPUTED_VALUE"""),"") | AT45: =IFERROR(__xludf.DUMMYFUNCTION("""COMPUTED_VALUE"""),0.0) -> 0 | AU45: =IFERROR(__xludf.DUMMYFUNCTION("""COMPUTED_VALUE"""),0.0) -> 0 | AV45: =IFERROR(__xludf.DUMMYFUNCTION("""COMPUTED_VALUE"""),"") | AW45: =IFERROR(__xludf.DUMMYFUNCTION("""COMPUTED_VALUE"""),0.0) -> 0 | AX45: =IFERROR(__xludf.DUMMYFUNCTION("""COMPUTED_VALUE"""),0.0) -> 0 | AY45: =IFERROR(__xludf.DUMMYFUNCTION("""COMPUTED_VALUE"""),"") | AZ45: =IFERROR(__xludf.DUMMYFUNCTION("""COMPUTED_VALUE"""),0.0) -> 0 | BA45: =IFERROR(__xludf.DUMMYFUNCTION("""COMPUTED_VALUE"""),0.0) -> 0 | BB45: =IFERROR(__xludf.DUMMYFUNCTION("""COMPUTED_VALUE"""),"")
